Workbook

Sheet Indicators - Classified
A1: # | B1: Mexicali indicator | C1: Domain | D1: Domain | L1: Subdomain | M1: Indicator / Category | N1: Subject | O1: Lens / Enfoque | V1: Reason this matters (draft) | Y1: Can we calculate this? Do we have data for Mexicali? (0: No / 1: Yes / 2: TBD) | Z1: What is the most pragmatic way of measuring it? | AA1: Article # | AB1: Excluded indicator | AC1: Methods sub-indices/measures | AD1: Potential data sources | AE1: Notes | AF1: Doubts/Questions
A2: Unique ID | B2: =COUNTA(_xlfn.UNIQUE(B3:B677))-1 -> 82 | D2: Safety | E2: Built Environment | F2: Ambient Environment | G2: Housing | H2: Economic Development | I2: Social Infrastructure | J2: Sociodemographics | K2: Mobility & Transport | L2: =COUNTA(_xlfn.UNIQUE(L3:L677))-1 -> 18 | M2: =COUNTA(_xlfn.UNIQUE(M3:M677))-1 -> 30 | N2: =COUNTA(_xlfn.UNIQUE(N3:N677))-1 & " unique of " &COUNTA(N3:N677) -> 80 unique of 81 | O2: =COUNTA(_xlfn.UNIQUE(O3:O677))-1 -> 10 | P2: Proximity | Q2: Accessibility (threshold) | R2: Quantity (threshold) | S2: Density (threshold) | T2: Diversity | U2: Quality | W2: Citation(s) | X2: Effect size (signed measure and confidence interval/uncertainty if stated) | Y2: =COUNTA(_xlfn.UNIQUE(Y3:Y677))-1 -> 2 | Z2: =COUNTA(_xlfn.UNIQUE(Z3:Z677))-1 -> 5 | AA2: =COUNTA(_xlfn.UNIQUE(AA3:AA677))-1 -> 25 | AB2: =COUNTIF(AB3:AB84,"<>") & " (Number indicates duplicated indicator #)" -> 0 (Number indicates duplicated indicator #) | AC2: =COUNTA(_xlfn.UNIQUE(AC3:AC677))-1 -> 32 | AD2: =COUNTA(_xlfn.UNIQUE(AD3:AD677))-1 -> 19 | AE2: =COUNTA(_xlfn.UNIQUE(AE3:AE677))-1 -> 18 | AF2: =COUNTA(_xlfn.UNIQUE(AF3:AF677))-1 -> 28
A3: 289 | B3: Housing affordability | C3: Housing | G3: x | M3: Affordable Housing | N3: Housing affordability | O3: Accessibility; Equity 27: Quantity | Q3: x | R3: x | V3: Affordable housing is essential for liveability and health as high housing costs limit resources for other social determinants of health like food and healthcare. | W3: Saitluanga, 2014, 'Spatial pattern of urban livability in Himalayan region: a case of Aizawl City'; Porio, 2015, 'Sustainable development goals and quality of life targets: insights from metro Manila' | X3: Association reported; no effect size provided. | AA3: 22; 27 | AC3: 27: ['median housing cost relative to income'] 22: ['Percentage of land being used for informal housing'] | AD3: "con la ENIGH se puede calcular gasto de alquiler entre ingresos" https://www.inegi.org.mx/programas/enigh/nc/2024/ "Encuesta Nacional de Vivienda (ENVI) 2020" https://www.inegi.org.mx/programas/envi/2020/ " Tipología de vivienda (2024)" from the Actualizaciones del territorio maps https://www.mexicali.gob.mx/sitioimip/geovisor | AE3: ER: Data will only be available at the city-level from the "Encuesta Nacional de Vivienda (ENVI) 2020" https://www.inegi.org.mx/programas/envi/2020/ We could also use the categories from the " Tipología de vivienda (2024)" from the Actualizaciones del territorio maps https://www.mexicali.gob.mx/sitioimip/geovisor
A4: 290 | B4: =N4 -> Land and house price | C4: Housing | G4: x | M4: Affordable Housing | N4: Land and house price | O4: Quantity; Equity | R4: x | V4: High housing and land prices are linked to reduced affordability and financial stress, which can negatively impact residents' overall quality of life and residential stability. | W4: Liu et al., 2020, 'Using multi-source data to assess livability in Hong Kong at the community-based level: A combined subjective-objective approach' | X4: Association reported; no effect size provided. | AA4: 16 | AC4: 16: ['Exploratory Factor Analysis', 'Standard Deviational Ellipse,', 'Hot Spot Analysis,', 'Network Analysis'] | AD4: "con la ENIGH se puede calcular gasto de alquiler entre ingresos" https://www.inegi.org.mx/programas/enigh/nc/2024/ "Encuesta Nacional de Vivienda (ENVI) 2020" https://www.inegi.org.mx/programas/envi/2020/ " Tipología de vivienda (2024)" from the Actualizaciones del territorio maps https://www.mexicali.gob.mx/sitioimip/geovisor | AE4: ER: Juan, el catastro tiene costo del lote y vivienda? https://tecmx.sharepoint.com/:f:/s/Mexicali-SIUM/IgCo34MzoO2pQ6n_8_fN7n7yAXbMN8SNG9AALvIBr0s7taI?e=R4YpGb https://tecmx.sharepoint.com/:f:/s/Mexicali-SIUM/IgCIU9bPtEF1RI3-GeohnPsyAV8qQj9UYPAZZ3rpy6S1RZE?e=mcIQXk | AF4: CH: To judge what is "high" and unaffordable may require some interpretation / guidance / use of a threshold (in Australia we us a 30:40 measure of housing affordability stress https://www.ahuri.edu.au/analysis/brief/understanding-3040-indicator-housing-affordability-stress
A5: 293 | B5: =N5 -> Number of days with good air quality | C5: Ambient Environment | F5: x | L5: Risks | M5: Air Quality | N5: Number of days with good air quality | O5: Quantity | R5: x | V5: The frequency of days with high-quality air is a fundamental indicator of urban environmental health and atmospheric safety for residents. | W5: Estoque et al., 2019, 'A review of quality of life (QOL) assessments and indicators: Towards a "QOL-Climate" assessment framework'; Liang et al., 2020, 'Assessment of the impact of climate change on cities livability in China' | X5: Liveability score: weighted indicator, no individual effect size reported | AA5: 3; 31 | AC5: 3: ['Entropy TOPSIS model', 'Tobit model'] 31: ['Grey relational degree', 'Entropy-TOPSIS model'] | AD5: Official Air Quality monitoring system: https://www.mexicali.gob.mx/portalmexicali/calidad-aire/indices?id=1 Review historial data from this source
A6: 292 | B6: =N6 -> Air quality | C6: Ambient Environment | F6: x | L6: Risks | M6: Air Quality | N6: Air quality | O6: Quality | U6: x | V6: Better air quality prioritizes physical health and promotes overall well-being by reducing exposure to harmful atmospheric pollutants. | W6: Wang et al., 2011, 'A Comparative Study of Beijing and Three Global Cities: A Perspective on Urban Livability'; Mahmud et al., 2020, 'Assessment of Groundwater Quality in Khulna City of Bangladesh in Terms of Water Quality Index for Drinking Purpose' | X6: Association reported; no effect size provided. | Y6: 2 | AA6: 18;22 | AC6: 1: ['Delphi', "Kendall's coefficient", "Cronbach's alpha value"] 6: ['Delphi Process', 'Analytic Hierarchy Process'] 18: ['Analytic Hierarchy Process (AHP)'] 22: ['N/A'] | AD6: Official Air Quality monitoring system: https://www.mexicali.gob.mx/portalmexicali/calidad-aire/indices?id=1 | AF6: ER: Too broad (should be defined by particles)?
A7: 8 | B7: =N7 -> Good air quality | C7: Ambient Environment | F7: x | L7: Risks | M7: Air Quality | N7: Good air quality | O7: Quality | U7: x | V7: Suitable air quality is a fundamental environmental requirement for reducing risks of respiratory and cardiovascular diseases in urban populations. | W7: Yang et al., 2021, 'Spatiotemporal trends and driving factors of urban livability in the Yangtze River Delta Agglomeration'; Zhu et al., 2021, 'Enhancing and promoting national environmental goals through local integrated coastal management initiatives and legislation' | X7: Association reported; no effect size provided. | AA7: 16 | AC7: ['Exploratory Factor Analysis', 'Standard Deviational Ellipse,', 'Hot Spot Analysis,', 'Network Analysis'] | AD7: Official Air Quality monitoring system: https://www.mexicali.gob.mx/portalmexicali/calidad-aire/indices?id=1
A8: 136 | B8: =N8 -> Annual average nitrogen dioxide (1-e6 mmol/m²) | C8: Ambient Environment | F8: x | L8: Risks | M8: Air Quality | N8: Annual average nitrogen dioxide (1-e6 mmol/m²) | O8: Quantity; Quality | R8: x | U8: x | V8: Nitrogen dioxide is identified as a major urban problem impacting health and wellbeing, with high concentrations linked to respiratory and cardiovascular issues. | W8: Lowe et al., 2015, 'Planning healthy, liveable and sustainable cities: how can indicators inform policy?'; Badland et al., 2014, 'Urban liveability: emerging lessons from Australia for exploring the potential for indicators to measure the social determinants of health' | X8: Association reported; no effect size provided. | Y8: 1 | AA8: 13 | AC8: ['Identification of measurable spatial indicators, how they can me calculated and monitored'] | AD8: Sentinel-5P NRTI NO2: Near Real-Time Nitrogen Dioxide (https://developers.google.com/earth-engine/datasets/catalog/COPERNICUS_S5P_NRTI_L3_NO2?hl=es-419)
A9: 173 | B9: =N9 -> Number of days PM 2.5 exceeds WHO standard (25 µg/m³) | C9: Ambient Environment | F9: x | L9: Risks | M9: Air Quality | N9: Number of days PM 2.5 exceeds WHO standard (25 µg/m³) | O9: Quantity | R9: x | V9: Monitoring PM2.5 levels relative to international WHO standards ensures that the city is tracking environmental risks that impact population cardiovascular and respiratory health. | W9: Lowe et al., 2015, 'Planning healthy, liveable and sustainable cities: how can indicators inform policy?'; Badland et al., 2014, 'Urban liveability: emerging lessons from Australia for exploring the potential for indicators to measure the social determinants of health' | X9: Association reported; no effect size provided. | AA9: 13 | AC9: ['Identification of measurable spatial indicators, how they can me calculated and monitored'] | AD9: Official Air Quality monitoring system: https://www.mexicali.gob.mx/portalmexicali/calidad-aire/indices?id=1 Review historial data from this source
A10: 252 | B10: =N10 -> Per capita SO2 emissions | C10: Ambient Environment | F10: x | L10: Risks | M10: Air Quality | N10: Per capita SO2 emissions | O10: Quantity | R10: x | V10: Lower levels of sulfur dioxide emissions signify reduced industrial pollution and progress toward carbon reduction, which are necessary for a sustainable living environment. | W10: Estoque et al., 2019, 'A review of quality of life (QOL) assessments and indicators: Towards a "QOL-Climate" assessment framework'; Liang et al., 2020, 'Assessment of the impact of climate change on cities livability in China' | X10: Liveability score: weighted indicator, no individual effect size reported | AA10: 31, 3 | AC10: 3: ['Entropy TOPSIS model', 'Tobit model'] 31:['Grey relational degree', 'Entropy-TOPSIS model'] | AE10: ER: Review if there is available data from SEMARNAT for: Bióxido de azufre (SO2) "We could potentially use data from: Registro de Emisiones y Transferencias de Contaminantes (RETC) 2004-2024 (https://sinat.semarnat.gob.mx:8443/retc/retc/index.php) or Taking Stock on industry (https://takingstock.cec.org/Map?IndustryLevel=4&Measure=3&MediaTypes=2&ReportType=1&ResultType=1&Years=2023)"
A11: 19 | B11: =N11 -> Building design | C11: Built Environment | E11: x | L11: Urban Morphology | M11: Buildings | N11: Building design | O11: Quantity | R11: x | V11: Building morphology and arrangement are critical for housing quality and social interaction, supporting healthy environments through improved urban ventilation. | W11: Chan & Liu, 2018, 'Effects of neighborhood building density, height, greenspace, and cleanliness on indoor environment and health'; Ramponi & Blocken, 2012, 'A computational study on the influence of urban morphology on wind-induced outdoor ventilation'; Yuan & Ng, 2012, 'Building porosity for better urban ventilation' | X11: Association reported; no effect size provided. | AA11: 23 | AC11: ['Design Analysis', 'Airflow simulations'] | AF11: I am not sure we can obtain data for this
A12: 22 | B12: =N12 -> Building height | C12: Built Environment | E12: x | L12: Urban Morphology | M12: Buildings | N12: Building height | O12: Quantity | R12: x | V12: Variation in building heights within a neighbourhood improves natural ventilation and passive pollutant dispersion while supporting residential privacy and safety. | W12: Ng, 2010, 'Designing high density cities for social & environmental sustainability'; An et al., 2019, 'Exploration of sustainable building morphologies for effective passive pollutant dispersion' | X12: Association reported; no effect size provided. | AA12: 23 | AC12: ['Design Analysis', 'Airflow simulations'] | AF12: ER: Can we calculate this with OpenBuildings?
A13: 1 | B13: =N13 -> Public services | C13: Social Infrastructure | I13: x | L13: Public Services | M13: Community Facilities | N13: Public services | O13: Accessibility | Q13: 500 | U13: x | V13: Access to telecommunication infrastructure and mobile network coverage is identified as a vital public service and a major interest for resident liveability. | W13: Atkisson & Hatcher, 2001, 'The compass index of sustainability'; Valentin & Spangenberg, 2000, 'A guide to community sustainability indicators' | X13: Liveability score: weighted indicator, no individual effect size reported | AA13: 8 | AC13: ['Hierarchical Modelling using Analytic Hierarchy Process (AHP)'] | AF13: CH: is there much variation in access to telecommunications infrastructure in mexicali?
A14: 46 | B14: ="Access to "&LOWER(N14) -> Access to community centres | C14: Social Infrastructure | I14: x | L14: Community, culture & leisure | M14: Community Facilities | N14: Community centres | O14: Accessibility | P14: x | Q14: 500 | R14: x | S14: x | V14: Multi-purpose community centres provide important opportunities for social interaction and community connection, which are vital for mental and social wellbeing. | W14: Saitluanga, 2014, 'Spatial pattern of urban livability in Himalayan region: a case of Aizawl City' | X14: Association reported; no effect size provided. | Y14: 1 | Z14: Destination analysis using GHSCI tools with permutations of: distance to closest, access within threshold(s), and where applicable count per sqkm and per 1,000 persons | AA14: 22 | AC14: ['Percentage of residents living < 400 m of community centre'] | AD14: OSM/ DENUE/IMIP
A15: 394 | B15: ="Access to "&LOWER(N15) -> Access to youth centres | C15: Social Infrastructure | I15: x | L15: Community, culture & leisure | M15: Community Facilities | N15: Youth centres | O15: Quantity | P15: x | Q15: 500 | R15: x | S15: x | V15: Access to youth centres provides essential social infrastructure that supports social cohesion, mental health, and community wellbeing for young residents. | W15: Lowe et al., 2015, 'Planning healthy, liveable and sustainable cities: how can indicators inform policy?' | X15: Association reported; no effect size provided. | Z15: Destination analysis using GHSCI tools with permutations of: distance to closest, access within threshold(s), and where applicable count per sqkm and per 1,000 persons | AA15: 13 | AC15: ['Identification of measurable spatial indicators, how they can me calculated and monitored'] | AD15: OSM/ DENUE/IMIP
A16: 11 | B16: ="Access to "&LOWER(N16) -> Access to bakery | C16: Economic Development | H16: x | I16: x | L16: Food Environment | M16: Convenience Destinations | N16: Bakery | O16: Quantity | P16: x | Q16: 500 | R16: x | S16: x | V16: The presence of local bakeries and food services contributes to the convenience of urban life and supports the everyday functional needs of residents. | W16: Ghasemi, 2024, 'Enhancing urban livability: Analyzing Tehran through equitable land use distribution' | X16: Association reported; no effect size provided. | Z16: Destination analysis using GHSCI tools with permutations of: distance to closest, access within threshold(s), and where applicable count per sqkm and per 1,000 persons | AA16: 16 | AC16: ['Exploratory Factor Analysis', 'Standard Deviational Ellipse,', 'Hot Spot Analysis,', 'Network Analysis'] | AD16: OSM/ DENUE/IMIP | AE16: CH: Probably should be grouped with other convenience destinations/ ER: Agreed, but particulary with those food-related, maybe part of a food environment comoposite index?
A17: 129 | B17: ="Access to "&LOWER(N17) -> Access to markets | C17: Economic Development | H17: x | I17: x | L17: Food Environment | M17: Convenience Destinations | N17: Markets | O17: Quantity | P17: x | Q17: 500 | R17: x | S17: x | V17: Local markets provide residents with access to fresh food and opportunities for economic activity and social interaction within their neighborhoods. | W17: Ghasemi, 2024, 'Enhancing urban livability: Analyzing Tehran through equitable land use distribution'; Yang et al., 2021, 'Spatiotemporal trends and driving factors of urban livability in the Yangtze River Delta Agglomeration' | X17: Association reported; no effect size provided. | Z17: Destination analysis using GHSCI tools with permutations of: distance to closest, access within threshold(s), and where applicable count per sqkm and per 1,000 persons | AA17: 16 | AC17: ['Exploratory Factor Analysis', 'Standard Deviational Ellipse,', 'Hot Spot Analysis,', 'Network Analysis'] | AD17: OSM/ DENUE/IMIP | AF17: ER: This one can be part of a composite sub-index
A18: 132 | B18: ="Access to "&LOWER(N18) -> Access to minimarts | C18: Economic Development | H18: x | L18: Food Environment | M18: Convenience Destinations | N18: Minimarts | O18: Quantity | P18: x | Q18: 500 | R18: x | S18: x | V18: The availability of minimarts is an indicator of local food access, supporting the convenient provision of daily necessities that shape urban life quality. | W18: Lowe et al., 2015, 'Planning healthy, liveable and sustainable cities: how can indicators inform policy?'; Alderton et al., 2019, 'What is the meaning of urban liveability for a city in a low-to-middle-income country? Contextualising liveability for Bangkok, Thailand' | X18: Association reported; no effect size provided. | Z18: Destination analysis using GHSCI tools with permutations of: distance to closest, access within threshold(s), and where applicable count per sqkm and per 1,000 persons | AA18: 13 | AC18: ['Identification of measurable spatial indicators, how they can me calculated and monitored'] | AD18: OSM/ DENUE/IMIP | AE18: CH: worth noting, minimarts may not be 'healthy food' necessarily (depends on context how its interpreted -- eg is OXXO a healthy food destination? maybe more associated with junk/convenience food?)
A19: 232 | B19: ="Access to "&LOWER(N19) -> Access to restaurants | C19: Economic Development | H19: x | I19: x | L19: Food Environment | M19: Convenience Destinations | N19: Restaurants | O19: Quantity | P19: x | Q19: 500 | R19: x | S19: x | V19: Restaurants contribute to the recreational diversity of urban districts, offering spaces for socialization and enhancing the vibrancy of the neighborhood. | W19: Ghasemi, 2024, 'Enhancing urban livability: Analyzing Tehran through equitable land use distribution'; Kang et al., 2022, 'Can tourism development make cities more livable? Investigating 40 cities in China' | X19: Association reported; no effect size provided. | Z19: Destination analysis using GHSCI tools with permutations of: distance to closest, access within threshold(s), and where applicable count per sqkm and per 1,000 persons | AA19: 16 | AC19: ['Exploratory Factor Analysis', 'Standard Deviational Ellipse,', 'Hot Spot Analysis,', 'Network Analysis'] | AD19: OSM/ DENUE
A20: 367 | B20: ="Access to "&LOWER(N20) -> Access to supermarket | C20: Economic Development | H20: x | I20: x | L20: Food Environment | M20: Convenience Destinations | N20: Supermarket | O20: Quantity | P20: x | Q20: 500 | R20: x | S20: x | V20: The availability of supermarkets is a indicator of the formal food environment that influences residents' ability to access varied and nutritional food options. | W20: Lowe et al., 2015, 'Planning healthy, liveable and sustainable cities: how can indicators inform policy?' | X20: Association reported; no effect size provided. | Z20: Destination analysis using GHSCI tools with permutations of: distance to closest, access within threshold(s), and where applicable count per sqkm and per 1,000 persons | AA20: 13 | AC20: ['Identification of measurable spatial indicators, how they can me calculated and monitored'] | AD20: OSM/ DENUE | AE20: Worth measuring access to supermarkets in a number of different ways (distance, count, within threshold) as required | AF20: ER: Review the composite hierarchy number
A21: 169 | B21: ="Access to "&LOWER(N21) -> Access to petrol station (>= 250m away) | C21: Economic Development | H21: x | L21: Resources | M21: Convenience Destinations | N21: Petrol station (>= 250m away) | O21: Proximity | P21: x | Q21: >=250m | R21: x | S21: x | V21: Living at a sufficient distance from gas stations improves residents' safety by reducing the risks of fire incidents and accidents associated with hazardous fuel locations. | W21: Basu et al., 2021, 'Urban Livability Index Assessment Based on Land-Use Changes in an Indian Medium-Sized City (Raiganj)' | X21: Association reported; no effect size provided. | Z21: Destination analysis using GHSCI tools with permutations of: distance to closest, access within threshold(s), and where applicable count per sqkm and per 1,000 persons | AA21: 18 | AC21: ['Analytic Hierarchy Process (AHP)'] | AD21: OSM/ DENUE/IMIP (abasto layer) https://www.mexicali.gob.mx/sitioimip/geovisor/geovisor/?url=act-terr&access_token= | AE21: CH: the evidence for this one might be complex -- I can imagine there might be a sweet spot --- yes, you don't want to be too close (how close is that, maybe that is our indicator --- not within XXX distance m, if we can link with citable evidence.) But the reality is people do drive, and need petrol or perhaps electrical charging; living too far from one could impact some aspects of life. Lets be guided by evidence here. Here's a good basis for an indicator: Petrol station within 250m is associated with increased relative risk of childhood leukemia. Another study: https://link.springer.com/article/10.1007/s00420-021-01767-y
A22: 296 | B22: =N22 -> Crime? | C22: Safety | D22: x | L22: Personal Safety | M22: Crime | N22: Crime? | O22: Accessibility | Q22: x | V22: Personal safety and the reduction of urban risk through protective infrastructure are identified as fundamental requirements for city liveability and resident well-being. | W22: Mercer, 2017, 'Quality of Living Survey'; Economist Intelligence Unit (EIU), 2012, 'Quality of Life Index' | X22: Liveability score: weighted indicator, no individual effect size reported | AA22: 8 | AC22: ['Hierarchical Modelling using Analytic Hierarchy Process (AHP)'] | AF22: CH: Only useful if it can be acquired with meaningful variation
A23: 121 | B23: ="Access to "&LOWER(N23) -> Access to libraries | C23: Social Infrastructure | I23: x | L23: Community, culture & leisure | M23: Culture & Leisure | N23: Libraries | O23: Proximity | P23: x | Q23: 1000 | R23: x | S23: x | V23: Easy access to cultural facilities like libraries is a key component of urban convenience, allowing residents to satisfy their fundamental information and educational requirements. | W23: Onnom et al., 2018, 'Development of a Liveable City Index (LCI) Using Multi Criteria Geospatial Modelling for Medium Class Cities in Developing Countries'; Liu et al., 2020, 'Using Multi-Source Data to Assess Livability in Hong Kong at the Community-Based Level: A Combined Subjective-Objective Approach' | X23: Association reported; no effect size provided. | Z23: Destination analysis using GHSCI tools with permutations of: distance to closest, access within threshold(s), and where applicable count per sqkm and per 1,000 persons | AA23: 18 | AC23: ['Analytic Hierarchy Process (AHP)'] | AD23: OSM/ DENUE/IMIP
A24: 228 | B24: ="Access to "&LOWER(N24) -> Access to religious buildings | C24: Social Infrastructure | I24: x | L24: Community, Culture & Leisure | M24: Culture & Leisure | N24: Religious buildings | O24: Proximity | P24: x | Q24: 500 | R24: x | S24: x | V24: Access to religious centres contributes to the amenity value of urban areas, providing social and cultural comfort that enhances human wellbeing. | W24: Rehdanz and Maddison, 2008, 'Local environmental quality and life-satisfaction in Germany' | X24: Association reported; no effect size provided. | Z24: Destination analysis using GHSCI tools with permutations of: distance to closest, access within threshold(s), and where applicable count per sqkm and per 1,000 persons | AA24: 20 | AC24: ['Proximity analysis following digitization and Euclidean distance computation'] | AD24: OSM/ DENUE/IMIP
A25: 58 | B25: ="Access to "&LOWER(N25) -> Access to cultural centers | C25: Social Infrastructure | I25: x | L25: Community, culture & leisure | M25: Culture & Leisure | N25: Cultural centers | O25: Quantity | P25: x | Q25: 1000 | R25: x | S25: x | V25: Cultural centers serve as important hubs for social and cultural activities that enhance community identity and promote the psychological well-being of residents. | W25: Kang et al., 2022, 'Can tourism development make cities more livable? Investigating 40 cities in China' | X25: Association reported; no effect size provided. | Z25: Destination analysis using GHSCI tools with permutations of: distance to closest, access within threshold(s), and where applicable count per sqkm and per 1,000 persons | AA25: 16 | AC25: ['Exploratory Factor Analysis', 'Standard Deviational Ellipse,', 'Hot Spot Analysis,', 'Network Analysis'] | AD25: OSM/ DENUE/IMIP | AF25: ER: This can be part of a "City amenities" composite index
A26: 134 | B26: ="Access to "&LOWER(N26) -> Access to museums | C26: Social Infrastructure | I26: x | L26: Community, culture & leisure | M26: Culture & Leisure | N26: Museums | O26: Quantity | P26: x | Q26: 1000 | R26: x | S26: x | V26: Museums provide important cultural infrastructure that supports social development, lifelong learning, and community social cohesion. | W26: Lowe et al., 2015, 'Planning healthy, liveable and sustainable cities: how can indicators inform policy?' | X26: Association reported; no effect size provided. | Z26: Destination analysis using GHSCI tools with permutations of: distance to closest, access within threshold(s), and where applicable count per sqkm and per 1,000 persons | AA26: 13 | AC26: ['Identification of measurable spatial indicators, how they can me calculated and monitored'] | AD26: OSM/ DENUE/IMIP | AF26: ER: This can be part of a "City amenities" composite index
A27: 61 | B27: =N27 -> Cycling infrastructure | C27: Mobility & Transport | K27: x | L27: Active Travel | M27: Cycling infrastructure | N27: Cycling infrastructure | O27: Accessibility | Q27: x | V27: Dedicated cycling infrastructure encourages sustainable, eco-friendly transportation and promotes physical health through regular active mobility. | W27: Mekuria et al., 2017, 'Improving Liveability Using Green and Active Modes'; Stehlin, 2014, 'Regulating inclusion: Spatial form, social process, and the normalization of cycling practice in the USA'; Ruggeri, 2013, 'From Transit Stop to Urbanity Node'; Whitney et al., 2020, 'Livable streets and global competitiveness: A survey of Mexico City' | X27: Compliance rate: 85.7% of evaluated liveability indices in the studied communities were related to public transport and green space availability. | AA27: 27 | AD27: IMIP: https://www.mexicali.gob.mx/sitioimip/geovisor/geovisor/?url=pimus&access_token= | AE27: CH: This sounds like a suite of indicators/ ER: Agreed, we could use the cycling indicators we have generating for this
A28: 338 | B28: =N28 -> Dwelling density | C28: Sociodemographics | J28: x | L28: Household | M28: Demographics | N28: Dwelling density | O28: Density | S28: x | V28: Appropriate household density within dwelling units is key to preventing the negative social and health consequences of urban overcrowding. | W28: Reynolds-Salmon et al., 2024, 'Does household size matter? Crowding and its effects on child development' | X28: Association reported; no effect size provided. | AA28: 16; 27; | AC28: 16: ['Exploratory Factor Analysis', 'Standard Deviational Ellipse,', 'Hot Spot Analysis,', 'Network Analysis'] 27: indicating the number of housing units per acre | AD28: INEGI Census
A29: 340 | B29: =N29 -> Population density | C29: Sociodemographics | J29: x | L29: City | M29: Demographics | N29: Population density | O29: Density | S29: x | V29: Excessive population density in fragile environments increases resource consumption and environmental stress, which can degrade the long-term liveability of a city. | W29: Chen et al., 2020, 'Response of resources and environment carrying capacity under the evolution of land use structure in Chongqing Section of the Three Gorges Reservoir Area'; Dong et al., 2021, 'The coupling coordinated relationship between new-type urbanization, eco-environment and its driving Mechanism: A case of Guanzhong, China' | X29: Urban liveability: β = -0.041 (p < 0.01), inverse association | AA29: 3; 8; 19; 27 | AC29: 3: ['Entropy TOPSIS model', 'Tobit model'] 8: ['Hierarchical Modelling using Analytic Hierarchy Process (AHP)'] 19: ['machine learning is integrated into semantic image segmentation technique to extract green pixels from the street view images using the scene parsing method; SVG', 'entropy index (relative percentage of various land-use types)'] 27: [GIS mapping] | AD29: INEGI Census | AG29: * Indicator categoy Demographics & subdomain city
A30: 112 | B30: =N30 -> Jobs | C30: Economic Development | H30: x | M30: Employment | N30: Jobs | O30: Quantity; Presence | R30: x | V30: Local employment opportunities allow residents to live and work within the same district, improving work-life balance and reducing the health burdens of long commutes. | W30: Saitluanga, 2014, 'Spatial pattern of urban livability in Himalayan region: a case of Aizawl City' | X30: Association reported; no effect size provided. | AA30: 22 | AC30: ['Percentage of residents living and working in the same district'] | AE30: Pues sí uno tiene El valor de fuerza laboral sería mejor con ese y El cociente sobre los que pueden trabajar
A31: 325 | B31: =N31 -> Fire incidence rate by population | C31: Ambient Environment; Safety | D31: x | F31: x | L31: Risks | M31: Fire | N31: Fire incidence rate by population | O31: Quantity | R31: x | V31: Fire safety, measured by the occurrence rate in the population, is a critical component of urban security, essential for protecting lives and property. | W31: Arpan & Joy, 2018, 'Livability assessment within a metropolis based on the impact of integrated urban geographic factors (IUGFs) on clustering urban centers of Kolkata'; Zhan et al., 2018, 'Assessment and determinants of satisfaction with urban livability in China' | X31: No health outcome assessed. | Y31: 2 | AA31: 17 | AC31: ['Not specified'] | AE31: ER: In Mexicali the Risk Atlas states that the most relevant fires are those related to industry, however, there is no data available for these.
A32: 71 | B32: =N32 -> Flooding | C32: Ambient Environment | F32: x | L32: Risks | M32: Flooding | N32: Flooding | O32: Accessibility | R32: x | V32: Mitigating the exposure and impact of urban flooding is essential for maintaining residents' health and safety, particularly for those in informal and vulnerable housing. | W32: No external citations provided for this indicator. | X32: No health outcome assessed. | Y32: 1 | AA32: 22 | AC32: ['N/A'] | AD32: Risk Atlas layers for Mexicali (https://www.mexicali.gob.mx/sitioimip/geovisor/geovisor/?geovisor_id=2&access_token=)
A33: 326 | B33: =N33 -> Flooding - annual average days for main roads | C33: Ambient Environment | F33: x | L33: Risks | M33: Flooding | N33: Flooding - annual average days for main roads | O33: Quantity | R33: x | V33: The duration of flooding in main road areas contributes to environmental risks and disruption of essential services, which can impact public health and safety. | W33: Parise, 2018, 'A brief review of global climate change and the public health consequences' | X33: Association reported; no effect size provided. | Y33: 2 | AA33: 13 | AC33: ['Identification of measurable spatial indicators, how they can me calculated and monitored']
A34: 72 | B34: =N34 -> Flooding - main roads | C34: Ambient Environment | F34: x | L34: Risks | M34: Flooding | N34: Flooding - main roads | O34: Quantity | R34: x | V34: The number of flood-prone locations on main roads is an indicator of infrastructure vulnerability that directly affects environmental safety and health risk management. | W34: Parise, 2018, 'A brief review of global climate change and the public health consequences' | X34: Association reported; no effect size provided. | Y34: 1 | AA34: 13 | AC34: ['Identification of measurable spatial indicators, how they can me calculated and monitored'] | AD34: Risk Atlas layers for Mexicali (https://www.mexicali.gob.mx/sitioimip/geovisor/geovisor/?geovisor_id=2&access_token=)
A35: 170 | B35: ="Access to "&LOWER(N35) -> Access to pharmacies | C35: Social Infrastructure | I35: x | L35: Health & Healthcare | M35: Health & Social Services | N35: Pharmacies | O35: Density | P35: x | Q35: 1000 | R35: x | S35: per 1000 persons | V35: Access to medical stores is identified by residents as a fundamental amenity for liveability, ensuring the availability of healthcare commodities across the city. | W35: Chi et al., 2021, 'From Comparative and Statistical Assessments of Liveability and Health Conditions of Districts in Hong Kong towards Future City Development'; Suptelo & Sehida, 2020, 'Factors of Post-Industrial Transformations of Urban Sociogeosystems (Case Kharkiv)' | X35: Amenity accessibility: association reported; no individual effect size provided. | Z35: Destination analysis using GHSCI tools with permutations of: distance to closest, access within threshold(s), and where applicable count per sqkm and per 1,000 persons | AA35: 5 | AC35: ['Supervised classification in Erdas Imagine Software.', 'regression'] | AD35: OSM/ DENUE/IMIP
A36: 97 | B36: ="Access to "&LOWER(N36) -> Access to health centres | C36: Social Infrastructure | I36: x | L36: Health & Healthcare | M36: Health & Social Services | N36: Health centres | O36: Proximity | P36: x | Q36: 1000 | R36: x | S36: x | V36: Proximity to healthcare facilities is essential for maintaining urban life quality and ensures residents have timely access to medical services. | W36: McMichael, 2000, 'The urban environment and health in a world of increasing globalisation: issues for developing countries' | X36: Association reported; no effect size provided. | Z36: Destination analysis using GHSCI tools with permutations of: distance to closest, access within threshold(s), and where applicable count per sqkm and per 1,000 persons | AA36: 19; 20 | AC36: 19: ['machine learning is integrated into semantic image segmentation technique to extract green pixels from the street view images using the scene parsing method; SVG', 'entropy index (relative percentage of various land-use types)'] 20: ['Proximity analysis following digitization and Euclidean distance computation'] | AD36: OSM/ DENUE/IMIP | AE36: I would make this distance to General Practitioner / local health centre
A37: 101 | B37: ="Access to "&LOWER(N37) -> Access to hospitals | C37: Social Infrastructure | I37: x | L37: Health & Healthcare | M37: Health & Social Services | N37: Hospitals | O37: Quantity; Presence | P37: x | Q37: 2000 | R37: x | S37: x | V37: The physical availability and accessibility of healthcare facilities, such as hospitals, are essential determinants of health within the urban liveability framework. | W37: Mercer, 2017, 'Quality of Living Survey'; Economist Intelligence Unit (EIU), 2012, 'Quality of Life Index' | X37: Liveability score: weighted indicator, no individual effect size reported | Z37: Destination analysis using GHSCI tools with permutations of: distance to closest, access within threshold(s), and where applicable count per sqkm and per 1,000 persons | AA37: 8 | AC37: ['Hierarchical Modelling using Analytic Hierarchy Process (AHP)'] | AD37: OSM/ DENUE/IMIP | AE37: I would make this distance to hospital (as distinct from distance to GP)
A38: 382 | B38: =N38 -> Urban heat island | C38: Ambient Environment | F38: x | L38: Risks | M38: Heat | N38: Urban heat island | O38: Quantity | R38: x | V38: Mitigating the urban heat island effect by reducing localized temperature increases promotes thermal comfort and supports the physical and mental well-being of city dwellers. | W38: Leya et al., 2022, 'Spatial Variations of Urban Heat Island Development in Khulna City, Bangladesh: Implications for Urban Planning and Development' | X38: Association reported; no effect size provided. | AA38: 18 | AC38: ['Analytic Hierarchy Process (AHP)'] | AF38: ER: Key indicator
A39: 127 | B39: ="Access to "&LOWER(N39) -> Access to manufacturing district / centre | C39: Economic Development | H39: x | L39: Economy | M39: Industry; Employment | N39: Manufacturing district / centre | O39: Proximity | P39: x | Q39: ? | R39: x | S39: x | V39: Manufacturing centres are sources of industrial hazards and pollution; restricting residential proximity ensures physical safety and protects wellbeing. | W39: Onnom et al., 2018, 'Development of a Liveable City Index (LCI) using multi criteria geospatial modelling for medium class cities in developing countries' | X39: Association reported; no effect size provided. | Z39: Destination analysis using GHSCI tools with permutations of: distance to closest, access within threshold(s), and where applicable count per sqkm and per 1,000 persons | AA39: 20 | AC39: ['Proximity analysis following digitization and Euclidean distance computation'] | AD39: DENUE | AE39: CH: we need to provide clear evidence/guidance about what this means (e.g. is proximity good because of employment opportunities, or bad because of exposure to air/noise pollution?) | AF39: ER: High relevance as Condesa haz manufacturing facilities.
A40: 405 | B40: =N40 -> Land use type | C40: Ambient Environment | F40: x | L40: Resources | M40: Land | N40: Land use type | O40: Quality | U40: x | AA40: 28 | AD40: https://www.mexicali.gob.mx/sitioimip/geovisor/geovisor/?url=pducpmp&access_token= IMIP: usos de suelo https://tecmx.sharepoint.com/:f:/s/Mexicali-SIUM/IgCeSV3JIwQpT6TXm52Vw2gqAXN8KTu7Dex3TtPfbb754oo?e=4QOX5y | AF40: ER: Could be used to calculate land use mix
A41: 385 | B41: =N41 -> Vegetation | C41: Ambient Environment | F41: x | L41: Resources | M41: Land | N41: Vegetation | O41: Quantity | R41: x | V41: Vegetation as a land use type is the optimal land category for human settlement, directly supporting liveability and wellbeing through ecosystem services and green space provision. | W41: No external citations provided for this indicator. | X41: Liveability score: scored 100/100 as the most suitable land type for settlement; Association reported; no health effect size provided. | AA41: 28 | AC41: ['Analytic Hierarchy Profess (AHP)', 'Delphi method', 'Literature analysis']
A42: 116 | B42: =N42 -> Land use mix | C42: Built Environment | E42: x | L42: Urban Morphology | M42: Land Use | N42: Land use mix | O42: Quality | U42: x | V42: Source article not available for review. | W42: Not reported. | X42: Not reported. | AA42: 30 | AC42: ['GIS-based spatial diagnostics'] | AD42: https://www.mexicali.gob.mx/sitioimip/geovisor/geovisor/?url=pducpmp&access_token= IMIP: usos de suelo https://tecmx.sharepoint.com/:f:/s/Mexicali-SIUM/IgCeSV3JIwQpT6TXm52Vw2gqAXN8KTu7Dex3TtPfbb754oo?e=4QOX5y
A43: 230 | B43: =N43 -> Residential area | C43: Built Environment | E43: x | L43: Urban Morphology | M43: Land Use | N43: Residential area | O43: Density | S43: x | V43: Adequate residential area per capita is important for ensuring privacy, comfort, and a high standard of living within urban dwellings. | W43: Saeed et al., 2022, 'An integrated approach for developing an urban livability composite index—A cities’ ranking road map to achieve urban sustainability' | X43: Association reported; no effect size provided. | AA43: 16 | AC43: ['Exploratory Factor Analysis', 'Standard Deviational Ellipse,', 'Hot Spot Analysis,', 'Network Analysis'] | AD43: https://www.mexicali.gob.mx/sitioimip/geovisor/geovisor/?url=pducpmp&access_token= IMIP: usos de suelo https://tecmx.sharepoint.com/:f:/s/Mexicali-SIUM/IgCeSV3JIwQpT6TXm52Vw2gqAXN8KTu7Dex3TtPfbb754oo?e=4QOX5y | AF43: ER: Could be used to calculate land use mix
A44: 167 | B44: =N44 -> Pedestrian infrastructure | C44: Mobility & Transport | K44: x | L44: Active Travel | M44: Pedestrian Infrastructure | N44: Pedestrian infrastructure | O44: Accessibility | Q44: x | V44: Proper sidewalks and crosswalks are critical for safe walkability, encouraging residents to engage in health-promoting physical activities. | W44: Baobeid et al., 2021, 'Walkability and its relationships with health, sustainability, and liveability'; Geller, 2003, 'Smart growth: A prescription for livable cities'; Furlan, 2015, 'Liveability and Social Capital in West Bay' | X44: Proximity target: All essential amenities and recreational facilities in the proposed design are located within a 15-minute walk. | AA44: 27 | AD44: Inventario Nacional de Vivienda
A45: 365 | B45: =N45 -> Street light infrastructure | C45: Safety | D45: x | L45: Road Safety | M45: Pedestrian Infrastructure | N45: Street light infrastructure | O45: Quality | U45: x | V45: Well-lit pedestrian networks are essential for social sustainability, creating a safe environment that encourages nighttime use of public space. | W45: Ahmed, 2012, 'Urban social sustainability: A study of the Emirati local communities in Al Ain' | X45: No health outcome assessed. | Y45: 1 | Z45: Proportion of road segments with presence of public lightning | AA45: 23 | AC45: ['Field observation'] | AD45: Inventario Nacional de Vivienda | AF45: I think its good to measure if we can, but the evidence is complicated (e.g. real/perceived safety vs carbon emissions and 'night sky' preservation from light pollution) https://pmc.ncbi.nlm.nih.gov/articles/PMC4509526/#s0075
A46: 75 | B46: Sidewalk availability | C46: Safety | D46: x | L46: Road Safety | M46: Pedestrian Infrastructure | N46: Sidewalk availability | O46: Quantity | R46: x | V46: Adequate footpath provision is a key building block of liveable neighbourhoods, directly supporting the physical health and activity levels of residents. | W46: Hooper et al., 2015, 'The building blocks of a liveable neighbourhood: Identifying the key performance indicators for walking' | X46: Association reported; no effect size provided. | AA46: 23 | AC46: ['Design Analysis'] | AF46: ER: Only footpaths may not be feasible but we do have data for sidewalk availability
A47: 74 | B47: =N47 -> Walkability Index | C47: Safety | D47: x | L47: Road Safety | M47: Pedestrian Infrastructure | N47: Walkability Index | O47: Quality | U47: x | V47: Walking-friendly urban environments support safety and promote healthy lifestyles through human-oriented design. | W47: Skalicky & Čerpes, 2019, 'Comprehensive assessment methodology for liveable residential environment' | X47: Association reported; no effect size provided. | Z47: Part of GHSCI pipeline | AA47: 23 | AC47: ['Design Analysis'] | AF47: ER: Could this one be part of the Walkability Index?; CH: Great idea --- maybe this row could stand in for the walkability index?
A48: 235 | B48: =N48 -> Road accident locations | C48: Safety | D48: x | L48: Road Safety | M48: Pedestrian Infrastructure | N48: Road accident locations | O48: Quantity | R48: x | V48: Monitoring road accident locations supports the development of safer transport infrastructure to reduce injuries and fatalities from vehicular traffic. | W48: Lowe et al., 2015, 'Planning healthy, liveable and sustainable cities: how can indicators inform policy?' | X48: Association reported; no effect size provided. | AA48: 13 | AC48: ['Identification of measurable spatial indicators, how they can me calculated and monitored'] | AD48: INEGI Accidentes de Tránsito: https://www.inegi.org.mx/programas/accidentes/#documentacion
A49: 334 | B49: =N49 -> Traffic accident fatalities | C49: Safety | D49: x | L49: Road Safety | M49: Pedestrian Infrastructure | N49: Traffic accident fatalities | O49: Quantity | R49: x | V49: Traffic accident fatalities are a primary indicator of road safety; reduced mortality is a fundamental requirement for a secure and livable city environment. | W49: Kourtit et al., 2021, 'Safe cities in the new urban world: A comparative cluster dynamics analysis through machine learning'; Arpan & Joy, 2018, 'Livability assessment within a metropolis based on the impact of integrated urban geographic factors (IUGFs) on clustering urban centers of Kolkata' | X49: No health outcome assessed. | AA49: 17 | AC49: ['Not specified'] | AD49: INEGI Accidentes de Tránsito: https://www.inegi.org.mx/programas/accidentes/#documentacion
A50: 162 | B50: ="Access to "&LOWER(N50) -> Access to parks (local, neighbourhood, district, regional) | C50: Built Environment | E50: x | L50: Green & Blue Infrastructure | M50: Public Open Spaces | N50: Parks (local, neighbourhood, district, regional) | O50: Proximity | P50: x | Q50: 500 | R50: x | S50: x | V50: Source article not available for review. | W50: Not reported. | X50: Not reported. | Z50: Destination analysis using GHSCI tools with permutations of: distance to closest, access within threshold(s), and where applicable count per sqkm and per 1,000 persons | AA50: 19 | AC50: ['machine learning is integrated into semantic image segmentation technique to extract green pixels from the street view images using the scene parsing method; SVG', 'entropy index (relative percentage of various land-use types)'] | AD50: OSM/ IMIP https://www.mexicali.gob.mx/sitioimip/geovisor/geovisor/?url=act-terr&access_token= | AF50: CH: Do you have the data to distinguish "parks" from "public green space"?
A51: 91 | B51: ="Access to "&LOWER(N51) -> Access to public green space | C51: Built Environment | E51: x | L51: Green & Blue Infrastructure | M51: Public Open Spaces | N51: Public green space | O51: Proximity | P51: x | Q51: 500 | R51: x | S51: x | V51: Source article not available for review. | W51: Not reported. | X51: Not reported. | Z51: Destination analysis using GHSCI tools with permutations of: distance to closest, access within threshold(s), and where applicable count per sqkm and per 1,000 persons | AA51: 35 | AC51: 35: [Intercept survey around UGS] | AD51: OSM/ IMIP https://www.mexicali.gob.mx/sitioimip/geovisor/geovisor/?url=act-terr&access_token= | AE51: Access: The green spaces that were considered were only the publicly accessible ones that consist of parks,_x000D_gardens, and recreation areas managed by the municipalities._x000D_• Priority was given to amenities (e.g., green spaces still with some public amenities: walking paths, seating areas,_x000D_shaded zones, etc.) to ensure the usability of the spaces and a proper relationship with the public.
A52: 187 | B52: ="Access to "&LOWER(N52) -> Access to public open space | C52: Built Environment | E52: x | L52: Green & Blue Infrastructure | M52: Public Open Spaces | N52: Public open space | O52: Accessibility | P52: x | Q52: 500 m | R52: x | S52: x | U52: any, 1.5 Ha | V52: Availability of open spaces provides urban residents with areas for comfort, enjoyment, and relaxation, directly contributing to their overall quality of life. | W52: Zhan et al., 2018, 'Assessment and Determinants of Satisfaction with Urban Livability in China'; Paul & Sen, 2018, 'Livability Assessment within a Metropolis Based on the Impact of Integrated Urban Geographic Factors (IUGFs) on Clustering Urban Centers of Kolkata' | X52: Association reported; no effect size provided. | Z52: Destination analysis using GHSCI tools with permutations of: distance to closest, access within threshold(s), and where applicable count per sqkm and per 1,000 persons | AA52: 18 | AC52: ['Analytic Hierarchy Process (AHP)'] | AD52: OSM/ IMIP https://www.mexicali.gob.mx/sitioimip/geovisor/geovisor/?url=act-terr&access_token= | AF52: ER: Do we want to have public open spaces combined with parks?
A53: 174 | B53: ="Access to "&LOWER(N53) -> Access to police station | C53: Safety | D53: x | L53: Personal Safety | M53: Public Services | N53: Police station | O53: Proximity | P53: x | Q53: 1000 | R53: x | S53: x | V53: Neighborhoods located near police stations experience enhanced security and stability, allowing residents to live without feeling threatened or harmed. | W53: Fu et al., 2019, 'The Livable Urban Landscape: GIS and Remote Sensing Extracted Land Use Assessment for Urban Livability in Changchun Proper, China'; Liu et al., 2020, 'Using Multi-Source Data to Assess Livability in Hong Kong at the Community-Based Level: A Combined Subjective-Objective Approach'; Paul & Sen, 2018, 'Livability Assessment within a Metropolis Based on the Impact of Integrated Urban Geographic Factors (IUGFs) on Clustering Urban Centers of Kolkata' | X53: Association reported; no effect size provided. | Z53: Destination analysis using GHSCI tools with permutations of: distance to closest, access within threshold(s), and where applicable count per sqkm and per 1,000 persons | AA53: 18;20;8 | AC53: 18: ['Analytic Hierarchy Process (AHP)'] 20: ['Proximity analysis following digitization and Euclidean distance computation'] 21: ['Kernel Density Estimation (KDE) to identify spatial clusters of walkability-related features', 'Line Density Analysis to measure connectivity of pedestrian infrastructure. These methods complement each other by capturing both the qualitative and quantitative aspects of walkability'] 8: ['Hierarchical Modelling using Analytic Hierarchy Process (AHP)'] | AD53: IMIP: https://www.mexicali.gob.mx/sitioimip/geovisor/geovisor/?url=act-terr&access_token= INEGI: Marco Geoestadítico (SIP layer) | AF53: ER: Could this one be part of a composite index with distance to fire station (69)?
A54: 69 | B54: ="Access to "&LOWER(N54) -> Access to fire station | C54: Safety | D54: x | L54: Personal Safety | M54: Public Services | N54: Fire station | O54: Proximity | P54: x | Q54: 1000 | R54: x | S54: x | V54: Close proximity to fire stations ensures rapid emergency response times, which is essential for protecting residents from physical harm and property damage. | W54: Liu et al., 2020, 'Using Multi-Source Data to Assess Livability in Hong Kong at the Community-Based Level: A Combined Subjective-Objective Approach' | X54: Association reported; no effect size provided. | Z54: Destination analysis using GHSCI tools with permutations of: distance to closest, access within threshold(s), and where applicable count per sqkm and per 1,000 persons | AA54: 18 | AC54: ['Analytic Hierarchy Process (AHP)'] | AD54: IMIP: https://www.mexicali.gob.mx/sitioimip/geovisor/geovisor/?url=act-terr&access_token= INEGI: Marco Geoestadítico (SIP layer) | AF54: ER: Could this one be part of a composite index with distance to fire station (174)? CH: Interesting idea --- I'm not sure "distance to closest" is the most interesting headline here, but rather access within threshold if we can support it with evidence. If we can find citable evidence that you should be within XXX m of fire, police, hospital etc -- this could be a score for emergency services provision. But distance alone may not be great --- imagine if you were 0m from all three, would you want to live there with sirens going off all the time? Maybe not! I don't think living next to these places is something we want to suggest is perfect, so much as access within a reasonable distance for when you need it
A55: 225 | B55: ="Access to "&LOWER(N55) -> Access to recreational areas | C55: Social Infrastructure | I55: x | L55: Community, Culture & Leisure | M55: Recreational areas | N55: Recreational areas | O55: Proximity | P55: x | Q55: 500 | R55: x | S55: x | V55: Easy access to recreational facilities emphasizes the provision of spaces that offer pleasure and physical comfort, improving the overall livability of urban environments. | W55: Basu et al., 2021, 'Urban Livability Index Assessment Based on Land-Use Changes in an Indian Medium-Sized City (Raiganj)'; Fu et al., 2019, 'The Livable Urban Landscape: GIS and Remote Sensing Extracted Land Use Assessment for Urban Livability in Changchun Proper, China' | X55: Association reported; no effect size provided. | Z55: Destination analysis using GHSCI tools with permutations of: distance to closest, access within threshold(s), and where applicable count per sqkm and per 1,000 persons | AA55: 18 | AC55: ['Analytic Hierarchy Process (AHP)'] | AD55: OSM/ DENUE/IMIP
A56: 257 | B56: ="Access to "&LOWER(N56) -> Access to sports centres | C56: Social Infrastructure | I56: x | L56: Community, Culture & Leisure | M56: Recreational areas | N56: Sports centres | O56: Quantity | P56: x | Q56: 500 | R56: x | S56: x | V56: The provision of sport centres is critical for promoting physical activity, which reduces the risk of chronic diseases and improves mental health outcome. | W56: Lowe et al., 2015, 'Planning healthy, liveable and sustainable cities: how can indicators inform policy?'; Sachs et al., 2019, 'Six transformations to achieve the sustainable development goals' | X56: Association reported; no effect size provided. | Z56: Destination analysis using GHSCI tools with permutations of: distance to closest, access within threshold(s), and where applicable count per sqkm and per 1,000 persons | AA56: 13; 16; 20 | AC56: 13: ['Identification of measurable spatial indicators, how they can me calculated and monitored'] 16: ['Exploratory Factor Analysis', 'Standard Deviational Ellipse,', 'Hot Spot Analysis,', 'Network Analysis'] | AD56: OSM/ DENUE/IMIP
A57: 218 | B57: Co-location of recreational areas with public transport | C57: Social Infrastructure | I57: x | L57: Community, Culture & Leisure | M57: Recreational areas | N57: Public transport | O57: Proximity | P57: x | Q57: x | R57: x | S57: x | U57: x | V57: Proximity to diverse transportation options ensures inclusive regional accessibility, allowing a wider demographic to benefit from recreational and social infrastructure. | W57: Project for Public Space, 2016, 'What Makes a Successful Place?'; CABE and DETR, 2001, 'The value of urban design' | X57: Visit frequency: High satisfaction with transportation proximity (mean = 4.03) is linked to the overall visit frequency correlation (rho = 0.310). | Z57: Destination analysis using GHSCI tools with permutations of: distance to closest, access within threshold(s), and where applicable count per sqkm and per 1,000 persons | AA57: 15 | AC57: ['Likert scale'] | AD57: OSM/ DENUE/IMIP | AF57: ER: This one can be part of another composite indicator of either public transport or public open spaces
A58: 96 | B58: ="Access to "&LOWER(N58) -> Access to hawker/stall | C58: Built Environment | E58: x | L58: Urban Design | M58: Streetscape | N58: Hawker/stall | O58: Quantity | P58: x | Q58: x | R58: x | S58: x | V58: Regulating permitted locations for sidewalk hawkers ensures local food access and livelihood security while managing urban street safety and hygiene. | W58: Alderton et al., 2019, 'What is the meaning of urban liveability for a city in a low-to-middle-income country? Contextualising liveability for Bangkok, Thailand' | X58: Association reported; no effect size provided. | Z58: Destination analysis using GHSCI tools with permutations of: distance to closest, access within threshold(s), and where applicable count per sqkm and per 1,000 persons | AA58: 13 | AC58: ['Identification of measurable spatial indicators, how they can me calculated and monitored'] | AD58: Inventario Nacional de Vivienda | AF58: ER: We have available data on if there are fixed or semi-fixed stalls present but we can't know if these have a permit or not. CH: I think lets not take it too literally -- street food/hawkers are part of a vibrant food environment, let's measure this (the permitted thing if this was from Bangkok mattered to them because they are the metropolitan administration; may have some relevance to public health but lets not make it a barrier to measuring street food)
A59: 107 | B59: =N59 -> The difference between the relative humidity in July and the optimum humidity for human body | C59: Ambient Environment | F59: x | L59: Ambient | M59: Thermal comfort | N59: The difference between the relative humidity in July and the optimum humidity for human body | O59: Quantity | R59: x | V59: The difference from optimal humidity in July affects thermal comfort and respiratory wellness, with extreme humidity levels impacting residents' physical health. | W59: Zhan et al., 2018, 'Assessment and determinants of satisfaction with urban livability in China'; Tang et al., 2017, 'Comprehensive evaluation of trends in human settlements quality changes and spatial differentiation characteristics of 35 Chinese major cities' | X59: No health outcome assessed. | AA59: 17 | AC59: ['Not specified'] | AF59: checar indicator
A60: 337 | B60: =N60 -> Humidity | C60: Ambient Environment | F60: x | L60: Ambient | M60: Thermal comfort | N60: Humidity | O60: Quantity | R60: x | V60: Appropriate humidity levels are necessary for human thermal comfort and can affect respiratory health and the perceived quality of the urban environment. | W60: Kashi et al., 2024, 'Effects of extreme weather events and climate change on cities’ livability'; Liang and Li, 2020, 'Resilience and sustainable development goals based social-ecological indicators and assessment of coastal urban areas' | X60: Association reported; no effect size provided. | Z60: Thermal comfort indicator to be calculated by Rossano | AA60: 16 | AC60: ['Exploratory Factor Analysis', 'Standard Deviational Ellipse,', 'Hot Spot Analysis,', 'Network Analysis'] | AE60: ER: Rossano will work on the Thermal comfort indicator
A61: 366 | B61: =N61 -> Hours of sunshine in January | C61: Ambient Environment | F61: x | L61: Ambient | M61: Thermal comfort | N61: Hours of sunshine in January | O61: Quantity | R61: x | V61: Adequate sunshine duration in January supports mental wellbeing and provides natural lighting and heating, contributing to a pleasant living environment. | W61: Arpan & Joy, 2018, 'Livability assessment within a metropolis based on the impact of integrated urban geographic factors (IUGFs) on clustering urban centers of Kolkata'; Li & Jin, 2012, 'Characteristics and spatial-temporal differences of urban human settlement environment in China' | X61: No health outcome assessed. | Z61: Thermal comfort indicator to be calculated by Rossano | AA61: 17 | AC61: ['Not specified'] | AE61: ER: Rossano will work on the Thermal comfort indicator | AF61: CH: "Sunshine in January" is a very parochially phrased indicator (assumption that January is in northern hemisphere, so this is sunshine in Winter I assume; or vice versa. But it would be better to be explicit as to which it means!) / ER: This one is part of a "Natural Environment Pleaseantness" I think this could be usueful or it can be part of the heat risk indicators
A62: 371 | B62: =N62 -> Temperature | C62: Ambient Environment | F62: x | L62: Ambient | M62: Thermal comfort | N62: Temperature | O62: Quantity | R62: x | V62: Maintaining urban temperatures within a comfortable range is vital for physical health and preventing heat-related illnesses and thermal discomfort. | W62: Kashi et al., 2024, 'Effects of extreme weather events and climate change on cities’ livability'; Alijani et al., 2020, 'A new approach of urban livability in Tehran: Thermal comfort as a primitive indicator' | X62: Association reported; no effect size provided. | Z62: Thermal comfort indicator to be calculated by Rossano | AA62: 16 | AC62: ['Exploratory Factor Analysis', 'Standard Deviational Ellipse,', 'Hot Spot Analysis,', 'Network Analysis'] | AE62: ER: Rossano will work on the Thermal comfort indicator
A63: 370 | B63: =N63 -> Average temperature in sunshine | C63: Ambient Environment | F63: x | L63: Ambient | M63: Thermal comfort | N63: Average temperature in sunshine | O63: Quantity | R63: x | V63: Average winter temperature (as January mean) is a key climate amenity that influences residents' physiological comfort and health during the cold season. | W63: Zhan et al., 2018, 'Assessment and determinants of satisfaction with urban livability in China'; Li et al., 2008, 'Review of the theories and methods of livable city' | X63: No health outcome assessed. | Y63: 2 | Z63: Thermal comfort indicator to be calculated by Rossano | AA63: 17 | AC63: ['Not specified'] | AE63: ER: Rossano will work on the Thermal comfort indicator | AF63: Will this be surface temperature or street level temperature?
A64: 372 | B64: =N64 -> The difference between the average temperature in July and the optimal temperature for human body | C64: Ambient Environment | F64: x | L64: Ambient | M64: Thermal comfort | N64: The difference between the average temperature in July and the optimal temperature for human body | O64: Quantity | R64: x | V64: The difference from optimal temperature in July indicates thermal comfort; excessive summer heat is linked to physiological stress and reduced outdoor activity. | W64: Zhan et al., 2018, 'Assessment and determinants of satisfaction with urban livability in China'; Cao et al., 2019, 'The framework of relationship between built environment and residents healthy based on activity perspective' | X64: No health outcome assessed. | Z64: Thermal comfort indicator to be calculated by Rossano | AA64: 17 | AC64: ['Not specified'] | AE64: ER: Rossano will work on the Thermal comfort indicator | AF64: Care needs to be taken: is "July" relevant for Mexicali? (e.g. better to calculate as "Hottest month" if that was intended by the authors; July is too parochial)
A65: 26 | B65: ="Access to "&LOWER(N65) -> Access to buses: stops | C65: Mobility & Transport | K65: x | L65: Public Transport | M65: Transport Stops | N65: Buses: Stops | O65: Density | P65: x | Q65: x | R65: x | S65: per 1000 persons | V65: Proximity to bus stops improves accessibility to city facilities and services, acting as a major engine of urban growth and resident liveability. | W65: Higgs et al., 2019, 'The Urban Liveability Index: developing a policy-relevant urban liveability composite measure and evaluating associations with transport mode choice'; Suptelo & Sehida, 2020, 'Factors of Post-Industrial Transformations of Urban Sociogeosystems (Case Kharkiv)' | X65: Transportation accessibility: association reported; no individual effect size provided. | Z65: Destination analysis using GHSCI tools with permutations of: distance to closest, access within threshold(s), and where applicable count per sqkm and per 1,000 persons | AA65: 5 | AC65: ['Supervised classification in Erdas Imagine Software.', 'regression'] | AD65: IMIP: https://www.mexicali.gob.mx/sitioimip/geovisor/geovisor/?url=pimus&access_token=
A66: 223 | B66: ="Access to "&LOWER(N66) -> Access to public transport | C66: Mobility & Transport | K66: x | L66: Public Transport | M66: Transport Stops; Transport Routes | N66: Public transport | O66: Accessibility | P66: x | Q66: x | R66: x | S66: x | V66: Extensive public transit coverage ensures equitable access to city-wide opportunities and services, reducing health inequities related to mobility. | W66: Kashef, 2016, 'Urban liveability across disciplinary and professional boundaries'; Cervero, 2009, 'Transport infrastructure and global competitiveness'; Bassolas et al., 2019, 'Hierarchical organization of urban mobility and its connection with city liveability'; Vuchic, 2017, 'Transportation for Livable Cities' | X66: Compliance rate: 85.7% of evaluated liveability indices in the studied communities were related to public transport and green space availability. | Z66: Destination analysis using GHSCI tools with permutations of: distance to closest, access within threshold(s), and where applicable count per sqkm and per 1,000 persons | AA66: 27 | AD66: IMIP: https://www.mexicali.gob.mx/sitioimip/geovisor/geovisor/?url=pimus&access_token=
A67: 135 | B67: =N67 -> NDVI | C67: Ambient Environment | E67: x | L67: Ambient | M67: Vegetation | N67: NDVI | O67: Quantity | R67: x | V67: The Normalised Difference Vegetation Index (NDVI) is used to track city-wide greenness, which supports mental health and environmental sustainability. | W67: Sachs et al., 2019, 'Six transformations to achieve the sustainable development goals'; Lowe et al., 2015, 'Planning healthy, liveable and sustainable cities: how can indicators inform policy?' | X67: Association reported; no effect size provided. | AA67: 13 | AC67: ['Identification of measurable spatial indicators, how they can me calculated and monitored']
A68: 378 | B68: =N68 -> Vegetation coverage: Canopy | C68: Ambient Environment | E68: x | L68: Ambient | M68: Vegetation | N68: Vegetation coverage: Canopy | O68: Quantity | R68: x | V68: Urban tree canopy coverage mitigates local temperatures and provides shade and aesthetic value that support mental wellbeing and encourage physical activity in public spaces. | W68: Appleyard, 1981, 'Livable Streets'; Basiago, 1999, 'Economic, social, and environmental sustainability in development theory and urban planning practice' | X68: Association reported; no effect size provided. | AA68: 22 | AC68: ['N/A']
A69: 388 | B69: =N69 -> Vegetation mix | C69: Ambient Environment | E69: x | L69: Ambient | M69: Vegetation | N69: Vegetation mix | O69: Diversity | T69: x | V69: A variety of urban vegetation supports biodiversity and ecological health, while providing aesthetic and psychological benefits that enhance the living environment. | W69: Khorrami et al., 2021, 'The indicators and methods used for measuring urban liveability: A scoping review'; Liu et al., 2020, 'Using multi-source data to assess livability in Hong Kong at the community-based level: A combined subjective-objective approach' | X69: Association reported; no effect size provided. | AA69: 16 | AC69: ['Exploratory Factor Analysis', 'Standard Deviational Ellipse,', 'Hot Spot Analysis,', 'Network Analysis']
A70: 389 | B70: =N70 -> Vegetation percent | C70: Ambient Environment | F70: x | L70: Ambient | M70: Vegetation | N70: Vegetation percent | O70: Quantity | R70: x | V70: Mean vegetation coverage across the city helps mitigate the urban heat island effect and provides psychological health benefits through exposure to nature. | W70: Lowe et al., 2015, 'Planning healthy, liveable and sustainable cities: how can indicators inform policy?'; Sachs et al., 2019, 'Six transformations to achieve the sustainable development goals' | X70: Association reported; no effect size provided. | AA70: 13 | AC70: ['Identification of measurable spatial indicators, how they can me calculated and monitored']
A71: 3 | B71: ="Access to "&LOWER(N71) -> Access to activity centres | C71: Social Infrastructure | I71: x | L71: Community, Culture & Leisure | M71: Walkability | N71: Activity centres | O71: Proximity | P71: x | Q71: 500 | R71: x | S71: x | V71: Proximity to healthcare and grocery stores ensures that residents can easily manage their health and maintain a nutritious daily diet. | W71: Almashhour & Samara, 2022, 'Evaluating Liveability Perceptions'; Zhu et al., 2020, 'Assessing community-level liveability using combined remote sensing and internet-based big geospatial data'; Gough, 2015, 'Reconciling liveability and sustainability'; Zanella et al., 2015, 'The assessment of cities' liveability integrating human wellbeing and environmental impact'; Benita et al., 2021, 'A spatial liveability index for dense urban centers' | X71: Proximity target: All essential amenities and recreational facilities in the proposed design are located within a 15-minute walk. | Z71: Destination analysis using GHSCI tools with permutations of: distance to closest, access within threshold(s), and where applicable count per sqkm and per 1,000 persons | AA71: 27 | AD71: OSM/ DENUE/IMIP | AE71: This indicator has multiple amenities from different domains | AF71: ER: This indicator can also be part of the built environment domain / Walkability; CH: I think this means we include it then?
A72: 125 | B72: ="Access to "&LOWER(N72) -> Access to major road | C72: Built Environment | E72: x | L72: Urban Morphology | M72: Walkability | N72: Major road | O72: Proximity | P72: x | Q72: >=100m | R72: x | S72: x | V72: Major roads are a source of air and noise pollution associated with negative health impacts | W72: Zhan et al., 2018, 'Assessment and Determinants of Satisfaction with Urban Livability in China'; Tao et al., 2015, 'Housing Choices of Migrant Workers in China: Beyond the Hukou Perspective' | X72: Association reported; no effect size provided. | Z72: Destination analysis using GHSCI tools with permutations of: distance to closest, access within threshold(s), and where applicable count per sqkm and per 1,000 persons | AA72: 18 | AC72: ['Analytic Hierarchy Process (AHP)']
A73: 126 | B73: ="Access to "&LOWER(N73) -> Access to major road intersection | C73: Built Environment | E73: x | L73: Urban Morphology | M73: Walkability | N73: Major road intersection | O73: Proximity | P73: x | Q73: >=100m | R73: x | S73: x | V73: Living further from major road intersections reduces the risk of traffic accidents and fire incident risks, thereby fostering a safer and more stable residential environment. | W73: Basu et al., 2021, 'Urban Livability Index Assessment Based on Land-Use Changes in an Indian Medium-Sized City (Raiganj)'; Onnom et al., 2018, 'Development of a Liveable City Index (LCI) Using Multi Criteria Geospatial Modelling for Medium Class Cities in Developing Countries'; Fu et al., 2019, 'The Livable Urban Landscape: GIS and Remote Sensing Extracted Land Use Assessment for Urban Livability in Changchun Proper, China' | X73: Association reported; no effect size provided. | Z73: Destination analysis using GHSCI tools with permutations of: distance to closest, access within threshold(s), and where applicable count per sqkm and per 1,000 persons | AA73: 18 | AC73: ['Analytic Hierarchy Process (AHP)']
A74: 180 | B74: ="Access to "&LOWER(N74) -> Access to schools: primary | C74: Social Infrastructure | I74: x | L74: Education | M74: Walkability | N74: Schools: Primary | O74: Proximity | P74: x | Q74: x | R74: x | S74: x | V74: Close proximity to primary schools supports family-oriented livability by facilitating easy and convenient access to essential basic education for young residents. | W74: Onnom et al., 2018, 'Development of a Liveable City Index (LCI) Using Multi Criteria Geospatial Modelling for Medium Class Cities in Developing Countries'; Fu et al., 2019, 'The Livable Urban Landscape: GIS and Remote Sensing Extracted Land Use Assessment for Urban Livability in Changchun Proper, China'; Liu et al., 2020, 'Using Multi-Source Data to Assess Livability in Hong Kong at the Community-Based Level: A Combined Subjective-Objective Approach' | X74: Association reported; no effect size provided. | Z74: Destination analysis using GHSCI tools with permutations of: distance to closest, access within threshold(s), and where applicable count per sqkm and per 1,000 persons | AA74: 18 | AC74: ['Analytic Hierarchy Process (AHP)'] | AD74: OSM/ DENUE/IMIP
A75: 246 | B75: ="Access to "&LOWER(N75) -> Access to schools: secondary | C75: Social Infrastructure | I75: x | L75: Education | M75: Walkability | N75: Schools: Secondary | O75: Proximity | P75: x | Q75: x | R75: x | S75: x | V75: Ensuring secondary schools are within a accessible distance enhances urban convenience and satisfies the educational requirements of residents, contributing to higher community satisfaction. | W75: Onnom et al., 2018, 'Development of a Liveable City Index (LCI) Using Multi Criteria Geospatial Modelling for Medium Class Cities in Developing Countries'; Fu et al., 2019, 'The Livable Urban Landscape: GIS and Remote Sensing Extracted Land Use Assessment for Urban Livability in Changchun Proper, China'; Liu et al., 2020, 'Using Multi-Source Data to Assess Livability in Hong Kong at the Community-Based Level: A Combined Subjective-Objective Approach' | X75: Association reported; no effect size provided. | Z75: Destination analysis using GHSCI tools with permutations of: distance to closest, access within threshold(s), and where applicable count per sqkm and per 1,000 persons | AA75: 18 | AC75: ['Analytic Hierarchy Process (AHP)'] | AD75: OSM/ DENUE/IMIP
A76: 379 | B76: ="Access to "&LOWER(N76) -> Access to schools: tertiary (universities) | C76: Social Infrastructure | I76: x | L76: Education | M76: Walkability | N76: Schools: Tertiary (Universities) | O76: Proximity | P76: x | Q76: x | R76: x | S76: x | V76: Universities provide essential social infrastructure; their accessibility contributes to the overall convenience and livability rating of urban environments. | W76: Ibem and Amole, 2013, 'Residential satisfaction in public core housing in Abeokuta, Ogun State, Nigeria'; Huang and Du, 2015, 'Assessment and determinants of residential satisfaction with public housing in Hangzhou, China' | X76: Association reported; no effect size provided. | Z76: Destination analysis using GHSCI tools with permutations of: distance to closest, access within threshold(s), and where applicable count per sqkm and per 1,000 persons | AA76: 20 | AC76: ['Proximity analysis following digitization and Euclidean distance computation'] | AD76: OSM/ DENUE/IMIP
A77: 38 | B77: ="Access to "&LOWER(N77) -> Access to city center | C77: Built Environment | E77: x | L77: Urban Morphology | M77: Walkability | N77: City center | O77: Proximity | P77: x | Q77: x | R77: x | S77: x | V77: Areas closer to the city center offer easy access to a variety of facilities such as employment, shopping, and entertainment, making them highly livable from a convenience perspective. | W77: Basu et al., 2021, 'Urban Livability Index Assessment Based on Land-Use Changes in an Indian Medium-Sized City (Raiganj)'; Onnom et al., 2018, 'Development of a Liveable City Index (LCI) Using Multi Criteria Geospatial Modelling for Medium Class Cities in Developing Countries'; Fu et al., 2019, 'The Livable Urban Landscape: GIS and Remote Sensing Extracted Land Use Assessment for Urban Livability in Changchun Proper, China' | X77: Association reported; no effect size provided. | Z77: Destination analysis using GHSCI tools with permutations of: distance to closest, access within threshold(s), and where applicable count per sqkm and per 1,000 persons | AA77: 18 | AC77: ['Analytic Hierarchy Process (AHP)']
A78: 238 | B78: =N78 -> Road density | C78: Built Environment | E78: x | L78: Urban Morphology | M78: Walkability | N78: Road density | O78: Density | S78: x | V78: Road density is a key driver of urban expansion and accessibility to city amenities, though it must be managed to mitigate traffic congestion and resident dissatisfaction. | W78: Higgs et al., 2019, 'The Urban Liveability Index: developing a policy-relevant urban liveability composite measure and evaluating associations with transport mode choice'; Pradhan et al., 2021, 'Urbanization, transportation infrastructure, ICT, and economic growth: A temporal causal analysis' | X78: Accessibility and urban expansion: association reported; no individual effect size provided. | AA78: 5 | AC78: ['Supervised classification in Erdas Imagine Software.', 'regression'] | AD78: INEGI: Marco Geoestadístico Nacional/ OSM
A79: 362 | B79: =N79 -> Street connectivity | C79: Built Environment | E79: x | L79: Urban Morphology | M79: Walkability | N79: Street connectivity | O79: Quality | U79: x | V79: A well-connected pedestrian network promotes a safe environment and directly supports the physical health of residents by encouraging walking. | W79: Ahmed, 2012, 'Urban social sustainability: A study of the Emirati local communities in Al Ain' | X79: Association reported; no effect size provided. | AA79: 23 | AC79: ['Design Analysis', 'Field observation'] | AF79: ER: Review the composite hierarchy number
A80: 62 | B80: =N80 -> Level of cycling traffic stress | C80: Mobility & Transport | K80: x | L80: Active Travel | M80: Walking Infrastructure | N80: Level of cycling traffic stress | O80: Quantity | U80: x | V80: Designing side alleys to promote walking and cycling integrates residents into the urban fabric and supports a healthy, human-oriented environment. | W80: Skalicky & Čerpes, 2019, 'Comprehensive assessment methodology for liveable residential environment' | X80: Association reported; no effect size provided. | Z80: Level of traffic stress network using GHSCI | AA80: 23 | AC80: [Space syntax analysis', 'Field observation'] | AF80: ER: From the original article this was obtained, this is defined as "Fu2 Integration into a wider urban structure" Which is actually focused on "High-quality residential environment includes the coexistence of various social groups ensuring them to live in quality residential environment and preventing their users and residential environments from isolation." So, I am not sure how we could measure this (I agree, could be difficult to measure in a meaningful way)
A81: 341 | B81: =N81 -> Annual hazardous waste (kg) | C81: Ambient Environment; Safety | D81: x | F81: x | L81: Risks | M81: Waste Management | N81: Annual hazardous waste (kg) | O81: Quantity | R81: x | V81: Monitoring hazardous waste volumes is essential for preventing the accumulation of toxic substances in the environment that can cause severe illness or injury. | W81: Giles-Corti et al., 2019, 'Achieving the SDGs: evaluating indicators to be used to benchmark and monitor progress towards creating healthy and sustainable cities' | X81: Association reported; no effect size provided. | Y81: 1 | AA81: 13 | AC81: ['Identification of measurable spatial indicators, how they can me calculated and monitored'] | AE81: ER: We can obtain data for some industries from the Taking Stock website
A82: 10 | B82: ="Access to "&LOWER(N82) -> Access to blue space | C82: Ambient Environment | F82: x | L82: Resources | M82: Water | N82: Blue space | O82: Quantity | P82: x | Q82: 500 | R82: x | S82: x | V82: Proximity to available water resources is a critical liveability indicator in arid urban environments, as access to water is fundamental to human health, comfort, and survival. | W82: No external citations provided for this indicator. | X82: Liveability composite: weighted at 10.24% in the index; Association reported; no individual health effect size provided. | Y82: 1 | Z82: Destination analysis using GHSCI tools with permutations of: distance to closest, access within threshold(s), and where applicable count per sqkm and per 1,000 persons | AA82: 28 | AC82: ['Based on Landsat OLI_TIRS multispectral data, thenormalized differential water index (MNDWI) was calculated, where: MNDWI = G - MIR/G + MIR where MIR is the reflectance value of the infrared band in Landsat andGis the reflectance value of the infrared band. Single-factor scores wereevaluated in combination with the effects of water bodies on thelivability of urban environments within a certain radiation distance.When the radiation range of water bodies was < 200 m, the areas surroundingwater bodies (e.g., wetlands and parks) were the most livable,reaching scores of 100. Water bodies could influence the livability of theurban environment within 200–500 m, where AWR was evaluated ashaving a score of 90. Areas 500–1000 m away from water bodies mightbe influenced by other buildings, where AWR had a score of 80. Areas1000–1500 m away from water bodies require travel by foot, bike orother means, and their AWR score was 60. Since water resources areextremely important to arid cities, the lowest limit was determined as60. That means the lowest level of the livability in this area is theGenerally livable when only water resources are considered.'] | AD82: Landsat OLI_TIRS multispectral data | AF82: checar indicator /ER: This would need to include the canals
A83: 0 | B83: Mexicali Liveability Index | P83: x | Q83: x | R83: x | S83: x | T83: x | U83: x
A84: 335 | B84: =N84 -> Urbanization rate | C84: Sociodemographics | J84: x | L84: City | N84: Urbanization rate | V84: Rapid urbanization can place excessive strain on the fragile ecosystems of underdeveloped regions, potentially diminishing the quality of the living environment. | W84: Fu et al., 2017, 'Hydrogeomorphic ecosystem responses to natural and anthropogenic changes in the Loess Plateau of China'; Bediroglu, 2021, 'Developing GIS interface for the automated analysis and assessment of livable and sustainable city criterion sets' | X84: Urban liveability: β = -0.082 (p < 0.05), inverse association | AA84: 3 | AC84: ['Entropy TOPSIS model', 'Tobit model'] | AD84: GHSL | AE84: ER: This can be measured with the longitudinal data and analysis we have on our scaling and remoteness article

Sheet Lens - Enfoque
A1: Lens / Enfoque (plural approaches for considering an indicator) | B1: Reference | C1: Description of analytical lens | D1: Indicator example (e.g. aggregate for manzanas / AGEB / grid, as appropriate/feasible) | E1: Example reference
A2: Proximity | B2: Network distance | C2: Distance to closest (m) along the pedestrian network | D2: Average distance to the closest blue space (m)
A3: Accessibility | B3: Within threshold distance | C3: Access within relevant threshold | D3: Percentage of population who can access a blue space within threshold distances (<300m; 300-600m; 600-1200m; 1200-1500m;>1500m)
A4: Quantity | B4: Within area or threshold | C4: Count within relevant threshold | D4: Count of blue spaces within threshold distances (<300m; 300-600m; 600-1200m; 1200-1500m;>1500m)
A5: Density | B5: Within area or threshold | C5: Relative to another unit (e.g. sqkm or per capita), or percentage coverage | D5: Percentage of blue space within neighbourhood
D6: Supermarkets per km2
D7: Square meters of green space per capita
A8: Diversity | B8: Within area or threshold | C8: Entropy score (is what I think of) | D8: Land use mix | E8: Mavoa, S., Eagleson, S., Badland, H. M., Gunn, L., Boulange, C., Stewart, J., & Giles-Corti, B. (2018). Identifying appropriate land-use mix measures for use in a national walkability index. Journal of Transport and Land Use, 11(1). https://doi.org/10.5198/jtlu.2018.1132
A9: Quality | B9: Depends? | D9: >= 9sqm green space per capita within 15 minutes walking distance | E9: https://unhabitat.org/developing-public-space-and-land-values-in-cities-and-neighbourhoods

Sheet Article list
A1: Article # | B1: title | C1: Author | D1: Year | E1: Search | F1: Notas | G1: Extra relevant | H1: Excluded
A2: 1 | B2: A methodology for the identification of significant factors for the improvement of pedestrian facilities in an urban area | C2: Aromal | D2: 2021 | E2: 1 | F2: This article's main aim is to develop a comprehensive list of factors that would help in the decision-making process for the improvement of pedestrian facilities in urban areas. It includes built environment factors related to liveability and in fact a domain they call Ambience/Liveability. Should we keep it? | H2: 2026-07-17 ER JN CH discussion (doesn't meet inclusion / exclusion criteria)
A3: 2 | B3: A sustainability assessment framework for population density in central Indian cities | C3: Kamble | D3: 2021 | E3: 1 | F3: Not focused on liveability | H3: Excluded
A4: 3 | B4: Assessment and key factors of urban liveability in underdeveloped regions: A case study of the Loess Plateau, China | C4: Xiao | D4: 2022 | E4: 1
A5: 4 | B5: Can Tourism Development Make Cities More Livable? Investigating 40 Cities in China | C5: Kang | D5: 2022 | E5: 1,2,3 | H5: 2026-07-17 ER JN CH discussion (doesn't meet inclusion / exclusion criteria)
A6: 5 | B6: Constructing a city liveability index and evaluating the spatial pattern of liveability of Guwahati city | C6: Mahanta | D6: 2025 | E6: 1
A7: 6 | B7: Decision-Making Framework for Prioritizing the Improvement of Pedestrian Facilities in Urban Areas Using Integrated Delphi, AHP, and TOPSIS Approach | C7: Aromal | D7: 2022 | E7: 1 | F7: Not focused on liveability | H7: Excluded
A8: 7 | B8: Determining Factors Influencing Residents’ Satisfaction Regarding Urban Livability in Pakistan | C8: Baig | D8: 2019 | E8: 1 | F8: This study ONLY uses survey data | H8: 2026-07-17 ER JN CH discussion (doesn't meet inclusion / exclusion criteria)
A9: 8 | B9: Development of a Liveable City Index (LCI) Using Multi Criteria Geospatial Modelling for Medium Class Cities in Developing Countries | C9: Onnom | D9: 2018 | E9: 1 | G9: *
A10: 9 | B10: Infill Architecture as a Solution for Livability and Historical Texture Quality Promotion | C10: Beiglu | D10: 2019 | E10: 1 | F10: This article is more conceptual, it does have a section on liveability and includes some measures but without detail on how these are calculated | H10: 2026-07-17 ER JN CH discussion (doesn't meet inclusion / exclusion criteria)
A11: 10 | B11: Investigation of Urban Design Approaches in Renewal Areas with Hybrid Decision Model | C11: Gungor | D11: 2022 | E11: 1 | F11: Not focused on liveability | H11: Excluded
A12: 11 | B12: Livability in dense residential neighbourhoods of Dhaka | C12: Satu | D12: 2019 | E12: 1 | F12: This study ONLY uses survey data | H12: 2026-07-17 ER JN CH discussion (doesn't meet inclusion / exclusion criteria)
A13: 12 | B13: Measuring Liveability by Exploring Urban Qualities of Kissy Street, Freetown, Sierra Leone | C13: Conteh | D13: 2016 | E13: 1
A14: 13 | B14: Measuring and monitoring liveability in a low-to-middle income country: a proof-of-concept for Bangkok, Thailand and lessons from an international partnership | C14: Alderton | D14: 2021 | E14: 1
A15: 14 | B15: Paying for the quality of life: The impacts of urban livability on CEO compensation | C15: Li | D15: 2021 | E15: 1 | F15: This study assesses if urban liveability is correlated with higher CEO compensation. Although is not focused on liverability, it does measure liveability as the independent variable | H15: 2026-07-17 ER JN CH discussion (doesn't meet inclusion / exclusion criteria); This article is not relevant as is not focused on the main population but only executives of listed companies;
A16: 15 | B16: Planning and designing livable recreational open spaces in developing countries. Insights from Souk Ahras City, Algeria | C16: Hafsi | D16: 2024 | E16: 1 | F16: This study investigated the role of urban planning and urban design in shaping livable recreational open spaces in Souk Ahras City, Algeria.
A17: 16 | B17: Spatial analysis and ranking of urban districts based on a comprehensive livability approach: the case of Tehran | C17: Kashi | D17: 2025 | E17: 1
A18: 17 | B18: The impact of economic development on urban livability: Evidence from 40 large and medium-sized cities of China | C18: Wang | D18: 2023 | E18: 1
A19: 18 | B19: Urban Livability in a Rapidly Urbanizing Mid-Size City: Lessons for Planning in the Global South | C19: Jodder | D19: 2024 | E19: 1
A20: 19 | B20: Urban greenness, mixed land-use, and life satisfaction: Evidence from residential locations and workplace settings in Beijing | C20: Wu | D20: 2022 | E20: 1 | F20: This study aims to provide insights into the interaction effect between neighbourhood greenness (proxied by eye-sensored street view exposure to greenspaces) and mixed land-use (measured by micro-level point-ofinterest entropy) in shaping residents’ life satisfaction (as an indicator of urban liveability).
A21: 20 | B21: Urban livability index assessment based on land-use changes in an Indian medium-sized city (Raiganj) | C21: Basu | D21: 2021 | E21: 1
A22: 21 | B22: Urban walkability assessment: methods and implications for city planning | C22: Chaudhary | D22: 2025 | E22: 1 | F22: Not focused on liveability | H22: Excluded
A23: 22 | B23: What is the meaning of urban liveability for a city in a low-to-middle-income country? Contextualising liveability for Bangkok, Thailand | C23: Alderton | D23: 2019 | E23: 1
A24: 23 | B24: Socio-physical liveability through socio-spatiality in low-income resettlement archetypes - A case of slum rehabilitation housing in Mumbai, India. | C24: Sarkar | D24: 2020 | E24: 3
A25: 24 | B25: Evaluating the impact of urban green spaces on public well-being and environmental sustainability in Saudi Arabian megacities | C25: Addas | D25: 2025 | E25: 3 | F25: Not focused on liveability | H25: Excluded
A26: 25 | B26: Urban green space in transition: A cross-continental perspective from eight Global North and South cities | C26: Derdoui | D26: 2025 | E26: 3 | F26: Not focused on liveability | H26: Excluded
A27: 26 | B27: Transforming Riyadh: urban development, quality of life, and spatial equity under Vision 2030 | C27: Mahboob | D27: 2025 | E27: 3
A28: 27 | B28: Integrated Framework for Enhancing Liveability and Ecological Sustainability in UAE Communities | C28: Alzaim | D28: 2024 | E28: 3
A29: 28 | B29: Evaluation of the livability of arid urban environments under global warming: A multi-parameter approach | C29: Chen | D29: 2023 | E29: 3 | G29: *
A30: 29 | B30: Setting up the ENVI-met digital tool to evaluate climatic conditions at an urban scale: a case study of Djelfa, Algeria | C30: Brahimi | D30: 2023 | E30: 3 | F30: Not focused on liveability | H30: Excluded
A31: 30 | B31: Transit-Oriented Development and Urban Livability in Gulf Cities: Comparative Analysis of Doha’s West Bay and Riyadh’s King Abdullah Financial District | C31: Mazzetto | D31: 2025 | E31: 3
A32: 31 | B32: Assessing spatial–temporal evolution and key factors of urban livability in arid zone: The case study of the Loess Plateau, China | C32: Xiao | D32: 2022 | E32: 3

Sheet Safety & Security
A1: Article # | B1: Excluded? | C1: Domain | D1: Subdomain | E1: Indicator / Category | F1: Subject | G1: Specific Measure lens / Enfoque | H1: Scale(s) | I1: Mexicali indicator | J1: Does it matter? | K1: Can we calculate this? Do we have data? | L1: What is the most pragmatic way of measuring it? | M1: Specific measures (from literature) | N1: Methods sub-indices/measures | O1: Notas | P1: Dudas
A2: 10 | B2: {=_xlfn.LET( _xlpm.ids, VALUE(_xlfn.TEXTSPLIT(SUBSTITUTE(A2,",",";"), ";", " ", TRUE)), _xlpm.status_list, _xlfn.MAP(_xlpm.ids, _xlfn.LAMBDA(_xlpm.id, _xlfn.LET( _xlpm.lookup_val, _xlfn.XLOOKUP(_xlpm.id, 'Article list'!$A$2:$A$995, 'Article list'!$H$2:$H$995, ""), AND(_xlpm.lookup_val <> "", _xlpm.lookup_val <> 0) ) )), _xlpm.total_count, COUNTA(_xlpm.ids), _xlpm.excluded_count, SUM(--_xlpm.status_list), _xlfn.IFS( _xlpm.excluded_count = _xlpm.total_count, TRUE, _xlpm.excluded_count = 0, FALSE, TRUE, "partial" ) )} -> TRUE | C2: Safety | D2: Personal Safety | E2: Public services | F2: ? | G2: quantity | M2: Security (Number of securing devices/arrangements) | N2: ['Fuzzy DEMATEL', 'Weighted Linear Combination (WLC),']
A3: 1 | B3: {=_xlfn.LET( _xlpm.ids, VALUE(_xlfn.TEXTSPLIT(SUBSTITUTE(A3,",",";"), ";", " ", TRUE)), _xlpm.status_list, _xlfn.MAP(_xlpm.ids, _xlfn.LAMBDA(_xlpm.id, _xlfn.LET( _xlpm.lookup_val, _xlfn.XLOOKUP(_xlpm.id, 'Article list'!$A$2:$A$995, 'Article list'!$H$2:$H$995, ""), AND(_xlpm.lookup_val <> "", _xlpm.lookup_val <> 0) ) )), _xlpm.total_count, COUNTA(_xlpm.ids), _xlpm.excluded_count, SUM(--_xlpm.status_list), _xlfn.IFS( _xlpm.excluded_count = _xlpm.total_count, TRUE, _xlpm.excluded_count = 0, FALSE, TRUE, "partial" ) )} -> TRUE | C3: Safety | D3: Personal Safety | F3: ? | M3: Building front/facxade | N3: ['Delphi', "Kendall's coefficient", "Cronbach's alpha value"]
A4: 1 | B4: {=_xlfn.LET( _xlpm.ids, VALUE(_xlfn.TEXTSPLIT(SUBSTITUTE(A4,",",";"), ";", " ", TRUE)), _xlpm.status_list, _xlfn.MAP(_xlpm.ids, _xlfn.LAMBDA(_xlpm.id, _xlfn.LET( _xlpm.lookup_val, _xlfn.XLOOKUP(_xlpm.id, 'Article list'!$A$2:$A$995, 'Article list'!$H$2:$H$995, ""), AND(_xlpm.lookup_val <> "", _xlpm.lookup_val <> 0) ) )), _xlpm.total_count, COUNTA(_xlpm.ids), _xlpm.excluded_count, SUM(--_xlpm.status_list), _xlfn.IFS( _xlpm.excluded_count = _xlpm.total_count, TRUE, _xlpm.excluded_count = 0, FALSE, TRUE, "partial" ) )} -> TRUE | C4: Safety | D4: Road Safety | E4: Pedestrian Infrastructure | F4: ? | G4: Presence | M4: Guard rails | N4: ['Delphi', "Kendall's coefficient", "Cronbach's alpha value"]
A5: 23 | B5: {=_xlfn.LET( _xlpm.ids, VALUE(_xlfn.TEXTSPLIT(SUBSTITUTE(A5,",",";"), ";", " ", TRUE)), _xlpm.status_list, _xlfn.MAP(_xlpm.ids, _xlfn.LAMBDA(_xlpm.id, _xlfn.LET( _xlpm.lookup_val, _xlfn.XLOOKUP(_xlpm.id, 'Article list'!$A$2:$A$995, 'Article list'!$H$2:$H$995, ""), AND(_xlpm.lookup_val <> "", _xlpm.lookup_val <> 0) ) )), _xlpm.total_count, COUNTA(_xlpm.ids), _xlpm.excluded_count, SUM(--_xlpm.status_list), _xlfn.IFS( _xlpm.excluded_count = _xlpm.total_count, TRUE, _xlpm.excluded_count = 0, FALSE, TRUE, "partial" ) )} -> FALSE | C5: Safety | D5: Road Safety | E5: Pedestrian Infrastructure | F5: ? | G5: Quality | M5: SN6 Streetscape design | N5: ['Design Analysis']
A6: 18 | B6: {=_xlfn.LET( _xlpm.ids, VALUE(_xlfn.TEXTSPLIT(SUBSTITUTE(A6,",",";"), ";", " ", TRUE)), _xlpm.status_list, _xlfn.MAP(_xlpm.ids, _xlfn.LAMBDA(_xlpm.id, _xlfn.LET( _xlpm.lookup_val, _xlfn.XLOOKUP(_xlpm.id, 'Article list'!$A$2:$A$995, 'Article list'!$H$2:$H$995, ""), AND(_xlpm.lookup_val <> "", _xlpm.lookup_val <> 0) ) )), _xlpm.total_count, COUNTA(_xlpm.ids), _xlpm.excluded_count, SUM(--_xlpm.status_list), _xlfn.IFS( _xlpm.excluded_count = _xlpm.total_count, TRUE, _xlpm.excluded_count = 0, FALSE, TRUE, "partial" ) )} -> FALSE | C6: Safety | D6: Personal Safety | E6: Public Services | F6: Fire station | G6: Proximity | H6: Distance (m) | M6: Distance to fire station | N6: ['Analytic Hierarchy Process (AHP)']
A7: 16 | B7: {=_xlfn.LET( _xlpm.ids, VALUE(_xlfn.TEXTSPLIT(SUBSTITUTE(A7,",",";"), ";", " ", TRUE)), _xlpm.status_list, _xlfn.MAP(_xlpm.ids, _xlfn.LAMBDA(_xlpm.id, _xlfn.LET( _xlpm.lookup_val, _xlfn.XLOOKUP(_xlpm.id, 'Article list'!$A$2:$A$995, 'Article list'!$H$2:$H$995, ""), AND(_xlpm.lookup_val <> "", _xlpm.lookup_val <> 0) ) )), _xlpm.total_count, COUNTA(_xlpm.ids), _xlpm.excluded_count, SUM(--_xlpm.status_list), _xlfn.IFS( _xlpm.excluded_count = _xlpm.total_count, TRUE, _xlpm.excluded_count = 0, FALSE, TRUE, "partial" ) )} -> FALSE | C7: Safety | D7: Personal Safety | E7: Public Services | F7: Fire station | G7: Quantity | M7: Number of fire station | N7: ['Exploratory Factor Analysis', 'Standard Deviational Ellipse,', 'Hot Spot Analysis,', 'Network Analysis']
A8: 23 | B8: {=_xlfn.LET( _xlpm.ids, VALUE(_xlfn.TEXTSPLIT(SUBSTITUTE(A8,",",";"), ";", " ", TRUE)), _xlpm.status_list, _xlfn.MAP(_xlpm.ids, _xlfn.LAMBDA(_xlpm.id, _xlfn.LET( _xlpm.lookup_val, _xlfn.XLOOKUP(_xlpm.id, 'Article list'!$A$2:$A$995, 'Article list'!$H$2:$H$995, ""), AND(_xlpm.lookup_val <> "", _xlpm.lookup_val <> 0) ) )), _xlpm.total_count, COUNTA(_xlpm.ids), _xlpm.excluded_count, SUM(--_xlpm.status_list), _xlfn.IFS( _xlpm.excluded_count = _xlpm.total_count, TRUE, _xlpm.excluded_count = 0, FALSE, TRUE, "partial" ) )} -> FALSE | C8: Safety | D8: Road Safety | E8: Pedestrian Infrastructure | F8: Footpaths | G8: Quality | M8: SN10 Walking friendly environment | N8: ['Design Analysis']
A9: 23 | B9: {=_xlfn.LET( _xlpm.ids, VALUE(_xlfn.TEXTSPLIT(SUBSTITUTE(A9,",",";"), ";", " ", TRUE)), _xlpm.status_list, _xlfn.MAP(_xlpm.ids, _xlfn.LAMBDA(_xlpm.id, _xlfn.LET( _xlpm.lookup_val, _xlfn.XLOOKUP(_xlpm.id, 'Article list'!$A$2:$A$995, 'Article list'!$H$2:$H$995, ""), AND(_xlpm.lookup_val <> "", _xlpm.lookup_val <> 0) ) )), _xlpm.total_count, COUNTA(_xlpm.ids), _xlpm.excluded_count, SUM(--_xlpm.status_list), _xlfn.IFS( _xlpm.excluded_count = _xlpm.total_count, TRUE, _xlpm.excluded_count = 0, FALSE, TRUE, "partial" ) )} -> FALSE | C9: Safety | D9: Road Safety | E9: Pedestrian Infrastructure | F9: Footpaths | G9: Quantity | M9: SN2 Total footpath provision | N9: ['Design Analysis']
A10: 23 | B10: {=_xlfn.LET( _xlpm.ids, VALUE(_xlfn.TEXTSPLIT(SUBSTITUTE(A10,",",";"), ";", " ", TRUE)), _xlpm.status_list, _xlfn.MAP(_xlpm.ids, _xlfn.LAMBDA(_xlpm.id, _xlfn.LET( _xlpm.lookup_val, _xlfn.XLOOKUP(_xlpm.id, 'Article list'!$A$2:$A$995, 'Article list'!$H$2:$H$995, ""), AND(_xlpm.lookup_val <> "", _xlpm.lookup_val <> 0) ) )), _xlpm.total_count, COUNTA(_xlpm.ids), _xlpm.excluded_count, SUM(--_xlpm.status_list), _xlfn.IFS( _xlpm.excluded_count = _xlpm.total_count, TRUE, _xlpm.excluded_count = 0, FALSE, TRUE, "partial" ) )} -> FALSE | C10: Safety | D10: Road Safety | E10: Pedestrian Infrastructure | F10: Footpaths | G10: Quality | M10: SN5 Appropriate width of the footpaths and side walks | N10: ['Design Analysis']
A11: 12 | B11: {=_xlfn.LET( _xlpm.ids, VALUE(_xlfn.TEXTSPLIT(SUBSTITUTE(A11,",",";"), ";", " ", TRUE)), _xlpm.status_list, _xlfn.MAP(_xlpm.ids, _xlfn.LAMBDA(_xlpm.id, _xlfn.LET( _xlpm.lookup_val, _xlfn.XLOOKUP(_xlpm.id, 'Article list'!$A$2:$A$995, 'Article list'!$H$2:$H$995, ""), AND(_xlpm.lookup_val <> "", _xlpm.lookup_val <> 0) ) )), _xlpm.total_count, COUNTA(_xlpm.ids), _xlpm.excluded_count, SUM(--_xlpm.status_list), _xlfn.IFS( _xlpm.excluded_count = _xlpm.total_count, TRUE, _xlpm.excluded_count = 0, FALSE, TRUE, "partial" ) )} -> FALSE | C11: Safety | D11: Personal Safety | E11: Public services | F11: Opinion | G11: Quality | H11: Area? | I11: Participación ciudadana | M11: Contact with city officials | N11: ['Likert Scale Measurement', 'One-Way ANOVA', 'Descriptive Statistics', 'Post Hoc (Tukey) Test', 'Mann-Whitney U Test', 'Qualitative Thematic Analysis']
A12: 12 | B12: {=_xlfn.LET( _xlpm.ids, VALUE(_xlfn.TEXTSPLIT(SUBSTITUTE(A12,",",";"), ";", " ", TRUE)), _xlpm.status_list, _xlfn.MAP(_xlpm.ids, _xlfn.LAMBDA(_xlpm.id, _xlfn.LET( _xlpm.lookup_val, _xlfn.XLOOKUP(_xlpm.id, 'Article list'!$A$2:$A$995, 'Article list'!$H$2:$H$995, ""), AND(_xlpm.lookup_val <> "", _xlpm.lookup_val <> 0) ) )), _xlpm.total_count, COUNTA(_xlpm.ids), _xlpm.excluded_count, SUM(--_xlpm.status_list), _xlfn.IFS( _xlpm.excluded_count = _xlpm.total_count, TRUE, _xlpm.excluded_count = 0, FALSE, TRUE, "partial" ) )} -> FALSE | C12: Safety | D12: Personal Safety | E12: Public services | F12: Opinion | G12: Perception | M12: Overall perception of safety | N12: ['Likert Scale Measurement', 'One-Way ANOVA', 'Descriptive Statistics', 'Post Hoc (Tukey) Test', 'Mann-Whitney U Test', 'Qualitative Thematic Analysis']
A13: 12 | B13: {=_xlfn.LET( _xlpm.ids, VALUE(_xlfn.TEXTSPLIT(SUBSTITUTE(A13,",",";"), ";", " ", TRUE)), _xlpm.status_list, _xlfn.MAP(_xlpm.ids, _xlfn.LAMBDA(_xlpm.id, _xlfn.LET( _xlpm.lookup_val, _xlfn.XLOOKUP(_xlpm.id, 'Article list'!$A$2:$A$995, 'Article list'!$H$2:$H$995, ""), AND(_xlpm.lookup_val <> "", _xlpm.lookup_val <> 0) ) )), _xlpm.total_count, COUNTA(_xlpm.ids), _xlpm.excluded_count, SUM(--_xlpm.status_list), _xlfn.IFS( _xlpm.excluded_count = _xlpm.total_count, TRUE, _xlpm.excluded_count = 0, FALSE, TRUE, "partial" ) )} -> FALSE | C13: Safety | D13: Personal Safety | E13: Public services | F13: Opinion | G13: Perception | M13: Perceived degree of crime | N13: ['Likert Scale Measurement', 'One-Way ANOVA', 'Descriptive Statistics', 'Post Hoc (Tukey) Test', 'Mann-Whitney U Test', 'Qualitative Thematic Analysis']
A14: 12 | B14: {=_xlfn.LET( _xlpm.ids, VALUE(_xlfn.TEXTSPLIT(SUBSTITUTE(A14,",",";"), ";", " ", TRUE)), _xlpm.status_list, _xlfn.MAP(_xlpm.ids, _xlfn.LAMBDA(_xlpm.id, _xlfn.LET( _xlpm.lookup_val, _xlfn.XLOOKUP(_xlpm.id, 'Article list'!$A$2:$A$995, 'Article list'!$H$2:$H$995, ""), AND(_xlpm.lookup_val <> "", _xlpm.lookup_val <> 0) ) )), _xlpm.total_count, COUNTA(_xlpm.ids), _xlpm.excluded_count, SUM(--_xlpm.status_list), _xlfn.IFS( _xlpm.excluded_count = _xlpm.total_count, TRUE, _xlpm.excluded_count = 0, FALSE, TRUE, "partial" ) )} -> FALSE | C14: Safety | D14: Personal Safety | E14: Public services | F14: Opinion | G14: Perception | M14: Perceived fairness of taxation | N14: ['Likert Scale Measurement', 'One-Way ANOVA', 'Descriptive Statistics', 'Post Hoc (Tukey) Test', 'Mann-Whitney U Test', 'Qualitative Thematic Analysis']
A15: 11 | B15: {=_xlfn.LET( _xlpm.ids, VALUE(_xlfn.TEXTSPLIT(SUBSTITUTE(A15,",",";"), ";", " ", TRUE)), _xlpm.status_list, _xlfn.MAP(_xlpm.ids, _xlfn.LAMBDA(_xlpm.id, _xlfn.LET( _xlpm.lookup_val, _xlfn.XLOOKUP(_xlpm.id, 'Article list'!$A$2:$A$995, 'Article list'!$H$2:$H$995, ""), AND(_xlpm.lookup_val <> "", _xlpm.lookup_val <> 0) ) )), _xlpm.total_count, COUNTA(_xlpm.ids), _xlpm.excluded_count, SUM(--_xlpm.status_list), _xlfn.IFS( _xlpm.excluded_count = _xlpm.total_count, TRUE, _xlpm.excluded_count = 0, FALSE, TRUE, "partial" ) )} -> TRUE | C15: Safety | D15: Personal Safety | E15: Public services | F15: Opinion | G15: Perception | M15: Perceived safety during day-time and night-time | N15: ['Distance-based accessibility measures', 'Objective environmental and neighbourhood indicators', 'Resident perception surveys using 5-point Likert scales', 'Satisfaction-based scoring for each livability dimension']
A16: 12 | B16: {=_xlfn.LET( _xlpm.ids, VALUE(_xlfn.TEXTSPLIT(SUBSTITUTE(A16,",",";"), ";", " ", TRUE)), _xlpm.status_list, _xlfn.MAP(_xlpm.ids, _xlfn.LAMBDA(_xlpm.id, _xlfn.LET( _xlpm.lookup_val, _xlfn.XLOOKUP(_xlpm.id, 'Article list'!$A$2:$A$995, 'Article list'!$H$2:$H$995, ""), AND(_xlpm.lookup_val <> "", _xlpm.lookup_val <> 0) ) )), _xlpm.total_count, COUNTA(_xlpm.ids), _xlpm.excluded_count, SUM(--_xlpm.status_list), _xlfn.IFS( _xlpm.excluded_count = _xlpm.total_count, TRUE, _xlpm.excluded_count = 0, FALSE, TRUE, "partial" ) )} -> FALSE | C16: Safety | D16: Personal Safety | E16: Public services | F16: Opinion | G16: Quantity | M16: Petty crimes (shoplifting, bag snatching, pickpocketing) | N16: ['Likert Scale Measurement', 'One-Way ANOVA', 'Descriptive Statistics', 'Post Hoc (Tukey) Test', 'Mann-Whitney U Test', 'Qualitative Thematic Analysis']
A17: 26 | B17: {=_xlfn.LET( _xlpm.ids, VALUE(_xlfn.TEXTSPLIT(SUBSTITUTE(A17,",",";"), ";", " ", TRUE)), _xlpm.status_list, _xlfn.MAP(_xlpm.ids, _xlfn.LAMBDA(_xlpm.id, _xlfn.LET( _xlpm.lookup_val, _xlfn.XLOOKUP(_xlpm.id, 'Article list'!$A$2:$A$995, 'Article list'!$H$2:$H$995, ""), AND(_xlpm.lookup_val <> "", _xlpm.lookup_val <> 0) ) )), _xlpm.total_count, COUNTA(_xlpm.ids), _xlpm.excluded_count, SUM(--_xlpm.status_list), _xlfn.IFS( _xlpm.excluded_count = _xlpm.total_count, TRUE, _xlpm.excluded_count = 0, FALSE, TRUE, "partial" ) )} -> FALSE | C17: Safety | D17: Personal Safety | F17: Opinion | G17: Perception | M17: Improvement in public perception of safety from a rating of 3 to 2 on a 5-point scale; Security | N17: ['Delphi method', 'GIS-based spatial analysis'] | O17: Perception
A18: 26 | B18: {=_xlfn.LET( _xlpm.ids, VALUE(_xlfn.TEXTSPLIT(SUBSTITUTE(A18,",",";"), ";", " ", TRUE)), _xlpm.status_list, _xlfn.MAP(_xlpm.ids, _xlfn.LAMBDA(_xlpm.id, _xlfn.LET( _xlpm.lookup_val, _xlfn.XLOOKUP(_xlpm.id, 'Article list'!$A$2:$A$995, 'Article list'!$H$2:$H$995, ""), AND(_xlpm.lookup_val <> "", _xlpm.lookup_val <> 0) ) )), _xlpm.total_count, COUNTA(_xlpm.ids), _xlpm.excluded_count, SUM(--_xlpm.status_list), _xlfn.IFS( _xlpm.excluded_count = _xlpm.total_count, TRUE, _xlpm.excluded_count = 0, FALSE, TRUE, "partial" ) )} -> FALSE | C18: Safety | D18: Personal Safety | F18: Opinion | G18: Perception | M18: Maintenance of violent crime at a severity rating of 1 on a 5-point scale; Security | N18: ['Delphi method', 'GIS-based spatial analysis'] | O18: Perception
A19: 9 | B19: {=_xlfn.LET( _xlpm.ids, VALUE(_xlfn.TEXTSPLIT(SUBSTITUTE(A19,",",";"), ";", " ", TRUE)), _xlpm.status_list, _xlfn.MAP(_xlpm.ids, _xlfn.LAMBDA(_xlpm.id, _xlfn.LET( _xlpm.lookup_val, _xlfn.XLOOKUP(_xlpm.id, 'Article list'!$A$2:$A$995, 'Article list'!$H$2:$H$995, ""), AND(_xlpm.lookup_val <> "", _xlpm.lookup_val <> 0) ) )), _xlpm.total_count, COUNTA(_xlpm.ids), _xlpm.excluded_count, SUM(--_xlpm.status_list), _xlfn.IFS( _xlpm.excluded_count = _xlpm.total_count, TRUE, _xlpm.excluded_count = 0, FALSE, TRUE, "partial" ) )} -> TRUE | C19: Safety | D19: Personal Safety | F19: Opinion | G19: Quality | M19: Neighborhood safety | N19: ['N/A']
A20: 15 | B20: {=_xlfn.LET( _xlpm.ids, VALUE(_xlfn.TEXTSPLIT(SUBSTITUTE(A20,",",";"), ";", " ", TRUE)), _xlpm.status_list, _xlfn.MAP(_xlpm.ids, _xlfn.LAMBDA(_xlpm.id, _xlfn.LET( _xlpm.lookup_val, _xlfn.XLOOKUP(_xlpm.id, 'Article list'!$A$2:$A$995, 'Article list'!$H$2:$H$995, ""), AND(_xlpm.lookup_val <> "", _xlpm.lookup_val <> 0) ) )), _xlpm.total_count, COUNTA(_xlpm.ids), _xlpm.excluded_count, SUM(--_xlpm.status_list), _xlfn.IFS( _xlpm.excluded_count = _xlpm.total_count, TRUE, _xlpm.excluded_count = 0, FALSE, TRUE, "partial" ) )} -> FALSE | C20: Safety | D20: Personal Safety | F20: Opinion | G20: Quality | M20: Recreational areas interiors are visible from the outside | N20: ['Likert scale']
A21: 15 | B21: {=_xlfn.LET( _xlpm.ids, VALUE(_xlfn.TEXTSPLIT(SUBSTITUTE(A21,",",";"), ";", " ", TRUE)), _xlpm.status_list, _xlfn.MAP(_xlpm.ids, _xlfn.LAMBDA(_xlpm.id, _xlfn.LET( _xlpm.lookup_val, _xlfn.XLOOKUP(_xlpm.id, 'Article list'!$A$2:$A$995, 'Article list'!$H$2:$H$995, ""), AND(_xlpm.lookup_val <> "", _xlpm.lookup_val <> 0) ) )), _xlpm.total_count, COUNTA(_xlpm.ids), _xlpm.excluded_count, SUM(--_xlpm.status_list), _xlfn.IFS( _xlpm.excluded_count = _xlpm.total_count, TRUE, _xlpm.excluded_count = 0, FALSE, TRUE, "partial" ) )} -> FALSE | C21: Safety | D21: Personal Safety | F21: Opinion | G21: Quality; Proximity | M21: Recreational areas are clearly visible from a distance | N21: ['Likert scale']
A22: 12 | B22: {=_xlfn.LET( _xlpm.ids, VALUE(_xlfn.TEXTSPLIT(SUBSTITUTE(A22,",",";"), ";", " ", TRUE)), _xlpm.status_list, _xlfn.MAP(_xlpm.ids, _xlfn.LAMBDA(_xlpm.id, _xlfn.LET( _xlpm.lookup_val, _xlfn.XLOOKUP(_xlpm.id, 'Article list'!$A$2:$A$995, 'Article list'!$H$2:$H$995, ""), AND(_xlpm.lookup_val <> "", _xlpm.lookup_val <> 0) ) )), _xlpm.total_count, COUNTA(_xlpm.ids), _xlpm.excluded_count, SUM(--_xlpm.status_list), _xlfn.IFS( _xlpm.excluded_count = _xlpm.total_count, TRUE, _xlpm.excluded_count = 0, FALSE, TRUE, "partial" ) )} -> FALSE | C22: Safety | D22: Road Safety | E22: Pedestrian infrastructure | F22: Opinion | G22: Quality | M22: Movement hazards for children, elderly and disabled | N22: ['Likert Scale Measurement', 'One-Way ANOVA', 'Descriptive Statistics', 'Post Hoc (Tukey) Test', 'Mann-Whitney U Test', 'Qualitative Thematic Analysis']
A23: 21 | B23: {=_xlfn.LET( _xlpm.ids, VALUE(_xlfn.TEXTSPLIT(SUBSTITUTE(A23,",",";"), ";", " ", TRUE)), _xlpm.status_list, _xlfn.MAP(_xlpm.ids, _xlfn.LAMBDA(_xlpm.id, _xlfn.LET( _xlpm.lookup_val, _xlfn.XLOOKUP(_xlpm.id, 'Article list'!$A$2:$A$995, 'Article list'!$H$2:$H$995, ""), AND(_xlpm.lookup_val <> "", _xlpm.lookup_val <> 0) ) )), _xlpm.total_count, COUNTA(_xlpm.ids), _xlpm.excluded_count, SUM(--_xlpm.status_list), _xlfn.IFS( _xlpm.excluded_count = _xlpm.total_count, TRUE, _xlpm.excluded_count = 0, FALSE, TRUE, "partial" ) )} -> TRUE | C23: Safety | D23: Road Safety | F23: Opinion | M23: Accidents and Safety | N23: ['Kernel Density Estimation (KDE) to identify spatial clusters of walkability-related features', 'Line Density Analysis to measure connectivity of pedestrian infrastructure. These methods complement each other by capturing both the qualitative and quantitative aspects of walkability'] | P23: Determine the correct indicator category
A24: 6 | B24: {=_xlfn.LET( _xlpm.ids, VALUE(_xlfn.TEXTSPLIT(SUBSTITUTE(A24,",",";"), ";", " ", TRUE)), _xlpm.status_list, _xlfn.MAP(_xlpm.ids, _xlfn.LAMBDA(_xlpm.id, _xlfn.LET( _xlpm.lookup_val, _xlfn.XLOOKUP(_xlpm.id, 'Article list'!$A$2:$A$995, 'Article list'!$H$2:$H$995, ""), AND(_xlpm.lookup_val <> "", _xlpm.lookup_val <> 0) ) )), _xlpm.total_count, COUNTA(_xlpm.ids), _xlpm.excluded_count, SUM(--_xlpm.status_list), _xlfn.IFS( _xlpm.excluded_count = _xlpm.total_count, TRUE, _xlpm.excluded_count = 0, FALSE, TRUE, "partial" ) )} -> TRUE | C24: Safety | F24: Opinion | M24: Passive Surveillance | N24: ['Delphi Process', 'Analytic Hierarchy Process']
A25: 18;20;21;8 | B25: {=_xlfn.LET( _xlpm.ids, VALUE(_xlfn.TEXTSPLIT(SUBSTITUTE(A25,",",";"), ";", " ", TRUE)), _xlpm.status_list, _xlfn.MAP(_xlpm.ids, _xlfn.LAMBDA(_xlpm.id, _xlfn.LET( _xlpm.lookup_val, _xlfn.XLOOKUP(_xlpm.id, 'Article list'!$A$2:$A$995, 'Article list'!$H$2:$H$995, ""), AND(_xlpm.lookup_val <> "", _xlpm.lookup_val <> 0) ) )), _xlpm.total_count, COUNTA(_xlpm.ids), _xlpm.excluded_count, SUM(--_xlpm.status_list), _xlfn.IFS( _xlpm.excluded_count = _xlpm.total_count, TRUE, _xlpm.excluded_count = 0, FALSE, TRUE, "partial" ) )} -> partial | C25: Safety | D25: Personal Safety | E25: Public Services | F25: Police station | G25: Proximity | M25: Distance to police station | N25: 18: ['Analytic Hierarchy Process (AHP)'] 20: ['Proximity analysis following digitization and Euclidean distance computation'] 21: ['Kernel Density Estimation (KDE) to identify spatial clusters of walkability-related features', 'Line Density Analysis to measure connectivity of pedestrian infrastructure. These methods complement each other by capturing both the qualitative and quantitative aspects of walkability'] 8: ['Hierarchical Modelling using Analytic Hierarchy Process (AHP)']
A26: 8 | B26: {=_xlfn.LET( _xlpm.ids, VALUE(_xlfn.TEXTSPLIT(SUBSTITUTE(A26,",",";"), ";", " ", TRUE)), _xlpm.status_list, _xlfn.MAP(_xlpm.ids, _xlfn.LAMBDA(_xlpm.id, _xlfn.LET( _xlpm.lookup_val, _xlfn.XLOOKUP(_xlpm.id, 'Article list'!$A$2:$A$995, 'Article list'!$H$2:$H$995, ""), AND(_xlpm.lookup_val <> "", _xlpm.lookup_val <> 0) ) )), _xlpm.total_count, COUNTA(_xlpm.ids), _xlpm.excluded_count, SUM(--_xlpm.status_list), _xlfn.IFS( _xlpm.excluded_count = _xlpm.total_count, TRUE, _xlpm.excluded_count = 0, FALSE, TRUE, "partial" ) )} -> FALSE | C26: Safety | D26: Personal Safety | E26: Public services | F26: Police station | G26: Presence; Proximity | M26: Location of Police station and mitigation office | N26: ['Hierarchical Modelling using Analytic Hierarchy Process (AHP)']
A27: 5 | B27: {=_xlfn.LET( _xlpm.ids, VALUE(_xlfn.TEXTSPLIT(SUBSTITUTE(A27,",",";"), ";", " ", TRUE)), _xlpm.status_list, _xlfn.MAP(_xlpm.ids, _xlfn.LAMBDA(_xlpm.id, _xlfn.LET( _xlpm.lookup_val, _xlfn.XLOOKUP(_xlpm.id, 'Article list'!$A$2:$A$995, 'Article list'!$H$2:$H$995, ""), AND(_xlpm.lookup_val <> "", _xlpm.lookup_val <> 0) ) )), _xlpm.total_count, COUNTA(_xlpm.ids), _xlpm.excluded_count, SUM(--_xlpm.status_list), _xlfn.IFS( _xlpm.excluded_count = _xlpm.total_count, TRUE, _xlpm.excluded_count = 0, FALSE, TRUE, "partial" ) )} -> FALSE | C27: Safety | D27: Personal Safety | E27: Public Services | F27: Police station | G27: Rate | M27: Police Outposts per 1000 persons | N27: ['Supervised classification in Erdas Imagine Software.', 'regression']
A28: 5 | B28: {=_xlfn.LET( _xlpm.ids, VALUE(_xlfn.TEXTSPLIT(SUBSTITUTE(A28,",",";"), ";", " ", TRUE)), _xlpm.status_list, _xlfn.MAP(_xlpm.ids, _xlfn.LAMBDA(_xlpm.id, _xlfn.LET( _xlpm.lookup_val, _xlfn.XLOOKUP(_xlpm.id, 'Article list'!$A$2:$A$995, 'Article list'!$H$2:$H$995, ""), AND(_xlpm.lookup_val <> "", _xlpm.lookup_val <> 0) ) )), _xlpm.total_count, COUNTA(_xlpm.ids), _xlpm.excluded_count, SUM(--_xlpm.status_list), _xlfn.IFS( _xlpm.excluded_count = _xlpm.total_count, TRUE, _xlpm.excluded_count = 0, FALSE, TRUE, "partial" ) )} -> FALSE | C28: Safety | D28: Personal Safety | E28: Public Services | F28: Police station | G28: Rate | M28: Police Stations per 1000 persons | N28: ['Supervised classification in Erdas Imagine Software.', 'regression']
A29: 13 | B29: {=_xlfn.LET( _xlpm.ids, VALUE(_xlfn.TEXTSPLIT(SUBSTITUTE(A29,",",";"), ";", " ", TRUE)), _xlpm.status_list, _xlfn.MAP(_xlpm.ids, _xlfn.LAMBDA(_xlpm.id, _xlfn.LET( _xlpm.lookup_val, _xlfn.XLOOKUP(_xlpm.id, 'Article list'!$A$2:$A$995, 'Article list'!$H$2:$H$995, ""), AND(_xlpm.lookup_val <> "", _xlpm.lookup_val <> 0) ) )), _xlpm.total_count, COUNTA(_xlpm.ids), _xlpm.excluded_count, SUM(--_xlpm.status_list), _xlfn.IFS( _xlpm.excluded_count = _xlpm.total_count, TRUE, _xlpm.excluded_count = 0, FALSE, TRUE, "partial" ) )} -> FALSE | C29: Safety | D29: Road Safety | E29: Pedestrian Infrastructure | F29: Road accident locations | G29: Quantity | H29: ? | M29: Number of locations with reported road accidents | N29: ['Identification of measurable spatial indicators, how they can me calculated and monitored']
A30: 8 | B30: {=_xlfn.LET( _xlpm.ids, VALUE(_xlfn.TEXTSPLIT(SUBSTITUTE(A30,",",";"), ";", " ", TRUE)), _xlpm.status_list, _xlfn.MAP(_xlpm.ids, _xlfn.LAMBDA(_xlpm.id, _xlfn.LET( _xlpm.lookup_val, _xlfn.XLOOKUP(_xlpm.id, 'Article list'!$A$2:$A$995, 'Article list'!$H$2:$H$995, ""), AND(_xlpm.lookup_val <> "", _xlpm.lookup_val <> 0) ) )), _xlpm.total_count, COUNTA(_xlpm.ids), _xlpm.excluded_count, SUM(--_xlpm.status_list), _xlfn.IFS( _xlpm.excluded_count = _xlpm.total_count, TRUE, _xlpm.excluded_count = 0, FALSE, TRUE, "partial" ) )} -> FALSE | C30: Safety | D30: Personal Safety | F30: Statistic | G30: Quantity | M30: Casualty | N30: ['Hierarchical Modelling using Analytic Hierarchy Process (AHP)']
A31: 8 | B31: {=_xlfn.LET( _xlpm.ids, VALUE(_xlfn.TEXTSPLIT(SUBSTITUTE(A31,",",";"), ";", " ", TRUE)), _xlpm.status_list, _xlfn.MAP(_xlpm.ids, _xlfn.LAMBDA(_xlpm.id, _xlfn.LET( _xlpm.lookup_val, _xlfn.XLOOKUP(_xlpm.id, 'Article list'!$A$2:$A$995, 'Article list'!$H$2:$H$995, ""), AND(_xlpm.lookup_val <> "", _xlpm.lookup_val <> 0) ) )), _xlpm.total_count, COUNTA(_xlpm.ids), _xlpm.excluded_count, SUM(--_xlpm.status_list), _xlfn.IFS( _xlpm.excluded_count = _xlpm.total_count, TRUE, _xlpm.excluded_count = 0, FALSE, TRUE, "partial" ) )} -> FALSE | C31: Safety | D31: Personal Safety | F31: Statistic | G31: Presence | M31: Crime | N31: ['Hierarchical Modelling using Analytic Hierarchy Process (AHP)']
A32: 1;6;21 | B32: {=_xlfn.LET( _xlpm.ids, VALUE(_xlfn.TEXTSPLIT(SUBSTITUTE(A32,",",";"), ";", " ", TRUE)), _xlpm.status_list, _xlfn.MAP(_xlpm.ids, _xlfn.LAMBDA(_xlpm.id, _xlfn.LET( _xlpm.lookup_val, _xlfn.XLOOKUP(_xlpm.id, 'Article list'!$A$2:$A$995, 'Article list'!$H$2:$H$995, ""), AND(_xlpm.lookup_val <> "", _xlpm.lookup_val <> 0) ) )), _xlpm.total_count, COUNTA(_xlpm.ids), _xlpm.excluded_count, SUM(--_xlpm.status_list), _xlfn.IFS( _xlpm.excluded_count = _xlpm.total_count, TRUE, _xlpm.excluded_count = 0, FALSE, TRUE, "partial" ) )} -> TRUE | C32: Safety | D32: Personal Safety | F32: Statistic | G32: Rate | M32: Crime rate
A33: 17 | B33: {=_xlfn.LET( _xlpm.ids, VALUE(_xlfn.TEXTSPLIT(SUBSTITUTE(A33,",",";"), ";", " ", TRUE)), _xlpm.status_list, _xlfn.MAP(_xlpm.ids, _xlfn.LAMBDA(_xlpm.id, _xlfn.LET( _xlpm.lookup_val, _xlfn.XLOOKUP(_xlpm.id, 'Article list'!$A$2:$A$995, 'Article list'!$H$2:$H$995, ""), AND(_xlpm.lookup_val <> "", _xlpm.lookup_val <> 0) ) )), _xlpm.total_count, COUNTA(_xlpm.ids), _xlpm.excluded_count, SUM(--_xlpm.status_list), _xlfn.IFS( _xlpm.excluded_count = _xlpm.total_count, TRUE, _xlpm.excluded_count = 0, FALSE, TRUE, "partial" ) )} -> FALSE | C33: Safety | D33: Road safety | E33: Pedestrian infrastructure | F33: Statistic | G33: Quantity | H33: Area | M33: Traffic accident fatalities | N33: ['Not specified']
A34: 6 | B34: {=_xlfn.LET( _xlpm.ids, VALUE(_xlfn.TEXTSPLIT(SUBSTITUTE(A34,",",";"), ";", " ", TRUE)), _xlpm.status_list, _xlfn.MAP(_xlpm.ids, _xlfn.LAMBDA(_xlpm.id, _xlfn.LET( _xlpm.lookup_val, _xlfn.XLOOKUP(_xlpm.id, 'Article list'!$A$2:$A$995, 'Article list'!$H$2:$H$995, ""), AND(_xlpm.lookup_val <> "", _xlpm.lookup_val <> 0) ) )), _xlpm.total_count, COUNTA(_xlpm.ids), _xlpm.excluded_count, SUM(--_xlpm.status_list), _xlfn.IFS( _xlpm.excluded_count = _xlpm.total_count, TRUE, _xlpm.excluded_count = 0, FALSE, TRUE, "partial" ) )} -> TRUE | C34: Safety | D34: Road safety | E34: Pedestrian Infrastructure; Cycling Infrastructure | F34: Statistic | G34: Rate | H34: Area | M34: Ped-vehicle crash rate/ Ped fatality rate | N34: ['Delphi Process', 'Analytic Hierarchy Process']
A35: 10 | B35: {=_xlfn.LET( _xlpm.ids, VALUE(_xlfn.TEXTSPLIT(SUBSTITUTE(A35,",",";"), ";", " ", TRUE)), _xlpm.status_list, _xlfn.MAP(_xlpm.ids, _xlfn.LAMBDA(_xlpm.id, _xlfn.LET( _xlpm.lookup_val, _xlfn.XLOOKUP(_xlpm.id, 'Article list'!$A$2:$A$995, 'Article list'!$H$2:$H$995, ""), AND(_xlpm.lookup_val <> "", _xlpm.lookup_val <> 0) ) )), _xlpm.total_count, COUNTA(_xlpm.ids), _xlpm.excluded_count, SUM(--_xlpm.status_list), _xlfn.IFS( _xlpm.excluded_count = _xlpm.total_count, TRUE, _xlpm.excluded_count = 0, FALSE, TRUE, "partial" ) )} -> TRUE | C35: Safety | D35: Personal Safety | E35: Public services | F35: Street light infrastructure | G35: Quality | M35: Illumination | N35: ['Fuzzy DEMATEL', 'Weighted Linear Combination (WLC),']
A36: 6 | B36: {=_xlfn.LET( _xlpm.ids, VALUE(_xlfn.TEXTSPLIT(SUBSTITUTE(A36,",",";"), ";", " ", TRUE)), _xlpm.status_list, _xlfn.MAP(_xlpm.ids, _xlfn.LAMBDA(_xlpm.id, _xlfn.LET( _xlpm.lookup_val, _xlfn.XLOOKUP(_xlpm.id, 'Article list'!$A$2:$A$995, 'Article list'!$H$2:$H$995, ""), AND(_xlpm.lookup_val <> "", _xlpm.lookup_val <> 0) ) )), _xlpm.total_count, COUNTA(_xlpm.ids), _xlpm.excluded_count, SUM(--_xlpm.status_list), _xlfn.IFS( _xlpm.excluded_count = _xlpm.total_count, TRUE, _xlpm.excluded_count = 0, FALSE, TRUE, "partial" ) )} -> TRUE | C36: Safety | D36: Road safety | E36: Pedestrian Infrastructure | F36: Street light infrastructure | G36: Quantity; Presence | M36: Lighting/ Clear visibility | N36: ['Delphi Process', 'Analytic Hierarchy Process']
A37: 23 | B37: {=_xlfn.LET( _xlpm.ids, VALUE(_xlfn.TEXTSPLIT(SUBSTITUTE(A37,",",";"), ";", " ", TRUE)), _xlpm.status_list, _xlfn.MAP(_xlpm.ids, _xlfn.LAMBDA(_xlpm.id, _xlfn.LET( _xlpm.lookup_val, _xlfn.XLOOKUP(_xlpm.id, 'Article list'!$A$2:$A$995, 'Article list'!$H$2:$H$995, ""), AND(_xlpm.lookup_val <> "", _xlpm.lookup_val <> 0) ) )), _xlpm.total_count, COUNTA(_xlpm.ids), _xlpm.excluded_count, SUM(--_xlpm.status_list), _xlfn.IFS( _xlpm.excluded_count = _xlpm.total_count, TRUE, _xlpm.excluded_count = 0, FALSE, TRUE, "partial" ) )} -> FALSE | C37: Safety | D37: Road Safety | E37: Pedestrian Infrastructure | F37: Street light infrastructure | G37: Quality | M37: SN4 Well-lit pedestrian network | N37: ['Field observation']
A38: 13 | B38: {=_xlfn.LET( _xlpm.ids, VALUE(_xlfn.TEXTSPLIT(SUBSTITUTE(A38,",",";"), ";", " ", TRUE)), _xlpm.status_list, _xlfn.MAP(_xlpm.ids, _xlfn.LAMBDA(_xlpm.id, _xlfn.LET( _xlpm.lookup_val, _xlfn.XLOOKUP(_xlpm.id, 'Article list'!$A$2:$A$995, 'Article list'!$H$2:$H$995, ""), AND(_xlpm.lookup_val <> "", _xlpm.lookup_val <> 0) ) )), _xlpm.total_count, COUNTA(_xlpm.ids), _xlpm.excluded_count, SUM(--_xlpm.status_list), _xlfn.IFS( _xlpm.excluded_count = _xlpm.total_count, TRUE, _xlpm.excluded_count = 0, FALSE, TRUE, "partial" ) )} -> FALSE | C38: Safety | D38: Road Safety | E38: Pedestrian Infrastructure | G38: Quantity | H38: ? | M38: Number of main road traffic jams | N38: ['Identification of measurable spatial indicators, how they can me calculated and monitored']

Sheet Mobility & Transport
A1: Article # | B1: Excluded? | C1: Domain | D1: Subdomain | E1: Indicator / Category | F1: Subject | G1: Specific Measure lens / Enfoque | H1: Scale | I1: Mexicali indicator | J1: Specific measures (from literature) | K1: Methods sub-indices/measures | L1: Notas | M1: Dudas | N1: Does it matter? | O1: Can we calculate this? Do we have data? | P1: What is the most pragmatic way of measuring it?
A2: 27 | B2: {=_xlfn.LET( _xlpm.ids, VALUE(_xlfn.TEXTSPLIT(SUBSTITUTE(A2,",",";"), ";", " ", TRUE)), _xlpm.status_list, _xlfn.MAP(_xlpm.ids, _xlfn.LAMBDA(_xlpm.id, _xlfn.LET( _xlpm.lookup_val, _xlfn.XLOOKUP(_xlpm.id, 'Article list'!$A$2:$A$995, 'Article list'!$H$2:$H$995, ""), AND(_xlpm.lookup_val <> "", _xlpm.lookup_val <> 0) ) )), _xlpm.total_count, COUNTA(_xlpm.ids), _xlpm.excluded_count, SUM(--_xlpm.status_list), _xlfn.IFS( _xlpm.excluded_count = _xlpm.total_count, TRUE, _xlpm.excluded_count = 0, FALSE, TRUE, "partial" ) )} -> FALSE | C2: Mobility & Transport | D2: Active Travel | E2: Cycling Infrastructure | G2: Presence | J2: Bikeability and biking lane availability; Infrastructure and Accessibility
A3: 23 | B3: {=_xlfn.LET( _xlpm.ids, VALUE(_xlfn.TEXTSPLIT(SUBSTITUTE(A3,",",";"), ";", " ", TRUE)), _xlpm.status_list, _xlfn.MAP(_xlpm.ids, _xlfn.LAMBDA(_xlpm.id, _xlfn.LET( _xlpm.lookup_val, _xlfn.XLOOKUP(_xlpm.id, 'Article list'!$A$2:$A$995, 'Article list'!$H$2:$H$995, ""), AND(_xlpm.lookup_val <> "", _xlpm.lookup_val <> 0) ) )), _xlpm.total_count, COUNTA(_xlpm.ids), _xlpm.excluded_count, SUM(--_xlpm.status_list), _xlfn.IFS( _xlpm.excluded_count = _xlpm.total_count, TRUE, _xlpm.excluded_count = 0, FALSE, TRUE, "partial" ) )} -> FALSE | C3: Mobility & Transport | D3: Active Travel | E3: Cycling infrastructure: Pedestrian infrastructure | G3: Accessibility | J3: SN11 Interconnected streets pedestrian and cyclist networks | K3: ['Design Analysis', 'Field observation', 'Airflow simulations', 'Daylight simulations']
A4: 23 | B4: {=_xlfn.LET( _xlpm.ids, VALUE(_xlfn.TEXTSPLIT(SUBSTITUTE(A4,",",";"), ";", " ", TRUE)), _xlpm.status_list, _xlfn.MAP(_xlpm.ids, _xlfn.LAMBDA(_xlpm.id, _xlfn.LET( _xlpm.lookup_val, _xlfn.XLOOKUP(_xlpm.id, 'Article list'!$A$2:$A$995, 'Article list'!$H$2:$H$995, ""), AND(_xlpm.lookup_val <> "", _xlpm.lookup_val <> 0) ) )), _xlpm.total_count, COUNTA(_xlpm.ids), _xlpm.excluded_count, SUM(--_xlpm.status_list), _xlfn.IFS( _xlpm.excluded_count = _xlpm.total_count, TRUE, _xlpm.excluded_count = 0, FALSE, TRUE, "partial" ) )} -> FALSE | C4: Mobility & Transport | D4: Active Travel | E4: Cycling infrastructure: Pedestrian infrastructure | G4: Quantity | J4: SN8 Promoting movement: walking and cycling in side alleys | K4: [Space syntax analysis', 'Field observation'] | M4: enfoque?
A5: 27 | B5: {=_xlfn.LET( _xlpm.ids, VALUE(_xlfn.TEXTSPLIT(SUBSTITUTE(A5,",",";"), ";", " ", TRUE)), _xlpm.status_list, _xlfn.MAP(_xlpm.ids, _xlfn.LAMBDA(_xlpm.id, _xlfn.LET( _xlpm.lookup_val, _xlfn.XLOOKUP(_xlpm.id, 'Article list'!$A$2:$A$995, 'Article list'!$H$2:$H$995, ""), AND(_xlpm.lookup_val <> "", _xlpm.lookup_val <> 0) ) )), _xlpm.total_count, COUNTA(_xlpm.ids), _xlpm.excluded_count, SUM(--_xlpm.status_list), _xlfn.IFS( _xlpm.excluded_count = _xlpm.total_count, TRUE, _xlpm.excluded_count = 0, FALSE, TRUE, "partial" ) )} -> FALSE | C5: Mobility & Transport | D5: Active Travel | E5: Cycling Infrastructure; Pedestrian Infrastructure | G5: Quality | J5: Well-maintained streets
A6: 6 | B6: {=_xlfn.LET( _xlpm.ids, VALUE(_xlfn.TEXTSPLIT(SUBSTITUTE(A6,",",";"), ";", " ", TRUE)), _xlpm.status_list, _xlfn.MAP(_xlpm.ids, _xlfn.LAMBDA(_xlpm.id, _xlfn.LET( _xlpm.lookup_val, _xlfn.XLOOKUP(_xlpm.id, 'Article list'!$A$2:$A$995, 'Article list'!$H$2:$H$995, ""), AND(_xlpm.lookup_val <> "", _xlpm.lookup_val <> 0) ) )), _xlpm.total_count, COUNTA(_xlpm.ids), _xlpm.excluded_count, SUM(--_xlpm.status_list), _xlfn.IFS( _xlpm.excluded_count = _xlpm.total_count, TRUE, _xlpm.excluded_count = 0, FALSE, TRUE, "partial" ) )} -> TRUE | C6: Mobility & Transport | D6: Active travel | E6: Pedestrian Infrastructure | G6: Presence | J6: Bollards | K6: ['Delphi Process', 'Analytic Hierarchy Process']
A7: 6 | B7: {=_xlfn.LET( _xlpm.ids, VALUE(_xlfn.TEXTSPLIT(SUBSTITUTE(A7,",",";"), ";", " ", TRUE)), _xlpm.status_list, _xlfn.MAP(_xlpm.ids, _xlfn.LAMBDA(_xlpm.id, _xlfn.LET( _xlpm.lookup_val, _xlfn.XLOOKUP(_xlpm.id, 'Article list'!$A$2:$A$995, 'Article list'!$H$2:$H$995, ""), AND(_xlpm.lookup_val <> "", _xlpm.lookup_val <> 0) ) )), _xlpm.total_count, COUNTA(_xlpm.ids), _xlpm.excluded_count, SUM(--_xlpm.status_list), _xlfn.IFS( _xlpm.excluded_count = _xlpm.total_count, TRUE, _xlpm.excluded_count = 0, FALSE, TRUE, "partial" ) )} -> TRUE | C7: Mobility & Transport | D7: Active travel | E7: Pedestrian Infrastructure | G7: Quantity; Quality | J7: Continuity/ No of Kerb cuts | K7: ['Delphi Process', 'Analytic Hierarchy Process']
A8: 1; 6 | B8: {=_xlfn.LET( _xlpm.ids, VALUE(_xlfn.TEXTSPLIT(SUBSTITUTE(A8,",",";"), ";", " ", TRUE)), _xlpm.status_list, _xlfn.MAP(_xlpm.ids, _xlfn.LAMBDA(_xlpm.id, _xlfn.LET( _xlpm.lookup_val, _xlfn.XLOOKUP(_xlpm.id, 'Article list'!$A$2:$A$995, 'Article list'!$H$2:$H$995, ""), AND(_xlpm.lookup_val <> "", _xlpm.lookup_val <> 0) ) )), _xlpm.total_count, COUNTA(_xlpm.ids), _xlpm.excluded_count, SUM(--_xlpm.status_list), _xlfn.IFS( _xlpm.excluded_count = _xlpm.total_count, TRUE, _xlpm.excluded_count = 0, FALSE, TRUE, "partial" ) )} -> TRUE | C8: Mobility & Transport | D8: Road Safety | E8: Pedestrian Infrastructure | G8: Presence; Quantity | J8: Crossing facilities | K8: 1: 'Delphi', "Kendall's coefficient", "Cronbach's alpha value"] 6: ['Delphi Process', 'Analytic Hierarchy Process']
A9: 1; 6 | B9: {=_xlfn.LET( _xlpm.ids, VALUE(_xlfn.TEXTSPLIT(SUBSTITUTE(A9,",",";"), ";", " ", TRUE)), _xlpm.status_list, _xlfn.MAP(_xlpm.ids, _xlfn.LAMBDA(_xlpm.id, _xlfn.LET( _xlpm.lookup_val, _xlfn.XLOOKUP(_xlpm.id, 'Article list'!$A$2:$A$995, 'Article list'!$H$2:$H$995, ""), AND(_xlpm.lookup_val <> "", _xlpm.lookup_val <> 0) ) )), _xlpm.total_count, COUNTA(_xlpm.ids), _xlpm.excluded_count, SUM(--_xlpm.status_list), _xlfn.IFS( _xlpm.excluded_count = _xlpm.total_count, TRUE, _xlpm.excluded_count = 0, FALSE, TRUE, "partial" ) )} -> TRUE | C9: Mobility & Transport | D9: Road Safety | E9: Pedestrian Infrastructure | G9: Quality | J9: Curb height | K9: ['Delphi', "Kendall's coefficient", "Cronbach's alpha value"]
A10: 1; 6 | B10: {=_xlfn.LET( _xlpm.ids, VALUE(_xlfn.TEXTSPLIT(SUBSTITUTE(A10,",",";"), ";", " ", TRUE)), _xlpm.status_list, _xlfn.MAP(_xlpm.ids, _xlfn.LAMBDA(_xlpm.id, _xlfn.LET( _xlpm.lookup_val, _xlfn.XLOOKUP(_xlpm.id, 'Article list'!$A$2:$A$995, 'Article list'!$H$2:$H$995, ""), AND(_xlpm.lookup_val <> "", _xlpm.lookup_val <> 0) ) )), _xlpm.total_count, COUNTA(_xlpm.ids), _xlpm.excluded_count, SUM(--_xlpm.status_list), _xlfn.IFS( _xlpm.excluded_count = _xlpm.total_count, TRUE, _xlpm.excluded_count = 0, FALSE, TRUE, "partial" ) )} -> TRUE | C10: Mobility & Transport | D10: Road Safety | E10: Pedestrian Infrastructure | G10: Presence; Quantity | J10: Curb Ramps/Ramp gradient | K10: ['Delphi', "Kendall's coefficient", "Cronbach's alpha value"]
A11: 12 | B11: {=_xlfn.LET( _xlpm.ids, VALUE(_xlfn.TEXTSPLIT(SUBSTITUTE(A11,",",";"), ";", " ", TRUE)), _xlpm.status_list, _xlfn.MAP(_xlpm.ids, _xlfn.LAMBDA(_xlpm.id, _xlfn.LET( _xlpm.lookup_val, _xlfn.XLOOKUP(_xlpm.id, 'Article list'!$A$2:$A$995, 'Article list'!$H$2:$H$995, ""), AND(_xlpm.lookup_val <> "", _xlpm.lookup_val <> 0) ) )), _xlpm.total_count, COUNTA(_xlpm.ids), _xlpm.excluded_count, SUM(--_xlpm.status_list), _xlfn.IFS( _xlpm.excluded_count = _xlpm.total_count, TRUE, _xlpm.excluded_count = 0, FALSE, TRUE, "partial" ) )} -> FALSE | C11: Mobility & Transport | D11: Active travel | E11: Pedestrian infrastructure | G11: Safety; Accessibility | J11: Difficulty of movement | K11: ['Likert Scale Measurement', 'One-Way ANOVA', 'Descriptive Statistics', 'Post Hoc (Tukey) Test', 'Mann-Whitney U Test', 'Qualitative Thematic Analysis']
A12: 1; 6 | B12: {=_xlfn.LET( _xlpm.ids, VALUE(_xlfn.TEXTSPLIT(SUBSTITUTE(A12,",",";"), ";", " ", TRUE)), _xlpm.status_list, _xlfn.MAP(_xlpm.ids, _xlfn.LAMBDA(_xlpm.id, _xlfn.LET( _xlpm.lookup_val, _xlfn.XLOOKUP(_xlpm.id, 'Article list'!$A$2:$A$995, 'Article list'!$H$2:$H$995, ""), AND(_xlpm.lookup_val <> "", _xlpm.lookup_val <> 0) ) )), _xlpm.total_count, COUNTA(_xlpm.ids), _xlpm.excluded_count, SUM(--_xlpm.status_list), _xlfn.IFS( _xlpm.excluded_count = _xlpm.total_count, TRUE, _xlpm.excluded_count = 0, FALSE, TRUE, "partial" ) )} -> TRUE | C12: Mobility & Transport | D12: Active Travel | E12: Pedestrian Infrastructure | G12: Quantity | J12: Effective walkway width | K12: 1: 'Delphi', "Kendall's coefficient", "Cronbach's alpha value"] 6: ['Delphi Process', 'Analytic Hierarchy Process']
A13: 6 | B13: {=_xlfn.LET( _xlpm.ids, VALUE(_xlfn.TEXTSPLIT(SUBSTITUTE(A13,",",";"), ";", " ", TRUE)), _xlpm.status_list, _xlfn.MAP(_xlpm.ids, _xlfn.LAMBDA(_xlpm.id, _xlfn.LET( _xlpm.lookup_val, _xlfn.XLOOKUP(_xlpm.id, 'Article list'!$A$2:$A$995, 'Article list'!$H$2:$H$995, ""), AND(_xlpm.lookup_val <> "", _xlpm.lookup_val <> 0) ) )), _xlpm.total_count, COUNTA(_xlpm.ids), _xlpm.excluded_count, SUM(--_xlpm.status_list), _xlfn.IFS( _xlpm.excluded_count = _xlpm.total_count, TRUE, _xlpm.excluded_count = 0, FALSE, TRUE, "partial" ) )} -> TRUE | C13: Mobility & Transport | D13: Active travel | E13: Pedestrian Infrastructure | G13: Quantity | J13: Effective walkway width | K13: ['Delphi Process', 'Analytic Hierarchy Process']
A14: 6 | B14: {=_xlfn.LET( _xlpm.ids, VALUE(_xlfn.TEXTSPLIT(SUBSTITUTE(A14,",",";"), ";", " ", TRUE)), _xlpm.status_list, _xlfn.MAP(_xlpm.ids, _xlfn.LAMBDA(_xlpm.id, _xlfn.LET( _xlpm.lookup_val, _xlfn.XLOOKUP(_xlpm.id, 'Article list'!$A$2:$A$995, 'Article list'!$H$2:$H$995, ""), AND(_xlpm.lookup_val <> "", _xlpm.lookup_val <> 0) ) )), _xlpm.total_count, COUNTA(_xlpm.ids), _xlpm.excluded_count, SUM(--_xlpm.status_list), _xlfn.IFS( _xlpm.excluded_count = _xlpm.total_count, TRUE, _xlpm.excluded_count = 0, FALSE, TRUE, "partial" ) )} -> TRUE | C14: Mobility & Transport | D14: Active travel | E14: Pedestrian Infrastructure | G14: Presence | J14: Guard rails/ Lateral Separation from vehicle traffic | K14: ['Delphi Process', 'Analytic Hierarchy Process']
A15: 6 | B15: {=_xlfn.LET( _xlpm.ids, VALUE(_xlfn.TEXTSPLIT(SUBSTITUTE(A15,",",";"), ";", " ", TRUE)), _xlpm.status_list, _xlfn.MAP(_xlpm.ids, _xlfn.LAMBDA(_xlpm.id, _xlfn.LET( _xlpm.lookup_val, _xlfn.XLOOKUP(_xlpm.id, 'Article list'!$A$2:$A$995, 'Article list'!$H$2:$H$995, ""), AND(_xlpm.lookup_val <> "", _xlpm.lookup_val <> 0) ) )), _xlpm.total_count, COUNTA(_xlpm.ids), _xlpm.excluded_count, SUM(--_xlpm.status_list), _xlfn.IFS( _xlpm.excluded_count = _xlpm.total_count, TRUE, _xlpm.excluded_count = 0, FALSE, TRUE, "partial" ) )} -> TRUE | C15: Mobility & Transport | D15: Active travel | E15: Pedestrian Infrastructure | G15: Presence | J15: Guide blocks/ Weigh blocks/ Warning Blocks | K15: ['Delphi Process', 'Analytic Hierarchy Process']
A16: 1 | B16: {=_xlfn.LET( _xlpm.ids, VALUE(_xlfn.TEXTSPLIT(SUBSTITUTE(A16,",",";"), ";", " ", TRUE)), _xlpm.status_list, _xlfn.MAP(_xlpm.ids, _xlfn.LAMBDA(_xlpm.id, _xlfn.LET( _xlpm.lookup_val, _xlfn.XLOOKUP(_xlpm.id, 'Article list'!$A$2:$A$995, 'Article list'!$H$2:$H$995, ""), AND(_xlpm.lookup_val <> "", _xlpm.lookup_val <> 0) ) )), _xlpm.total_count, COUNTA(_xlpm.ids), _xlpm.excluded_count, SUM(--_xlpm.status_list), _xlfn.IFS( _xlpm.excluded_count = _xlpm.total_count, TRUE, _xlpm.excluded_count = 0, FALSE, TRUE, "partial" ) )} -> TRUE | C16: Mobility & Transport | D16: Active Travel | E16: Pedestrian Infrastructure | G16: Quantity; Presence | J16: Lighting/clear visibility | K16: ['Delphi', "Kendall's coefficient", "Cronbach's alpha value"]
A17: 6 | B17: {=_xlfn.LET( _xlpm.ids, VALUE(_xlfn.TEXTSPLIT(SUBSTITUTE(A17,",",";"), ";", " ", TRUE)), _xlpm.status_list, _xlfn.MAP(_xlpm.ids, _xlfn.LAMBDA(_xlpm.id, _xlfn.LET( _xlpm.lookup_val, _xlfn.XLOOKUP(_xlpm.id, 'Article list'!$A$2:$A$995, 'Article list'!$H$2:$H$995, ""), AND(_xlpm.lookup_val <> "", _xlpm.lookup_val <> 0) ) )), _xlpm.total_count, COUNTA(_xlpm.ids), _xlpm.excluded_count, SUM(--_xlpm.status_list), _xlfn.IFS( _xlpm.excluded_count = _xlpm.total_count, TRUE, _xlpm.excluded_count = 0, FALSE, TRUE, "partial" ) )} -> TRUE | C17: Mobility & Transport | D17: Active travel | E17: Pedestrian Infrastructure | G17: Quantity | J17: No. of Traffic lanes/ Crossing distance | K17: ['Delphi Process', 'Analytic Hierarchy Process']
A18: 6 | B18: {=_xlfn.LET( _xlpm.ids, VALUE(_xlfn.TEXTSPLIT(SUBSTITUTE(A18,",",";"), ";", " ", TRUE)), _xlpm.status_list, _xlfn.MAP(_xlpm.ids, _xlfn.LAMBDA(_xlpm.id, _xlfn.LET( _xlpm.lookup_val, _xlfn.XLOOKUP(_xlpm.id, 'Article list'!$A$2:$A$995, 'Article list'!$H$2:$H$995, ""), AND(_xlpm.lookup_val <> "", _xlpm.lookup_val <> 0) ) )), _xlpm.total_count, COUNTA(_xlpm.ids), _xlpm.excluded_count, SUM(--_xlpm.status_list), _xlfn.IFS( _xlpm.excluded_count = _xlpm.total_count, TRUE, _xlpm.excluded_count = 0, FALSE, TRUE, "partial" ) )} -> TRUE | C18: Mobility & Transport | D18: Active travel | E18: Pedestrian Infrastructure | G18: Quantity; Presence | J18: Obstruction (due to electric poles, Garbage bins, trees, informal commercial activities, illegal vendors, presence of manholes and service covers, sign posts, infrigement by shops, on-street parking) | K18: ['Delphi Process', 'Analytic Hierarchy Process']
A19: 1 | B19: {=_xlfn.LET( _xlpm.ids, VALUE(_xlfn.TEXTSPLIT(SUBSTITUTE(A19,",",";"), ";", " ", TRUE)), _xlpm.status_list, _xlfn.MAP(_xlpm.ids, _xlfn.LAMBDA(_xlpm.id, _xlfn.LET( _xlpm.lookup_val, _xlfn.XLOOKUP(_xlpm.id, 'Article list'!$A$2:$A$995, 'Article list'!$H$2:$H$995, ""), AND(_xlpm.lookup_val <> "", _xlpm.lookup_val <> 0) ) )), _xlpm.total_count, COUNTA(_xlpm.ids), _xlpm.excluded_count, SUM(--_xlpm.status_list), _xlfn.IFS( _xlpm.excluded_count = _xlpm.total_count, TRUE, _xlpm.excluded_count = 0, FALSE, TRUE, "partial" ) )} -> TRUE | C19: Mobility & Transport | D19: Road Safety | E19: Pedestrian Infrastructure | G19: Quantity; Presence | J19: Obstructions | K19: ['Delphi', "Kendall's coefficient", "Cronbach's alpha value"]
A20: 1; 6 | B20: {=_xlfn.LET( _xlpm.ids, VALUE(_xlfn.TEXTSPLIT(SUBSTITUTE(A20,",",";"), ";", " ", TRUE)), _xlpm.status_list, _xlfn.MAP(_xlpm.ids, _xlfn.LAMBDA(_xlpm.id, _xlfn.LET( _xlpm.lookup_val, _xlfn.XLOOKUP(_xlpm.id, 'Article list'!$A$2:$A$995, 'Article list'!$H$2:$H$995, ""), AND(_xlpm.lookup_val <> "", _xlpm.lookup_val <> 0) ) )), _xlpm.total_count, COUNTA(_xlpm.ids), _xlpm.excluded_count, SUM(--_xlpm.status_list), _xlfn.IFS( _xlpm.excluded_count = _xlpm.total_count, TRUE, _xlpm.excluded_count = 0, FALSE, TRUE, "partial" ) )} -> TRUE | C20: Mobility & Transport | D20: Active Travel | E20: Pedestrian Infrastructure | G20: Presence | J20: Ped access points | K20: 1: 'Delphi', "Kendall's coefficient", "Cronbach's alpha value"] 6: ['Delphi Process', 'Analytic Hierarchy Process']
A21: 1 | B21: {=_xlfn.LET( _xlpm.ids, VALUE(_xlfn.TEXTSPLIT(SUBSTITUTE(A21,",",";"), ";", " ", TRUE)), _xlpm.status_list, _xlfn.MAP(_xlpm.ids, _xlfn.LAMBDA(_xlpm.id, _xlfn.LET( _xlpm.lookup_val, _xlfn.XLOOKUP(_xlpm.id, 'Article list'!$A$2:$A$995, 'Article list'!$H$2:$H$995, ""), AND(_xlpm.lookup_val <> "", _xlpm.lookup_val <> 0) ) )), _xlpm.total_count, COUNTA(_xlpm.ids), _xlpm.excluded_count, SUM(--_xlpm.status_list), _xlfn.IFS( _xlpm.excluded_count = _xlpm.total_count, TRUE, _xlpm.excluded_count = 0, FALSE, TRUE, "partial" ) )} -> TRUE | C21: Mobility & Transport | D21: Road Safety | E21: Pedestrian Infrastructure | G21: Quantity | J21: Ped-vehicle crash rate | K21: ['Delphi', "Kendall's coefficient", "Cronbach's alpha value"]
A22: 6 | B22: {=_xlfn.LET( _xlpm.ids, VALUE(_xlfn.TEXTSPLIT(SUBSTITUTE(A22,",",";"), ";", " ", TRUE)), _xlpm.status_list, _xlfn.MAP(_xlpm.ids, _xlfn.LAMBDA(_xlpm.id, _xlfn.LET( _xlpm.lookup_val, _xlfn.XLOOKUP(_xlpm.id, 'Article list'!$A$2:$A$995, 'Article list'!$H$2:$H$995, ""), AND(_xlpm.lookup_val <> "", _xlpm.lookup_val <> 0) ) )), _xlpm.total_count, COUNTA(_xlpm.ids), _xlpm.excluded_count, SUM(--_xlpm.status_list), _xlfn.IFS( _xlpm.excluded_count = _xlpm.total_count, TRUE, _xlpm.excluded_count = 0, FALSE, TRUE, "partial" ) )} -> TRUE | C22: Mobility & Transport | D22: Active travel | E22: Pedestrian Infrastructure | G22: Quantity | J22: Pedestrian delay at intersection | K22: ['Delphi Process', 'Analytic Hierarchy Process']
A23: 21 | B23: {=_xlfn.LET( _xlpm.ids, VALUE(_xlfn.TEXTSPLIT(SUBSTITUTE(A23,",",";"), ";", " ", TRUE)), _xlpm.status_list, _xlfn.MAP(_xlpm.ids, _xlfn.LAMBDA(_xlpm.id, _xlfn.LET( _xlpm.lookup_val, _xlfn.XLOOKUP(_xlpm.id, 'Article list'!$A$2:$A$995, 'Article list'!$H$2:$H$995, ""), AND(_xlpm.lookup_val <> "", _xlpm.lookup_val <> 0) ) )), _xlpm.total_count, COUNTA(_xlpm.ids), _xlpm.excluded_count, SUM(--_xlpm.status_list), _xlfn.IFS( _xlpm.excluded_count = _xlpm.total_count, TRUE, _xlpm.excluded_count = 0, FALSE, TRUE, "partial" ) )} -> TRUE | C23: Mobility & Transport | D23: Active Travel | E23: Pedestrian Infrastructure | G23: Presence | J23: Pedestrian Network | K23: ['Kernel Density Estimation (KDE) to identify spatial clusters of walkability-related features', 'Line Density Analysis to measure connectivity of pedestrian infrastructure. These methods complement each other by capturing both the qualitative and quantitative aspects of walkability']
A24: 6 | B24: {=_xlfn.LET( _xlpm.ids, VALUE(_xlfn.TEXTSPLIT(SUBSTITUTE(A24,",",";"), ";", " ", TRUE)), _xlpm.status_list, _xlfn.MAP(_xlpm.ids, _xlfn.LAMBDA(_xlpm.id, _xlfn.LET( _xlpm.lookup_val, _xlfn.XLOOKUP(_xlpm.id, 'Article list'!$A$2:$A$995, 'Article list'!$H$2:$H$995, ""), AND(_xlpm.lookup_val <> "", _xlpm.lookup_val <> 0) ) )), _xlpm.total_count, COUNTA(_xlpm.ids), _xlpm.excluded_count, SUM(--_xlpm.status_list), _xlfn.IFS( _xlpm.excluded_count = _xlpm.total_count, TRUE, _xlpm.excluded_count = 0, FALSE, TRUE, "partial" ) )} -> TRUE | C24: Mobility & Transport | D24: Active travel | E24: Pedestrian Infrastructure | G24: Quantity | J24: Pedestrian travel speed | K24: ['Delphi Process', 'Analytic Hierarchy Process']
A25: 27 | B25: {=_xlfn.LET( _xlpm.ids, VALUE(_xlfn.TEXTSPLIT(SUBSTITUTE(A25,",",";"), ";", " ", TRUE)), _xlpm.status_list, _xlfn.MAP(_xlpm.ids, _xlfn.LAMBDA(_xlpm.id, _xlfn.LET( _xlpm.lookup_val, _xlfn.XLOOKUP(_xlpm.id, 'Article list'!$A$2:$A$995, 'Article list'!$H$2:$H$995, ""), AND(_xlpm.lookup_val <> "", _xlpm.lookup_val <> 0) ) )), _xlpm.total_count, COUNTA(_xlpm.ids), _xlpm.excluded_count, SUM(--_xlpm.status_list), _xlfn.IFS( _xlpm.excluded_count = _xlpm.total_count, TRUE, _xlpm.excluded_count = 0, FALSE, TRUE, "partial" ) )} -> FALSE | C25: Mobility & Transport | D25: Active Travel | E25: Pedestrian Infrastructure | G25: Accesibility | J25: Pedestrian-friendly infrastructure (e.g., sidewalks, crosswalks); Infrastructure and Accessibility
A26: 13 | B26: {=_xlfn.LET( _xlpm.ids, VALUE(_xlfn.TEXTSPLIT(SUBSTITUTE(A26,",",";"), ";", " ", TRUE)), _xlpm.status_list, _xlfn.MAP(_xlpm.ids, _xlfn.LAMBDA(_xlpm.id, _xlfn.LET( _xlpm.lookup_val, _xlfn.XLOOKUP(_xlpm.id, 'Article list'!$A$2:$A$995, 'Article list'!$H$2:$H$995, ""), AND(_xlpm.lookup_val <> "", _xlpm.lookup_val <> 0) ) )), _xlpm.total_count, COUNTA(_xlpm.ids), _xlpm.excluded_count, SUM(--_xlpm.status_list), _xlfn.IFS( _xlpm.excluded_count = _xlpm.total_count, TRUE, _xlpm.excluded_count = 0, FALSE, TRUE, "partial" ) )} -> FALSE | C26: Mobility & Transport | D26: Active Travel | E26: Pedestrian Infrastructure | G26: Quantity | J26: Permitted sidewalk hawker/stall locations | K26: ['Identification of measurable spatial indicators, how they can me calculated and monitored']
A27: 15 | B27: {=_xlfn.LET( _xlpm.ids, VALUE(_xlfn.TEXTSPLIT(SUBSTITUTE(A27,",",";"), ";", " ", TRUE)), _xlpm.status_list, _xlfn.MAP(_xlpm.ids, _xlfn.LAMBDA(_xlpm.id, _xlfn.LET( _xlpm.lookup_val, _xlfn.XLOOKUP(_xlpm.id, 'Article list'!$A$2:$A$995, 'Article list'!$H$2:$H$995, ""), AND(_xlpm.lookup_val <> "", _xlpm.lookup_val <> 0) ) )), _xlpm.total_count, COUNTA(_xlpm.ids), _xlpm.excluded_count, SUM(--_xlpm.status_list), _xlfn.IFS( _xlpm.excluded_count = _xlpm.total_count, TRUE, _xlpm.excluded_count = 0, FALSE, TRUE, "partial" ) )} -> FALSE | C27: Mobility & Transport | D27: Active Travel | E27: Pedestrian Infrastructure | G27: Presence | J27: Presence of roads and paths that take people where they want to go | K27: ['Likert scale']
A28: 6 | B28: {=_xlfn.LET( _xlpm.ids, VALUE(_xlfn.TEXTSPLIT(SUBSTITUTE(A28,",",";"), ";", " ", TRUE)), _xlpm.status_list, _xlfn.MAP(_xlpm.ids, _xlfn.LAMBDA(_xlpm.id, _xlfn.LET( _xlpm.lookup_val, _xlfn.XLOOKUP(_xlpm.id, 'Article list'!$A$2:$A$995, 'Article list'!$H$2:$H$995, ""), AND(_xlpm.lookup_val <> "", _xlpm.lookup_val <> 0) ) )), _xlpm.total_count, COUNTA(_xlpm.ids), _xlpm.excluded_count, SUM(--_xlpm.status_list), _xlfn.IFS( _xlpm.excluded_count = _xlpm.total_count, TRUE, _xlpm.excluded_count = 0, FALSE, TRUE, "partial" ) )} -> TRUE | C28: Mobility & Transport | D28: Active travel | E28: Pedestrian Infrastructure | G28: Quantity | J28: Refuge Islands/ Median | K28: ['Delphi Process', 'Analytic Hierarchy Process']
A29: 6 | B29: {=_xlfn.LET( _xlpm.ids, VALUE(_xlfn.TEXTSPLIT(SUBSTITUTE(A29,",",";"), ";", " ", TRUE)), _xlpm.status_list, _xlfn.MAP(_xlpm.ids, _xlfn.LAMBDA(_xlpm.id, _xlfn.LET( _xlpm.lookup_val, _xlfn.XLOOKUP(_xlpm.id, 'Article list'!$A$2:$A$995, 'Article list'!$H$2:$H$995, ""), AND(_xlpm.lookup_val <> "", _xlpm.lookup_val <> 0) ) )), _xlpm.total_count, COUNTA(_xlpm.ids), _xlpm.excluded_count, SUM(--_xlpm.status_list), _xlfn.IFS( _xlpm.excluded_count = _xlpm.total_count, TRUE, _xlpm.excluded_count = 0, FALSE, TRUE, "partial" ) )} -> TRUE | C29: Mobility & Transport | D29: Active travel | E29: Pedestrian Infrastructure | G29: Quality | J29: Surface Condition | K29: ['Delphi Process', 'Analytic Hierarchy Process']
A30: 6 | B30: {=_xlfn.LET( _xlpm.ids, VALUE(_xlfn.TEXTSPLIT(SUBSTITUTE(A30,",",";"), ";", " ", TRUE)), _xlpm.status_list, _xlfn.MAP(_xlpm.ids, _xlfn.LAMBDA(_xlpm.id, _xlfn.LET( _xlpm.lookup_val, _xlfn.XLOOKUP(_xlpm.id, 'Article list'!$A$2:$A$995, 'Article list'!$H$2:$H$995, ""), AND(_xlpm.lookup_val <> "", _xlpm.lookup_val <> 0) ) )), _xlpm.total_count, COUNTA(_xlpm.ids), _xlpm.excluded_count, SUM(--_xlpm.status_list), _xlfn.IFS( _xlpm.excluded_count = _xlpm.total_count, TRUE, _xlpm.excluded_count = 0, FALSE, TRUE, "partial" ) )} -> TRUE | C30: Mobility & Transport | D30: Active travel | E30: Pedestrian Infrastructure | J30: Tactile paving at ingress and egress of a footpath or median refuge | K30: ['Delphi Process', 'Analytic Hierarchy Process']
A31: 6 | B31: {=_xlfn.LET( _xlpm.ids, VALUE(_xlfn.TEXTSPLIT(SUBSTITUTE(A31,",",";"), ";", " ", TRUE)), _xlpm.status_list, _xlfn.MAP(_xlpm.ids, _xlfn.LAMBDA(_xlpm.id, _xlfn.LET( _xlpm.lookup_val, _xlfn.XLOOKUP(_xlpm.id, 'Article list'!$A$2:$A$995, 'Article list'!$H$2:$H$995, ""), AND(_xlpm.lookup_val <> "", _xlpm.lookup_val <> 0) ) )), _xlpm.total_count, COUNTA(_xlpm.ids), _xlpm.excluded_count, SUM(--_xlpm.status_list), _xlfn.IFS( _xlpm.excluded_count = _xlpm.total_count, TRUE, _xlpm.excluded_count = 0, FALSE, TRUE, "partial" ) )} -> TRUE | C31: Mobility & Transport | D31: Active travel | E31: Pedestrian Infrastructure; Cycling Infrastructure | G31: Quantity; Presence | J31: Wayfinding/ Signage | K31: ['Delphi Process', 'Analytic Hierarchy Process']
A32: 12 | B32: {=_xlfn.LET( _xlpm.ids, VALUE(_xlfn.TEXTSPLIT(SUBSTITUTE(A32,",",";"), ";", " ", TRUE)), _xlpm.status_list, _xlfn.MAP(_xlpm.ids, _xlfn.LAMBDA(_xlpm.id, _xlfn.LET( _xlpm.lookup_val, _xlfn.XLOOKUP(_xlpm.id, 'Article list'!$A$2:$A$995, 'Article list'!$H$2:$H$995, ""), AND(_xlpm.lookup_val <> "", _xlpm.lookup_val <> 0) ) )), _xlpm.total_count, COUNTA(_xlpm.ids), _xlpm.excluded_count, SUM(--_xlpm.status_list), _xlfn.IFS( _xlpm.excluded_count = _xlpm.total_count, TRUE, _xlpm.excluded_count = 0, FALSE, TRUE, "partial" ) )} -> FALSE | C32: Mobility & Transport | D32: Active travel | E32: Road safety | G32: Density | J32: Spatial congestion / overcrowding | K32: ['Likert Scale Measurement', 'One-Way ANOVA', 'Descriptive Statistics', 'Post Hoc (Tukey) Test', 'Mann-Whitney U Test', 'Qualitative Thematic Analysis']
A33: 28 | B33: {=_xlfn.LET( _xlpm.ids, VALUE(_xlfn.TEXTSPLIT(SUBSTITUTE(A33,",",";"), ";", " ", TRUE)), _xlpm.status_list, _xlfn.MAP(_xlpm.ids, _xlfn.LAMBDA(_xlpm.id, _xlfn.LET( _xlpm.lookup_val, _xlfn.XLOOKUP(_xlpm.id, 'Article list'!$A$2:$A$995, 'Article list'!$H$2:$H$995, ""), AND(_xlpm.lookup_val <> "", _xlpm.lookup_val <> 0) ) )), _xlpm.total_count, COUNTA(_xlpm.ids), _xlpm.excluded_count, SUM(--_xlpm.status_list), _xlfn.IFS( _xlpm.excluded_count = _xlpm.total_count, TRUE, _xlpm.excluded_count = 0, FALSE, TRUE, "partial" ) )} -> FALSE | C33: Mobility & Transport | D33: Public transport | E33: Transport Routes | G33: Quantity | J33: <30; TA | K33: ['Analytic Hierarchy Profess (AHP)', 'Delphi method', 'Literature analysis']
A34: 28 | B34: {=_xlfn.LET( _xlpm.ids, VALUE(_xlfn.TEXTSPLIT(SUBSTITUTE(A34,",",";"), ";", " ", TRUE)), _xlpm.status_list, _xlfn.MAP(_xlpm.ids, _xlfn.LAMBDA(_xlpm.id, _xlfn.LET( _xlpm.lookup_val, _xlfn.XLOOKUP(_xlpm.id, 'Article list'!$A$2:$A$995, 'Article list'!$H$2:$H$995, ""), AND(_xlpm.lookup_val <> "", _xlpm.lookup_val <> 0) ) )), _xlpm.total_count, COUNTA(_xlpm.ids), _xlpm.excluded_count, SUM(--_xlpm.status_list), _xlfn.IFS( _xlpm.excluded_count = _xlpm.total_count, TRUE, _xlpm.excluded_count = 0, FALSE, TRUE, "partial" ) )} -> FALSE | C34: Mobility & Transport | D34: Public transport | E34: Transport Routes | G34: Quantity | J34: >1500; TA | K34: ['Analytic Hierarchy Profess (AHP)', 'Delphi method', 'Literature analysis']
A35: 28 | B35: {=_xlfn.LET( _xlpm.ids, VALUE(_xlfn.TEXTSPLIT(SUBSTITUTE(A35,",",";"), ";", " ", TRUE)), _xlpm.status_list, _xlfn.MAP(_xlpm.ids, _xlfn.LAMBDA(_xlpm.id, _xlfn.LET( _xlpm.lookup_val, _xlfn.XLOOKUP(_xlpm.id, 'Article list'!$A$2:$A$995, 'Article list'!$H$2:$H$995, ""), AND(_xlpm.lookup_val <> "", _xlpm.lookup_val <> 0) ) )), _xlpm.total_count, COUNTA(_xlpm.ids), _xlpm.excluded_count, SUM(--_xlpm.status_list), _xlfn.IFS( _xlpm.excluded_count = _xlpm.total_count, TRUE, _xlpm.excluded_count = 0, FALSE, TRUE, "partial" ) )} -> FALSE | C35: Mobility & Transport | D35: Public transport | E35: Transport Routes | G35: Quantity | J35: 30-300; TA | K35: ['Analytic Hierarchy Profess (AHP)', 'Delphi method', 'Literature analysis']
A36: 28 | B36: {=_xlfn.LET( _xlpm.ids, VALUE(_xlfn.TEXTSPLIT(SUBSTITUTE(A36,",",";"), ";", " ", TRUE)), _xlpm.status_list, _xlfn.MAP(_xlpm.ids, _xlfn.LAMBDA(_xlpm.id, _xlfn.LET( _xlpm.lookup_val, _xlfn.XLOOKUP(_xlpm.id, 'Article list'!$A$2:$A$995, 'Article list'!$H$2:$H$995, ""), AND(_xlpm.lookup_val <> "", _xlpm.lookup_val <> 0) ) )), _xlpm.total_count, COUNTA(_xlpm.ids), _xlpm.excluded_count, SUM(--_xlpm.status_list), _xlfn.IFS( _xlpm.excluded_count = _xlpm.total_count, TRUE, _xlpm.excluded_count = 0, FALSE, TRUE, "partial" ) )} -> FALSE | C36: Mobility & Transport | D36: Public transport | E36: Transport Routes | G36: Quantity | J36: 300-600; TA | K36: ['Analytic Hierarchy Profess (AHP)', 'Delphi method', 'Literature analysis']
A37: 28 | B37: {=_xlfn.LET( _xlpm.ids, VALUE(_xlfn.TEXTSPLIT(SUBSTITUTE(A37,",",";"), ";", " ", TRUE)), _xlpm.status_list, _xlfn.MAP(_xlpm.ids, _xlfn.LAMBDA(_xlpm.id, _xlfn.LET( _xlpm.lookup_val, _xlfn.XLOOKUP(_xlpm.id, 'Article list'!$A$2:$A$995, 'Article list'!$H$2:$H$995, ""), AND(_xlpm.lookup_val <> "", _xlpm.lookup_val <> 0) ) )), _xlpm.total_count, COUNTA(_xlpm.ids), _xlpm.excluded_count, SUM(--_xlpm.status_list), _xlfn.IFS( _xlpm.excluded_count = _xlpm.total_count, TRUE, _xlpm.excluded_count = 0, FALSE, TRUE, "partial" ) )} -> FALSE | C37: Mobility & Transport | D37: Public transport | E37: Transport Routes | G37: Quantity | J37: 600-1500; TA | K37: ['Analytic Hierarchy Profess (AHP)', 'Delphi method', 'Literature analysis']
A38: 10 | B38: {=_xlfn.LET( _xlpm.ids, VALUE(_xlfn.TEXTSPLIT(SUBSTITUTE(A38,",",";"), ";", " ", TRUE)), _xlpm.status_list, _xlfn.MAP(_xlpm.ids, _xlfn.LAMBDA(_xlpm.id, _xlfn.LET( _xlpm.lookup_val, _xlfn.XLOOKUP(_xlpm.id, 'Article list'!$A$2:$A$995, 'Article list'!$H$2:$H$995, ""), AND(_xlpm.lookup_val <> "", _xlpm.lookup_val <> 0) ) )), _xlpm.total_count, COUNTA(_xlpm.ids), _xlpm.excluded_count, SUM(--_xlpm.status_list), _xlfn.IFS( _xlpm.excluded_count = _xlpm.total_count, TRUE, _xlpm.excluded_count = 0, FALSE, TRUE, "partial" ) )} -> TRUE | C38: Mobility & Transport | D38: public transport | E38: transport routes | G38: quantity | J38: Bus (Number of lines) | K38: ['Fuzzy DEMATEL', 'Weighted Linear Combination (WLC),']
A39: 11 | B39: {=_xlfn.LET( _xlpm.ids, VALUE(_xlfn.TEXTSPLIT(SUBSTITUTE(A39,",",";"), ";", " ", TRUE)), _xlpm.status_list, _xlfn.MAP(_xlpm.ids, _xlfn.LAMBDA(_xlpm.id, _xlfn.LET( _xlpm.lookup_val, _xlfn.XLOOKUP(_xlpm.id, 'Article list'!$A$2:$A$995, 'Article list'!$H$2:$H$995, ""), AND(_xlpm.lookup_val <> "", _xlpm.lookup_val <> 0) ) )), _xlpm.total_count, COUNTA(_xlpm.ids), _xlpm.excluded_count, SUM(--_xlpm.status_list), _xlfn.IFS( _xlpm.excluded_count = _xlpm.total_count, TRUE, _xlpm.excluded_count = 0, FALSE, TRUE, "partial" ) )} -> TRUE | C39: Mobility & Transport | D39: Public Transport | E39: Transport Routes | G39: Quantity | J39: Duration of waiting time | K39: ['Distance-based accessibility measures', 'Objective environmental and neighbourhood indicators', 'Resident perception surveys using 5-point Likert scales', 'Satisfaction-based scoring for each livability dimension']
A40: 11 | B40: {=_xlfn.LET( _xlpm.ids, VALUE(_xlfn.TEXTSPLIT(SUBSTITUTE(A40,",",";"), ";", " ", TRUE)), _xlpm.status_list, _xlfn.MAP(_xlpm.ids, _xlfn.LAMBDA(_xlpm.id, _xlfn.LET( _xlpm.lookup_val, _xlfn.XLOOKUP(_xlpm.id, 'Article list'!$A$2:$A$995, 'Article list'!$H$2:$H$995, ""), AND(_xlpm.lookup_val <> "", _xlpm.lookup_val <> 0) ) )), _xlpm.total_count, COUNTA(_xlpm.ids), _xlpm.excluded_count, SUM(--_xlpm.status_list), _xlfn.IFS( _xlpm.excluded_count = _xlpm.total_count, TRUE, _xlpm.excluded_count = 0, FALSE, TRUE, "partial" ) )} -> TRUE | C40: Mobility & Transport | D40: Public Transport | E40: Transport Routes | G40: Quantity | J40: Modes used | K40: ['Distance-based accessibility measures', 'Objective environmental and neighbourhood indicators', 'Resident perception surveys using 5-point Likert scales', 'Satisfaction-based scoring for each livability dimension']
A41: 3 | B41: {=_xlfn.LET( _xlpm.ids, VALUE(_xlfn.TEXTSPLIT(SUBSTITUTE(A41,",",";"), ";", " ", TRUE)), _xlpm.status_list, _xlfn.MAP(_xlpm.ids, _xlfn.LAMBDA(_xlpm.id, _xlfn.LET( _xlpm.lookup_val, _xlfn.XLOOKUP(_xlpm.id, 'Article list'!$A$2:$A$995, 'Article list'!$H$2:$H$995, ""), AND(_xlpm.lookup_val <> "", _xlpm.lookup_val <> 0) ) )), _xlpm.total_count, COUNTA(_xlpm.ids), _xlpm.excluded_count, SUM(--_xlpm.status_list), _xlfn.IFS( _xlpm.excluded_count = _xlpm.total_count, TRUE, _xlpm.excluded_count = 0, FALSE, TRUE, "partial" ) )} -> FALSE | C41: Mobility & Transport | D41: Public Transport | E41: Transport Routes | G41: Density | J41: Number of buses per 10,000 people | K41: ['Entropy TOPSIS model', 'Tobit model']
A42: 31 | B42: {=_xlfn.LET( _xlpm.ids, VALUE(_xlfn.TEXTSPLIT(SUBSTITUTE(A42,",",";"), ";", " ", TRUE)), _xlpm.status_list, _xlfn.MAP(_xlpm.ids, _xlfn.LAMBDA(_xlpm.id, _xlfn.LET( _xlpm.lookup_val, _xlfn.XLOOKUP(_xlpm.id, 'Article list'!$A$2:$A$995, 'Article list'!$H$2:$H$995, ""), AND(_xlpm.lookup_val <> "", _xlpm.lookup_val <> 0) ) )), _xlpm.total_count, COUNTA(_xlpm.ids), _xlpm.excluded_count, SUM(--_xlpm.status_list), _xlfn.IFS( _xlpm.excluded_count = _xlpm.total_count, TRUE, _xlpm.excluded_count = 0, FALSE, TRUE, "partial" ) )} -> FALSE | C42: Mobility & Transport | D42: Public Transport | E42: transport routes | G42: Quantity | J42: Per capita urban road area; Urban public service capacity | K42: ['Grey relational degree', 'Entropy-TOPSIS model']
A43: 8 | B43: {=_xlfn.LET( _xlpm.ids, VALUE(_xlfn.TEXTSPLIT(SUBSTITUTE(A43,",",";"), ";", " ", TRUE)), _xlpm.status_list, _xlfn.MAP(_xlpm.ids, _xlfn.LAMBDA(_xlpm.id, _xlfn.LET( _xlpm.lookup_val, _xlfn.XLOOKUP(_xlpm.id, 'Article list'!$A$2:$A$995, 'Article list'!$H$2:$H$995, ""), AND(_xlpm.lookup_val <> "", _xlpm.lookup_val <> 0) ) )), _xlpm.total_count, COUNTA(_xlpm.ids), _xlpm.excluded_count, SUM(--_xlpm.status_list), _xlfn.IFS( _xlpm.excluded_count = _xlpm.total_count, TRUE, _xlpm.excluded_count = 0, FALSE, TRUE, "partial" ) )} -> FALSE | C43: Mobility & Transport | D43: Public transport | E43: Transport Routes | G43: Quality | J43: Transportation network | K43: ['Hierarchical Modelling using Analytic Hierarchy Process (AHP)'] | M43: too broad
A44: 16 | B44: {=_xlfn.LET( _xlpm.ids, VALUE(_xlfn.TEXTSPLIT(SUBSTITUTE(A44,",",";"), ";", " ", TRUE)), _xlpm.status_list, _xlfn.MAP(_xlpm.ids, _xlfn.LAMBDA(_xlpm.id, _xlfn.LET( _xlpm.lookup_val, _xlfn.XLOOKUP(_xlpm.id, 'Article list'!$A$2:$A$995, 'Article list'!$H$2:$H$995, ""), AND(_xlpm.lookup_val <> "", _xlpm.lookup_val <> 0) ) )), _xlpm.total_count, COUNTA(_xlpm.ids), _xlpm.excluded_count, SUM(--_xlpm.status_list), _xlfn.IFS( _xlpm.excluded_count = _xlpm.total_count, TRUE, _xlpm.excluded_count = 0, FALSE, TRUE, "partial" ) )} -> FALSE | C44: Mobility & Transport | D44: Public Transport | E44: Transport Stops | G44: Accesibility | J44: Access to transportation (minutes) | K44: ['Exploratory Factor Analysis', 'Standard Deviational Ellipse,', 'Hot Spot Analysis,', 'Network Analysis']
A45: 30 | B45: {=_xlfn.LET( _xlpm.ids, VALUE(_xlfn.TEXTSPLIT(SUBSTITUTE(A45,",",";"), ";", " ", TRUE)), _xlpm.status_list, _xlfn.MAP(_xlpm.ids, _xlfn.LAMBDA(_xlpm.id, _xlfn.LET( _xlpm.lookup_val, _xlfn.XLOOKUP(_xlpm.id, 'Article list'!$A$2:$A$995, 'Article list'!$H$2:$H$995, ""), AND(_xlpm.lookup_val <> "", _xlpm.lookup_val <> 0) ) )), _xlpm.total_count, COUNTA(_xlpm.ids), _xlpm.excluded_count, SUM(--_xlpm.status_list), _xlfn.IFS( _xlpm.excluded_count = _xlpm.total_count, TRUE, _xlpm.excluded_count = 0, FALSE, TRUE, "partial" ) )} -> FALSE | C45: Mobility & Transport | D45: Public transport | E45: Transport Stops | G45: Accessibility | J45: Accessibility (Transit) | K45: ['GIS-based spatial diagnostics']
A46: 7 | B46: {=_xlfn.LET( _xlpm.ids, VALUE(_xlfn.TEXTSPLIT(SUBSTITUTE(A46,",",";"), ";", " ", TRUE)), _xlpm.status_list, _xlfn.MAP(_xlpm.ids, _xlfn.LAMBDA(_xlpm.id, _xlfn.LET( _xlpm.lookup_val, _xlfn.XLOOKUP(_xlpm.id, 'Article list'!$A$2:$A$995, 'Article list'!$H$2:$H$995, ""), AND(_xlpm.lookup_val <> "", _xlpm.lookup_val <> 0) ) )), _xlpm.total_count, COUNTA(_xlpm.ids), _xlpm.excluded_count, SUM(--_xlpm.status_list), _xlfn.IFS( _xlpm.excluded_count = _xlpm.total_count, TRUE, _xlpm.excluded_count = 0, FALSE, TRUE, "partial" ) )} -> TRUE | C46: Mobility & Transport | D46: Public Transport | E46: Transport Stops | G46: Presence | J46: Availability of public transport | K46: ['Likert scale']
A47: 11 | B47: {=_xlfn.LET( _xlpm.ids, VALUE(_xlfn.TEXTSPLIT(SUBSTITUTE(A47,",",";"), ";", " ", TRUE)), _xlpm.status_list, _xlfn.MAP(_xlpm.ids, _xlfn.LAMBDA(_xlpm.id, _xlfn.LET( _xlpm.lookup_val, _xlfn.XLOOKUP(_xlpm.id, 'Article list'!$A$2:$A$995, 'Article list'!$H$2:$H$995, ""), AND(_xlpm.lookup_val <> "", _xlpm.lookup_val <> 0) ) )), _xlpm.total_count, COUNTA(_xlpm.ids), _xlpm.excluded_count, SUM(--_xlpm.status_list), _xlfn.IFS( _xlpm.excluded_count = _xlpm.total_count, TRUE, _xlpm.excluded_count = 0, FALSE, TRUE, "partial" ) )} -> TRUE | C47: Mobility & Transport | D47: Public Transport | E47: Transport Stops | G47: Proximity | J47: Average distance to the public transport station | K47: ['Distance-based accessibility measures', 'Objective environmental and neighbourhood indicators', 'Resident perception surveys using 5-point Likert scales', 'Satisfaction-based scoring for each livability dimension']
A48: 1; 6 | B48: {=_xlfn.LET( _xlpm.ids, VALUE(_xlfn.TEXTSPLIT(SUBSTITUTE(A48,",",";"), ";", " ", TRUE)), _xlpm.status_list, _xlfn.MAP(_xlpm.ids, _xlfn.LAMBDA(_xlpm.id, _xlfn.LET( _xlpm.lookup_val, _xlfn.XLOOKUP(_xlpm.id, 'Article list'!$A$2:$A$995, 'Article list'!$H$2:$H$995, ""), AND(_xlpm.lookup_val <> "", _xlpm.lookup_val <> 0) ) )), _xlpm.total_count, COUNTA(_xlpm.ids), _xlpm.excluded_count, SUM(--_xlpm.status_list), _xlfn.IFS( _xlpm.excluded_count = _xlpm.total_count, TRUE, _xlpm.excluded_count = 0, FALSE, TRUE, "partial" ) )} -> TRUE | C48: Mobility & Transport | D48: Public transport | E48: Transport Stops | G48: Quantity; Presence | J48: Bus stops | K48: 1: 'Delphi', "Kendall's coefficient", "Cronbach's alpha value"] 6: ['Delphi Process', 'Analytic Hierarchy Process']
A49: 5 | B49: {=_xlfn.LET( _xlpm.ids, VALUE(_xlfn.TEXTSPLIT(SUBSTITUTE(A49,",",";"), ";", " ", TRUE)), _xlpm.status_list, _xlfn.MAP(_xlpm.ids, _xlfn.LAMBDA(_xlpm.id, _xlfn.LET( _xlpm.lookup_val, _xlfn.XLOOKUP(_xlpm.id, 'Article list'!$A$2:$A$995, 'Article list'!$H$2:$H$995, ""), AND(_xlpm.lookup_val <> "", _xlpm.lookup_val <> 0) ) )), _xlpm.total_count, COUNTA(_xlpm.ids), _xlpm.excluded_count, SUM(--_xlpm.status_list), _xlfn.IFS( _xlpm.excluded_count = _xlpm.total_count, TRUE, _xlpm.excluded_count = 0, FALSE, TRUE, "partial" ) )} -> FALSE | C49: Mobility & Transport | D49: Public Transport | E49: Transport Stops | G49: Density | J49: Bus Stops per 1000 persons | K49: ['Supervised classification in Erdas Imagine Software.', 'regression']
A50: 20 | B50: {=_xlfn.LET( _xlpm.ids, VALUE(_xlfn.TEXTSPLIT(SUBSTITUTE(A50,",",";"), ";", " ", TRUE)), _xlpm.status_list, _xlfn.MAP(_xlpm.ids, _xlfn.LAMBDA(_xlpm.id, _xlfn.LET( _xlpm.lookup_val, _xlfn.XLOOKUP(_xlpm.id, 'Article list'!$A$2:$A$995, 'Article list'!$H$2:$H$995, ""), AND(_xlpm.lookup_val <> "", _xlpm.lookup_val <> 0) ) )), _xlpm.total_count, COUNTA(_xlpm.ids), _xlpm.excluded_count, SUM(--_xlpm.status_list), _xlfn.IFS( _xlpm.excluded_count = _xlpm.total_count, TRUE, _xlpm.excluded_count = 0, FALSE, TRUE, "partial" ) )} -> FALSE | C50: Mobility & Transport | D50: Public transport | E50: Transport Stops | G50: Proximity | J50: Distance to bus stands/stops | K50: ['Proximity analysis following digitization and Euclidean distance computation']
A51: 18 | B51: {=_xlfn.LET( _xlpm.ids, VALUE(_xlfn.TEXTSPLIT(SUBSTITUTE(A51,",",";"), ";", " ", TRUE)), _xlpm.status_list, _xlfn.MAP(_xlpm.ids, _xlfn.LAMBDA(_xlpm.id, _xlfn.LET( _xlpm.lookup_val, _xlfn.XLOOKUP(_xlpm.id, 'Article list'!$A$2:$A$995, 'Article list'!$H$2:$H$995, ""), AND(_xlpm.lookup_val <> "", _xlpm.lookup_val <> 0) ) )), _xlpm.total_count, COUNTA(_xlpm.ids), _xlpm.excluded_count, SUM(--_xlpm.status_list), _xlfn.IFS( _xlpm.excluded_count = _xlpm.total_count, TRUE, _xlpm.excluded_count = 0, FALSE, TRUE, "partial" ) )} -> FALSE | C51: Mobility & Transport | D51: Public transport | E51: Transport Stops | G51: Proximity | J51: Distance to bus terminal | K51: ['Analytic Hierarchy Process (AHP)']
A52: 19 | B52: {=_xlfn.LET( _xlpm.ids, VALUE(_xlfn.TEXTSPLIT(SUBSTITUTE(A52,",",";"), ";", " ", TRUE)), _xlpm.status_list, _xlfn.MAP(_xlpm.ids, _xlfn.LAMBDA(_xlpm.id, _xlfn.LET( _xlpm.lookup_val, _xlfn.XLOOKUP(_xlpm.id, 'Article list'!$A$2:$A$995, 'Article list'!$H$2:$H$995, ""), AND(_xlpm.lookup_val <> "", _xlpm.lookup_val <> 0) ) )), _xlpm.total_count, COUNTA(_xlpm.ids), _xlpm.excluded_count, SUM(--_xlpm.status_list), _xlfn.IFS( _xlpm.excluded_count = _xlpm.total_count, TRUE, _xlpm.excluded_count = 0, FALSE, TRUE, "partial" ) )} -> FALSE | C52: Mobility & Transport | D52: Public transport | E52: Transport Stops | G52: Proximity | J52: Distance to metro | K52: ['machine learning is integrated into semantic image segmentation technique to extract green pixels from the street view images using the scene parsing method; SVG', 'entropy index (relative percentage of various land-use types)']
A53: 20 | B53: {=_xlfn.LET( _xlpm.ids, VALUE(_xlfn.TEXTSPLIT(SUBSTITUTE(A53,",",";"), ";", " ", TRUE)), _xlpm.status_list, _xlfn.MAP(_xlpm.ids, _xlfn.LAMBDA(_xlpm.id, _xlfn.LET( _xlpm.lookup_val, _xlfn.XLOOKUP(_xlpm.id, 'Article list'!$A$2:$A$995, 'Article list'!$H$2:$H$995, ""), AND(_xlpm.lookup_val <> "", _xlpm.lookup_val <> 0) ) )), _xlpm.total_count, COUNTA(_xlpm.ids), _xlpm.excluded_count, SUM(--_xlpm.status_list), _xlfn.IFS( _xlpm.excluded_count = _xlpm.total_count, TRUE, _xlpm.excluded_count = 0, FALSE, TRUE, "partial" ) )} -> FALSE | C53: Mobility & Transport | D53: Public Transport | E53: Transport Stops | G53: Proximity | J53: Distance to railway stations | K53: ['Proximity analysis following digitization and Euclidean distance computation']
A54: 18 | B54: {=_xlfn.LET( _xlpm.ids, VALUE(_xlfn.TEXTSPLIT(SUBSTITUTE(A54,",",";"), ";", " ", TRUE)), _xlpm.status_list, _xlfn.MAP(_xlpm.ids, _xlfn.LAMBDA(_xlpm.id, _xlfn.LET( _xlpm.lookup_val, _xlfn.XLOOKUP(_xlpm.id, 'Article list'!$A$2:$A$995, 'Article list'!$H$2:$H$995, ""), AND(_xlpm.lookup_val <> "", _xlpm.lookup_val <> 0) ) )), _xlpm.total_count, COUNTA(_xlpm.ids), _xlpm.excluded_count, SUM(--_xlpm.status_list), _xlfn.IFS( _xlpm.excluded_count = _xlpm.total_count, TRUE, _xlpm.excluded_count = 0, FALSE, TRUE, "partial" ) )} -> FALSE | C54: Mobility & Transport | D54: Public transport | E54: Transport Stops | G54: Proximity | J54: Distance to train station | K54: ['Analytic Hierarchy Process (AHP)']
A55: 14 | B55: {=_xlfn.LET( _xlpm.ids, VALUE(_xlfn.TEXTSPLIT(SUBSTITUTE(A55,",",";"), ";", " ", TRUE)), _xlpm.status_list, _xlfn.MAP(_xlpm.ids, _xlfn.LAMBDA(_xlpm.id, _xlfn.LET( _xlpm.lookup_val, _xlfn.XLOOKUP(_xlpm.id, 'Article list'!$A$2:$A$995, 'Article list'!$H$2:$H$995, ""), AND(_xlpm.lookup_val <> "", _xlpm.lookup_val <> 0) ) )), _xlpm.total_count, COUNTA(_xlpm.ids), _xlpm.excluded_count, SUM(--_xlpm.status_list), _xlfn.IFS( _xlpm.excluded_count = _xlpm.total_count, TRUE, _xlpm.excluded_count = 0, FALSE, TRUE, "partial" ) )} -> TRUE | C55: Mobility & Transport | D55: Public Transport | E55: Transport Stops | G55: Quantity | J55: Number of buses per ten thousand person at year end | K55: ['Entropy measure']
A56: 14 | B56: {=_xlfn.LET( _xlpm.ids, VALUE(_xlfn.TEXTSPLIT(SUBSTITUTE(A56,",",";"), ";", " ", TRUE)), _xlpm.status_list, _xlfn.MAP(_xlpm.ids, _xlfn.LAMBDA(_xlpm.id, _xlfn.LET( _xlpm.lookup_val, _xlfn.XLOOKUP(_xlpm.id, 'Article list'!$A$2:$A$995, 'Article list'!$H$2:$H$995, ""), AND(_xlpm.lookup_val <> "", _xlpm.lookup_val <> 0) ) )), _xlpm.total_count, COUNTA(_xlpm.ids), _xlpm.excluded_count, SUM(--_xlpm.status_list), _xlfn.IFS( _xlpm.excluded_count = _xlpm.total_count, TRUE, _xlpm.excluded_count = 0, FALSE, TRUE, "partial" ) )} -> TRUE | C56: Mobility & Transport | D56: Public Transport | E56: Transport Stops | G56: Quantity | J56: Number of taxis at year end | K56: ['Entropy measure'] | L56: Need to revisit
A57: 13 | B57: {=_xlfn.LET( _xlpm.ids, VALUE(_xlfn.TEXTSPLIT(SUBSTITUTE(A57,",",";"), ";", " ", TRUE)), _xlpm.status_list, _xlfn.MAP(_xlpm.ids, _xlfn.LAMBDA(_xlpm.id, _xlfn.LET( _xlpm.lookup_val, _xlfn.XLOOKUP(_xlpm.id, 'Article list'!$A$2:$A$995, 'Article list'!$H$2:$H$995, ""), AND(_xlpm.lookup_val <> "", _xlpm.lookup_val <> 0) ) )), _xlpm.total_count, COUNTA(_xlpm.ids), _xlpm.excluded_count, SUM(--_xlpm.status_list), _xlfn.IFS( _xlpm.excluded_count = _xlpm.total_count, TRUE, _xlpm.excluded_count = 0, FALSE, TRUE, "partial" ) )} -> FALSE | C57: Mobility & Transport | D57: Public Transport | E57: Transport Stops | G57: Quantity | J57: Percentage of residents living 800 metres distance of any public transport | K57: ['Identification of measurable spatial indicators, how they can me calculated and monitored'] | M57: no estoy segura de que este bien clasificado
A58: 21 | B58: {=_xlfn.LET( _xlpm.ids, VALUE(_xlfn.TEXTSPLIT(SUBSTITUTE(A58,",",";"), ";", " ", TRUE)), _xlpm.status_list, _xlfn.MAP(_xlpm.ids, _xlfn.LAMBDA(_xlpm.id, _xlfn.LET( _xlpm.lookup_val, _xlfn.XLOOKUP(_xlpm.id, 'Article list'!$A$2:$A$995, 'Article list'!$H$2:$H$995, ""), AND(_xlpm.lookup_val <> "", _xlpm.lookup_val <> 0) ) )), _xlpm.total_count, COUNTA(_xlpm.ids), _xlpm.excluded_count, SUM(--_xlpm.status_list), _xlfn.IFS( _xlpm.excluded_count = _xlpm.total_count, TRUE, _xlpm.excluded_count = 0, FALSE, TRUE, "partial" ) )} -> TRUE | C58: Mobility & Transport | D58: Public Transport | E58: Transport Stops | G58: Proximity | J58: Proximity to Public Transport | K58: ['Kernel Density Estimation (KDE) to identify spatial clusters of walkability-related features', 'Line Density Analysis to measure connectivity of pedestrian infrastructure. These methods complement each other by capturing both the qualitative and quantitative aspects of walkability']
A59: 22 | B59: {=_xlfn.LET( _xlpm.ids, VALUE(_xlfn.TEXTSPLIT(SUBSTITUTE(A59,",",";"), ";", " ", TRUE)), _xlpm.status_list, _xlfn.MAP(_xlpm.ids, _xlfn.LAMBDA(_xlpm.id, _xlfn.LET( _xlpm.lookup_val, _xlfn.XLOOKUP(_xlpm.id, 'Article list'!$A$2:$A$995, 'Article list'!$H$2:$H$995, ""), AND(_xlpm.lookup_val <> "", _xlpm.lookup_val <> 0) ) )), _xlpm.total_count, COUNTA(_xlpm.ids), _xlpm.excluded_count, SUM(--_xlpm.status_list), _xlfn.IFS( _xlpm.excluded_count = _xlpm.total_count, TRUE, _xlpm.excluded_count = 0, FALSE, TRUE, "partial" ) )} -> FALSE | C59: Mobility & Transport | D59: Public Transport | E59: Transport Stops | G59: Quantity; Presence | J59: Public transport | K59: ['N/A']
A60: 10 | B60: {=_xlfn.LET( _xlpm.ids, VALUE(_xlfn.TEXTSPLIT(SUBSTITUTE(A60,",",";"), ";", " ", TRUE)), _xlpm.status_list, _xlfn.MAP(_xlpm.ids, _xlfn.LAMBDA(_xlpm.id, _xlfn.LET( _xlpm.lookup_val, _xlfn.XLOOKUP(_xlpm.id, 'Article list'!$A$2:$A$995, 'Article list'!$H$2:$H$995, ""), AND(_xlpm.lookup_val <> "", _xlpm.lookup_val <> 0) ) )), _xlpm.total_count, COUNTA(_xlpm.ids), _xlpm.excluded_count, SUM(--_xlpm.status_list), _xlfn.IFS( _xlpm.excluded_count = _xlpm.total_count, TRUE, _xlpm.excluded_count = 0, FALSE, TRUE, "partial" ) )} -> TRUE | C60: Mobility & Transport | D60: Public Transport | E60: Transport Stops | G60: Proximity | J60: Rail System (Distance (m)) | K60: ['Fuzzy DEMATEL', 'Weighted Linear Combination (WLC),']
A61: 5 | B61: {=_xlfn.LET( _xlpm.ids, VALUE(_xlfn.TEXTSPLIT(SUBSTITUTE(A61,",",";"), ";", " ", TRUE)), _xlpm.status_list, _xlfn.MAP(_xlpm.ids, _xlfn.LAMBDA(_xlpm.id, _xlfn.LET( _xlpm.lookup_val, _xlfn.XLOOKUP(_xlpm.id, 'Article list'!$A$2:$A$995, 'Article list'!$H$2:$H$995, ""), AND(_xlpm.lookup_val <> "", _xlpm.lookup_val <> 0) ) )), _xlpm.total_count, COUNTA(_xlpm.ids), _xlpm.excluded_count, SUM(--_xlpm.status_list), _xlfn.IFS( _xlpm.excluded_count = _xlpm.total_count, TRUE, _xlpm.excluded_count = 0, FALSE, TRUE, "partial" ) )} -> FALSE | C61: Mobility & Transport | D61: Public Transport | E61: Transport Stops | G61: Density | J61: Railway Stations per 1000 persons | K61: ['Supervised classification in Erdas Imagine Software.', 'regression']
A62: 27 | B62: {=_xlfn.LET( _xlpm.ids, VALUE(_xlfn.TEXTSPLIT(SUBSTITUTE(A62,",",";"), ";", " ", TRUE)), _xlpm.status_list, _xlfn.MAP(_xlpm.ids, _xlfn.LAMBDA(_xlpm.id, _xlfn.LET( _xlpm.lookup_val, _xlfn.XLOOKUP(_xlpm.id, 'Article list'!$A$2:$A$995, 'Article list'!$H$2:$H$995, ""), AND(_xlpm.lookup_val <> "", _xlpm.lookup_val <> 0) ) )), _xlpm.total_count, COUNTA(_xlpm.ids), _xlpm.excluded_count, SUM(--_xlpm.status_list), _xlfn.IFS( _xlpm.excluded_count = _xlpm.total_count, TRUE, _xlpm.excluded_count = 0, FALSE, TRUE, "partial" ) )} -> FALSE | C62: Mobility & Transport | D62: Public Transport | E62: Transport Stops; Transport Routes | G62: Presence; Accesibility | J62: Public transportation access and coverage; Infrastructure and Accessibility
A63: 26 | B63: {=_xlfn.LET( _xlpm.ids, VALUE(_xlfn.TEXTSPLIT(SUBSTITUTE(A63,",",";"), ";", " ", TRUE)), _xlpm.status_list, _xlfn.MAP(_xlpm.ids, _xlfn.LAMBDA(_xlpm.id, _xlfn.LET( _xlpm.lookup_val, _xlfn.XLOOKUP(_xlpm.id, 'Article list'!$A$2:$A$995, 'Article list'!$H$2:$H$995, ""), AND(_xlpm.lookup_val <> "", _xlpm.lookup_val <> 0) ) )), _xlpm.total_count, COUNTA(_xlpm.ids), _xlpm.excluded_count, SUM(--_xlpm.status_list), _xlfn.IFS( _xlpm.excluded_count = _xlpm.total_count, TRUE, _xlpm.excluded_count = 0, FALSE, TRUE, "partial" ) )} -> FALSE | C63: Mobility & Transport | D63: Public Transport | G63: Quantity | J63: Average one-way commute time within the five largest metropolitan areas; Urban Design | K63: ['Delphi method', 'GIS-based spatial analysis']
A64: 31 | B64: {=_xlfn.LET( _xlpm.ids, VALUE(_xlfn.TEXTSPLIT(SUBSTITUTE(A64,",",";"), ";", " ", TRUE)), _xlpm.status_list, _xlfn.MAP(_xlpm.ids, _xlfn.LAMBDA(_xlpm.id, _xlfn.LET( _xlpm.lookup_val, _xlfn.XLOOKUP(_xlpm.id, 'Article list'!$A$2:$A$995, 'Article list'!$H$2:$H$995, ""), AND(_xlpm.lookup_val <> "", _xlpm.lookup_val <> 0) ) )), _xlpm.total_count, COUNTA(_xlpm.ids), _xlpm.excluded_count, SUM(--_xlpm.status_list), _xlfn.IFS( _xlpm.excluded_count = _xlpm.total_count, TRUE, _xlpm.excluded_count = 0, FALSE, TRUE, "partial" ) )} -> FALSE | C64: Mobility & Transport | D64: Public Transport | G64: Quantity | J64: Number of buses per 10,000 people; Urban public service capacity | K64: ['Grey relational degree', 'Entropy-TOPSIS model']
A65: 6 | B65: {=_xlfn.LET( _xlpm.ids, VALUE(_xlfn.TEXTSPLIT(SUBSTITUTE(A65,",",";"), ";", " ", TRUE)), _xlpm.status_list, _xlfn.MAP(_xlpm.ids, _xlfn.LAMBDA(_xlpm.id, _xlfn.LET( _xlpm.lookup_val, _xlfn.XLOOKUP(_xlpm.id, 'Article list'!$A$2:$A$995, 'Article list'!$H$2:$H$995, ""), AND(_xlpm.lookup_val <> "", _xlpm.lookup_val <> 0) ) )), _xlpm.total_count, COUNTA(_xlpm.ids), _xlpm.excluded_count, SUM(--_xlpm.status_list), _xlfn.IFS( _xlpm.excluded_count = _xlpm.total_count, TRUE, _xlpm.excluded_count = 0, FALSE, TRUE, "partial" ) )} -> TRUE | C65: Mobility & Transport | D65: Active travel | J65: Speed Humps | K65: ['Delphi Process', 'Analytic Hierarchy Process'] | L65: Nueva clasificación
A66: 22 | B66: {=_xlfn.LET( _xlpm.ids, VALUE(_xlfn.TEXTSPLIT(SUBSTITUTE(A66,",",";"), ";", " ", TRUE)), _xlpm.status_list, _xlfn.MAP(_xlpm.ids, _xlfn.LAMBDA(_xlpm.id, _xlfn.LET( _xlpm.lookup_val, _xlfn.XLOOKUP(_xlpm.id, 'Article list'!$A$2:$A$995, 'Article list'!$H$2:$H$995, ""), AND(_xlpm.lookup_val <> "", _xlpm.lookup_val <> 0) ) )), _xlpm.total_count, COUNTA(_xlpm.ids), _xlpm.excluded_count, SUM(--_xlpm.status_list), _xlfn.IFS( _xlpm.excluded_count = _xlpm.total_count, TRUE, _xlpm.excluded_count = 0, FALSE, TRUE, "partial" ) )} -> FALSE | C66: Mobility & Transport | G66: Presence | J66: Traffic congestion | K66: ['N/A'] | M66: Accesibility lens??
A67: 6 | B67: {=_xlfn.LET( _xlpm.ids, VALUE(_xlfn.TEXTSPLIT(SUBSTITUTE(A67,",",";"), ";", " ", TRUE)), _xlpm.status_list, _xlfn.MAP(_xlpm.ids, _xlfn.LAMBDA(_xlpm.id, _xlfn.LET( _xlpm.lookup_val, _xlfn.XLOOKUP(_xlpm.id, 'Article list'!$A$2:$A$995, 'Article list'!$H$2:$H$995, ""), AND(_xlpm.lookup_val <> "", _xlpm.lookup_val <> 0) ) )), _xlpm.total_count, COUNTA(_xlpm.ids), _xlpm.excluded_count, SUM(--_xlpm.status_list), _xlfn.IFS( _xlpm.excluded_count = _xlpm.total_count, TRUE, _xlpm.excluded_count = 0, FALSE, TRUE, "partial" ) )} -> TRUE | C67: Mobility & Transport | D67: Active travel | J67: Traffic Control Devices/ Signals | K67: ['Delphi Process', 'Analytic Hierarchy Process'] | L67: Nueva clasificación
A68: 9 | B68: {=_xlfn.LET( _xlpm.ids, VALUE(_xlfn.TEXTSPLIT(SUBSTITUTE(A68,",",";"), ";", " ", TRUE)), _xlpm.status_list, _xlfn.MAP(_xlpm.ids, _xlfn.LAMBDA(_xlpm.id, _xlfn.LET( _xlpm.lookup_val, _xlfn.XLOOKUP(_xlpm.id, 'Article list'!$A$2:$A$995, 'Article list'!$H$2:$H$995, ""), AND(_xlpm.lookup_val <> "", _xlpm.lookup_val <> 0) ) )), _xlpm.total_count, COUNTA(_xlpm.ids), _xlpm.excluded_count, SUM(--_xlpm.status_list), _xlfn.IFS( _xlpm.excluded_count = _xlpm.total_count, TRUE, _xlpm.excluded_count = 0, FALSE, TRUE, "partial" ) )} -> TRUE | C68: Mobility & Transport | D68: Public transport | G68: Quality; Presence | J68: Transportation | K68: ['N/A']

Sheet Built Environment
A1: Article # | B1: Excluded? | C1: Domain | D1: Subdomain | E1: Indicator / Category | F1: Subject | G1: Specific Measure lens / Enfoque | H1: Scale | I1: Mexicali indicator | J1: Specific measures (from literature) | K1: Methods sub-indices/measures | L1: Notas | M1: Dudas | N1: Does it matter? | O1: Can we calculate this? Do we have data? | P1: What is the most pragmatic way of measuring it?
A2: 25;35 | B2: {=_xlfn.LET( _xlpm.ids, VALUE(_xlfn.TEXTSPLIT(SUBSTITUTE(A2,",",";"), ";", " ", TRUE)), _xlpm.status_list, _xlfn.MAP(_xlpm.ids, _xlfn.LAMBDA(_xlpm.id, _xlfn.LET( _xlpm.lookup_val, _xlfn.XLOOKUP(_xlpm.id, 'Article list'!$A$2:$A$995, 'Article list'!$H$2:$H$995, ""), AND(_xlpm.lookup_val <> "", _xlpm.lookup_val <> 0) ) )), _xlpm.total_count, COUNTA(_xlpm.ids), _xlpm.excluded_count, SUM(--_xlpm.status_list), _xlfn.IFS( _xlpm.excluded_count = _xlpm.total_count, TRUE, _xlpm.excluded_count = 0, FALSE, TRUE, "partial" ) )} -> partial | C2: Built Environment | D2: Green infrastructure | E2: Public open spaces | G2: Proximity | J2: Access to Urban Green Spaces | K2: 25: [Distance from residence calculated as the % of residents living within <500m, 500m-1km, 1-3 km and more 3 km from an UGS euclidean buffer 35: [Intercept survey around UGS] | L2: Access: The green spaces that were considered were only the publicly accessible ones that consist of parks,_x000D_gardens, and recreation areas managed by the municipalities._x000D_• Priority was given to amenities (e.g., green spaces still with some public amenities: walking paths, seating areas,_x000D_shaded zones, etc.) to ensure the usability of the spaces and a proper relationship with the public.
A3: 6 | B3: {=_xlfn.LET( _xlpm.ids, VALUE(_xlfn.TEXTSPLIT(SUBSTITUTE(A3,",",";"), ";", " ", TRUE)), _xlpm.status_list, _xlfn.MAP(_xlpm.ids, _xlfn.LAMBDA(_xlpm.id, _xlfn.LET( _xlpm.lookup_val, _xlfn.XLOOKUP(_xlpm.id, 'Article list'!$A$2:$A$995, 'Article list'!$H$2:$H$995, ""), AND(_xlpm.lookup_val <> "", _xlpm.lookup_val <> 0) ) )), _xlpm.total_count, COUNTA(_xlpm.ids), _xlpm.excluded_count, SUM(--_xlpm.status_list), _xlfn.IFS( _xlpm.excluded_count = _xlpm.total_count, TRUE, _xlpm.excluded_count = 0, FALSE, TRUE, "partial" ) )} -> TRUE | C3: Built Environment | J3: Advertisement Hoardings/ Bill boards | K3: ['Delphi Process', 'Analytic Hierarchy Process'] | M3: cómo se mide? indicator?
A4: 15 | B4: {=_xlfn.LET( _xlpm.ids, VALUE(_xlfn.TEXTSPLIT(SUBSTITUTE(A4,",",";"), ";", " ", TRUE)), _xlpm.status_list, _xlfn.MAP(_xlpm.ids, _xlfn.LAMBDA(_xlpm.id, _xlfn.LET( _xlpm.lookup_val, _xlfn.XLOOKUP(_xlpm.id, 'Article list'!$A$2:$A$995, 'Article list'!$H$2:$H$995, ""), AND(_xlpm.lookup_val <> "", _xlpm.lookup_val <> 0) ) )), _xlpm.total_count, COUNTA(_xlpm.ids), _xlpm.excluded_count, SUM(--_xlpm.status_list), _xlfn.IFS( _xlpm.excluded_count = _xlpm.total_count, TRUE, _xlpm.excluded_count = 0, FALSE, TRUE, "partial" ) )} -> FALSE | C4: Built Environment | D4: Green infrastructure | E4: Public open spaces | G4: Quantity | J4: Amount of recreational open space is sufficient | K4: ['Likert scale']
A5: 13 | B5: {=_xlfn.LET( _xlpm.ids, VALUE(_xlfn.TEXTSPLIT(SUBSTITUTE(A5,",",";"), ";", " ", TRUE)), _xlpm.status_list, _xlfn.MAP(_xlpm.ids, _xlfn.LAMBDA(_xlpm.id, _xlfn.LET( _xlpm.lookup_val, _xlfn.XLOOKUP(_xlpm.id, 'Article list'!$A$2:$A$995, 'Article list'!$H$2:$H$995, ""), AND(_xlpm.lookup_val <> "", _xlpm.lookup_val <> 0) ) )), _xlpm.total_count, COUNTA(_xlpm.ids), _xlpm.excluded_count, SUM(--_xlpm.status_list), _xlfn.IFS( _xlpm.excluded_count = _xlpm.total_count, TRUE, _xlpm.excluded_count = 0, FALSE, TRUE, "partial" ) )} -> FALSE | C5: Built Environment | D5: Green infrastructure | E5: Vegetation | G5: Quantity | J5: Annual mean Enhanced Vegetation Index | K5: ['Identification of measurable spatial indicators, how they can me calculated and monitored']
A6: 13 | B6: {=_xlfn.LET( _xlpm.ids, VALUE(_xlfn.TEXTSPLIT(SUBSTITUTE(A6,",",";"), ";", " ", TRUE)), _xlpm.status_list, _xlfn.MAP(_xlpm.ids, _xlfn.LAMBDA(_xlpm.id, _xlfn.LET( _xlpm.lookup_val, _xlfn.XLOOKUP(_xlpm.id, 'Article list'!$A$2:$A$995, 'Article list'!$H$2:$H$995, ""), AND(_xlpm.lookup_val <> "", _xlpm.lookup_val <> 0) ) )), _xlpm.total_count, COUNTA(_xlpm.ids), _xlpm.excluded_count, SUM(--_xlpm.status_list), _xlfn.IFS( _xlpm.excluded_count = _xlpm.total_count, TRUE, _xlpm.excluded_count = 0, FALSE, TRUE, "partial" ) )} -> FALSE | C6: Built Environment | D6: Green infrastructure | E6: Vegetation | G6: Quantity | J6: Annual mean Normalised Difference Vegetation Index | K6: ['Identification of measurable spatial indicators, how they can me calculated and monitored']
A7: 7 | B7: {=_xlfn.LET( _xlpm.ids, VALUE(_xlfn.TEXTSPLIT(SUBSTITUTE(A7,",",";"), ";", " ", TRUE)), _xlpm.status_list, _xlfn.MAP(_xlpm.ids, _xlfn.LAMBDA(_xlpm.id, _xlfn.LET( _xlpm.lookup_val, _xlfn.XLOOKUP(_xlpm.id, 'Article list'!$A$2:$A$995, 'Article list'!$H$2:$H$995, ""), AND(_xlpm.lookup_val <> "", _xlpm.lookup_val <> 0) ) )), _xlpm.total_count, COUNTA(_xlpm.ids), _xlpm.excluded_count, SUM(--_xlpm.status_list), _xlfn.IFS( _xlpm.excluded_count = _xlpm.total_count, TRUE, _xlpm.excluded_count = 0, FALSE, TRUE, "partial" ) )} -> TRUE | C7: Built Environment | E7: Pedestrian Infrastructure | G7: Quantity; Presence | J7: Availability of garbage collection services | K7: ['Likert scale']
A8: 27 | B8: {=_xlfn.LET( _xlpm.ids, VALUE(_xlfn.TEXTSPLIT(SUBSTITUTE(A8,",",";"), ";", " ", TRUE)), _xlpm.status_list, _xlfn.MAP(_xlpm.ids, _xlfn.LAMBDA(_xlpm.id, _xlfn.LET( _xlpm.lookup_val, _xlfn.XLOOKUP(_xlpm.id, 'Article list'!$A$2:$A$995, 'Article list'!$H$2:$H$995, ""), AND(_xlpm.lookup_val <> "", _xlpm.lookup_val <> 0) ) )), _xlpm.total_count, COUNTA(_xlpm.ids), _xlpm.excluded_count, SUM(--_xlpm.status_list), _xlfn.IFS( _xlpm.excluded_count = _xlpm.total_count, TRUE, _xlpm.excluded_count = 0, FALSE, TRUE, "partial" ) )} -> FALSE | C8: Built Environment | D8: Urban Morphology | E8: Land Use | G8: Presence | J8: Availability of mixed-use developments that blend housing with commercial and recreational spaces
A9: 18 | B9: {=_xlfn.LET( _xlpm.ids, VALUE(_xlfn.TEXTSPLIT(SUBSTITUTE(A9,",",";"), ";", " ", TRUE)), _xlpm.status_list, _xlfn.MAP(_xlpm.ids, _xlfn.LAMBDA(_xlpm.id, _xlfn.LET( _xlpm.lookup_val, _xlfn.XLOOKUP(_xlpm.id, 'Article list'!$A$2:$A$995, 'Article list'!$H$2:$H$995, ""), AND(_xlpm.lookup_val <> "", _xlpm.lookup_val <> 0) ) )), _xlpm.total_count, COUNTA(_xlpm.ids), _xlpm.excluded_count, SUM(--_xlpm.status_list), _xlfn.IFS( _xlpm.excluded_count = _xlpm.total_count, TRUE, _xlpm.excluded_count = 0, FALSE, TRUE, "partial" ) )} -> FALSE | C9: Built Environment | D9: Green infrastructure | E9: Public open spaces | G9: Accesibility | J9: Availability of open space | K9: ['Analytic Hierarchy Process (AHP)']
A10: 12 | B10: {=_xlfn.LET( _xlpm.ids, VALUE(_xlfn.TEXTSPLIT(SUBSTITUTE(A10,",",";"), ";", " ", TRUE)), _xlpm.status_list, _xlfn.MAP(_xlpm.ids, _xlfn.LAMBDA(_xlpm.id, _xlfn.LET( _xlpm.lookup_val, _xlfn.XLOOKUP(_xlpm.id, 'Article list'!$A$2:$A$995, 'Article list'!$H$2:$H$995, ""), AND(_xlpm.lookup_val <> "", _xlpm.lookup_val <> 0) ) )), _xlpm.total_count, COUNTA(_xlpm.ids), _xlpm.excluded_count, SUM(--_xlpm.status_list), _xlfn.IFS( _xlpm.excluded_count = _xlpm.total_count, TRUE, _xlpm.excluded_count = 0, FALSE, TRUE, "partial" ) )} -> FALSE | C10: Built Environment | D10: Green infrastructure | E10: Public open spaces | G10: Quantity | J10: Availability of outdoor play space | K10: ['Likert Scale Measurement', 'One-Way ANOVA', 'Descriptive Statistics', 'Post Hoc (Tukey) Test', 'Mann-Whitney U Test', 'Qualitative Thematic Analysis']
A11: 27 | B11: {=_xlfn.LET( _xlpm.ids, VALUE(_xlfn.TEXTSPLIT(SUBSTITUTE(A11,",",";"), ";", " ", TRUE)), _xlpm.status_list, _xlfn.MAP(_xlpm.ids, _xlfn.LAMBDA(_xlpm.id, _xlfn.LET( _xlpm.lookup_val, _xlfn.XLOOKUP(_xlpm.id, 'Article list'!$A$2:$A$995, 'Article list'!$H$2:$H$995, ""), AND(_xlpm.lookup_val <> "", _xlpm.lookup_val <> 0) ) )), _xlpm.total_count, COUNTA(_xlpm.ids), _xlpm.excluded_count, SUM(--_xlpm.status_list), _xlfn.IFS( _xlpm.excluded_count = _xlpm.total_count, TRUE, _xlpm.excluded_count = 0, FALSE, TRUE, "partial" ) )} -> FALSE | C11: Built Environment | D11: Housing | G11: Presence | J11: Availability of parking; Housing
A12: 18 | B12: {=_xlfn.LET( _xlpm.ids, VALUE(_xlfn.TEXTSPLIT(SUBSTITUTE(A12,",",";"), ";", " ", TRUE)), _xlpm.status_list, _xlfn.MAP(_xlpm.ids, _xlfn.LAMBDA(_xlpm.id, _xlfn.LET( _xlpm.lookup_val, _xlfn.XLOOKUP(_xlpm.id, 'Article list'!$A$2:$A$995, 'Article list'!$H$2:$H$995, ""), AND(_xlpm.lookup_val <> "", _xlpm.lookup_val <> 0) ) )), _xlpm.total_count, COUNTA(_xlpm.ids), _xlpm.excluded_count, SUM(--_xlpm.status_list), _xlfn.IFS( _xlpm.excluded_count = _xlpm.total_count, TRUE, _xlpm.excluded_count = 0, FALSE, TRUE, "partial" ) )} -> FALSE | C12: Built Environment | D12: Blue infrastructure | G12: Presence | J12: Availability of water areas | K12: ['Analytic Hierarchy Process (AHP)'] | M12: enfoque?
A13: 34 | B13: {=_xlfn.LET( _xlpm.ids, VALUE(_xlfn.TEXTSPLIT(SUBSTITUTE(A13,",",";"), ";", " ", TRUE)), _xlpm.status_list, _xlfn.MAP(_xlpm.ids, _xlfn.LAMBDA(_xlpm.id, _xlfn.LET( _xlpm.lookup_val, _xlfn.XLOOKUP(_xlpm.id, 'Article list'!$A$2:$A$995, 'Article list'!$H$2:$H$995, ""), AND(_xlpm.lookup_val <> "", _xlpm.lookup_val <> 0) ) )), _xlpm.total_count, COUNTA(_xlpm.ids), _xlpm.excluded_count, SUM(--_xlpm.status_list), _xlfn.IFS( _xlpm.excluded_count = _xlpm.total_count, TRUE, _xlpm.excluded_count = 0, FALSE, TRUE, "partial" ) )} -> FALSE | C13: Built Environment | D13: Green infrastructure | E13: Public open spaces | G13: Proximity | J13: Average distance from home to the nearest UGS | K13: [Intercept survey around UGS]
A14: 11 | B14: {=_xlfn.LET( _xlpm.ids, VALUE(_xlfn.TEXTSPLIT(SUBSTITUTE(A14,",",";"), ";", " ", TRUE)), _xlpm.status_list, _xlfn.MAP(_xlpm.ids, _xlfn.LAMBDA(_xlpm.id, _xlfn.LET( _xlpm.lookup_val, _xlfn.XLOOKUP(_xlpm.id, 'Article list'!$A$2:$A$995, 'Article list'!$H$2:$H$995, ""), AND(_xlpm.lookup_val <> "", _xlpm.lookup_val <> 0) ) )), _xlpm.total_count, COUNTA(_xlpm.ids), _xlpm.excluded_count, SUM(--_xlpm.status_list), _xlfn.IFS( _xlpm.excluded_count = _xlpm.total_count, TRUE, _xlpm.excluded_count = 0, FALSE, TRUE, "partial" ) )} -> TRUE | C14: Built Environment | D14: Urban Morphology | E14: Street Connectivity | G14: Proximity | J14: Average distance to the nearest open space and street corners | K14: ['Distance-based accessibility measures', 'Objective environmental and neighbourhood indicators', 'Resident perception surveys using 5-point Likert scales', 'Satisfaction-based scoring for each livability dimension']
A15: 6 | B15: {=_xlfn.LET( _xlpm.ids, VALUE(_xlfn.TEXTSPLIT(SUBSTITUTE(A15,",",";"), ";", " ", TRUE)), _xlpm.status_list, _xlfn.MAP(_xlpm.ids, _xlfn.LAMBDA(_xlpm.id, _xlfn.LET( _xlpm.lookup_val, _xlfn.XLOOKUP(_xlpm.id, 'Article list'!$A$2:$A$995, 'Article list'!$H$2:$H$995, ""), AND(_xlpm.lookup_val <> "", _xlpm.lookup_val <> 0) ) )), _xlpm.total_count, COUNTA(_xlpm.ids), _xlpm.excluded_count, SUM(--_xlpm.status_list), _xlfn.IFS( _xlpm.excluded_count = _xlpm.total_count, TRUE, _xlpm.excluded_count = 0, FALSE, TRUE, "partial" ) )} -> TRUE | C15: Built Environment | D15: Urban Morphology | E15: Block size | G15: Quantity | J15: Avg Building to Building Gap | K15: ['Delphi Process', 'Analytic Hierarchy Process'] | M15: Indicator
A16: 23 | B16: {=_xlfn.LET( _xlpm.ids, VALUE(_xlfn.TEXTSPLIT(SUBSTITUTE(A16,",",";"), ";", " ", TRUE)), _xlpm.status_list, _xlfn.MAP(_xlpm.ids, _xlfn.LAMBDA(_xlpm.id, _xlfn.LET( _xlpm.lookup_val, _xlfn.XLOOKUP(_xlpm.id, 'Article list'!$A$2:$A$995, 'Article list'!$H$2:$H$995, ""), AND(_xlpm.lookup_val <> "", _xlpm.lookup_val <> 0) ) )), _xlpm.total_count, COUNTA(_xlpm.ids), _xlpm.excluded_count, SUM(--_xlpm.status_list), _xlfn.IFS( _xlpm.excluded_count = _xlpm.total_count, TRUE, _xlpm.excluded_count = 0, FALSE, TRUE, "partial" ) )} -> FALSE | C16: Built Environment | D16: Urban morphology | E16: Buildings | G16: Quantity | J16: BF-2 Proportion and scale of space enclosed by buildings | K16: ['Design Analysis', 'Airflow simulations', 'Daylight simulations']
A17: 23 | B17: {=_xlfn.LET( _xlpm.ids, VALUE(_xlfn.TEXTSPLIT(SUBSTITUTE(A17,",",";"), ";", " ", TRUE)), _xlpm.status_list, _xlfn.MAP(_xlpm.ids, _xlfn.LAMBDA(_xlpm.id, _xlfn.LET( _xlpm.lookup_val, _xlfn.XLOOKUP(_xlpm.id, 'Article list'!$A$2:$A$995, 'Article list'!$H$2:$H$995, ""), AND(_xlpm.lookup_val <> "", _xlpm.lookup_val <> 0) ) )), _xlpm.total_count, COUNTA(_xlpm.ids), _xlpm.excluded_count, SUM(--_xlpm.status_list), _xlfn.IFS( _xlpm.excluded_count = _xlpm.total_count, TRUE, _xlpm.excluded_count = 0, FALSE, TRUE, "partial" ) )} -> FALSE | C17: Built Environment | D17: Urban morphology | E17: Buildings | G17: Quantity | J17: BF-3 Number of storeys/building height | K17: ['Design Analysis', 'Airflow simulations']
A18: 23 | B18: {=_xlfn.LET( _xlpm.ids, VALUE(_xlfn.TEXTSPLIT(SUBSTITUTE(A18,",",";"), ";", " ", TRUE)), _xlpm.status_list, _xlfn.MAP(_xlpm.ids, _xlfn.LAMBDA(_xlpm.id, _xlfn.LET( _xlpm.lookup_val, _xlfn.XLOOKUP(_xlpm.id, 'Article list'!$A$2:$A$995, 'Article list'!$H$2:$H$995, ""), AND(_xlpm.lookup_val <> "", _xlpm.lookup_val <> 0) ) )), _xlpm.total_count, COUNTA(_xlpm.ids), _xlpm.excluded_count, SUM(--_xlpm.status_list), _xlfn.IFS( _xlpm.excluded_count = _xlpm.total_count, TRUE, _xlpm.excluded_count = 0, FALSE, TRUE, "partial" ) )} -> FALSE | C18: Built Environment | D18: Urban morphology | E18: Buildings | G18: Quantity | J18: BF-4 Difference in building height in neighbourhood | K18: ['Design Analysis', 'Airflow simulations']
A19: 23 | B19: {=_xlfn.LET( _xlpm.ids, VALUE(_xlfn.TEXTSPLIT(SUBSTITUTE(A19,",",";"), ";", " ", TRUE)), _xlpm.status_list, _xlfn.MAP(_xlpm.ids, _xlfn.LAMBDA(_xlpm.id, _xlfn.LET( _xlpm.lookup_val, _xlfn.XLOOKUP(_xlpm.id, 'Article list'!$A$2:$A$995, 'Article list'!$H$2:$H$995, ""), AND(_xlpm.lookup_val <> "", _xlpm.lookup_val <> 0) ) )), _xlpm.total_count, COUNTA(_xlpm.ids), _xlpm.excluded_count, SUM(--_xlpm.status_list), _xlfn.IFS( _xlpm.excluded_count = _xlpm.total_count, TRUE, _xlpm.excluded_count = 0, FALSE, TRUE, "partial" ) )} -> FALSE | C19: Built Environment | D19: Urban morphology | E19: Land use | G19: Quantity | J19: BF-5 Provision of mixed-use buildings | K19: ['Field observation']
A20: 23 | B20: {=_xlfn.LET( _xlpm.ids, VALUE(_xlfn.TEXTSPLIT(SUBSTITUTE(A20,",",";"), ";", " ", TRUE)), _xlpm.status_list, _xlfn.MAP(_xlpm.ids, _xlfn.LAMBDA(_xlpm.id, _xlfn.LET( _xlpm.lookup_val, _xlfn.XLOOKUP(_xlpm.id, 'Article list'!$A$2:$A$995, 'Article list'!$H$2:$H$995, ""), AND(_xlpm.lookup_val <> "", _xlpm.lookup_val <> 0) ) )), _xlpm.total_count, COUNTA(_xlpm.ids), _xlpm.excluded_count, SUM(--_xlpm.status_list), _xlfn.IFS( _xlpm.excluded_count = _xlpm.total_count, TRUE, _xlpm.excluded_count = 0, FALSE, TRUE, "partial" ) )} -> FALSE | C20: Built Environment | D20: Urban morphology | E20: Buildings | G20: Quality | J20: BF-6 Colour and material harmony | K20: ['Field observation', 'Questionnaire']
A21: 23 | B21: {=_xlfn.LET( _xlpm.ids, VALUE(_xlfn.TEXTSPLIT(SUBSTITUTE(A21,",",";"), ";", " ", TRUE)), _xlpm.status_list, _xlfn.MAP(_xlpm.ids, _xlfn.LAMBDA(_xlpm.id, _xlfn.LET( _xlpm.lookup_val, _xlfn.XLOOKUP(_xlpm.id, 'Article list'!$A$2:$A$995, 'Article list'!$H$2:$H$995, ""), AND(_xlpm.lookup_val <> "", _xlpm.lookup_val <> 0) ) )), _xlpm.total_count, COUNTA(_xlpm.ids), _xlpm.excluded_count, SUM(--_xlpm.status_list), _xlfn.IFS( _xlpm.excluded_count = _xlpm.total_count, TRUE, _xlpm.excluded_count = 0, FALSE, TRUE, "partial" ) )} -> FALSE | C21: Built Environment | D21: Urban morphology | E21: Buildings | G21: Quantity | J21: BF-7 Building morphology and arrangement | K21: ['Design Analysis', 'Airflow simulations']
A22: 23 | B22: {=_xlfn.LET( _xlpm.ids, VALUE(_xlfn.TEXTSPLIT(SUBSTITUTE(A22,",",";"), ";", " ", TRUE)), _xlpm.status_list, _xlfn.MAP(_xlpm.ids, _xlfn.LAMBDA(_xlpm.id, _xlfn.LET( _xlpm.lookup_val, _xlfn.XLOOKUP(_xlpm.id, 'Article list'!$A$2:$A$995, 'Article list'!$H$2:$H$995, ""), AND(_xlpm.lookup_val <> "", _xlpm.lookup_val <> 0) ) )), _xlpm.total_count, COUNTA(_xlpm.ids), _xlpm.excluded_count, SUM(--_xlpm.status_list), _xlfn.IFS( _xlpm.excluded_count = _xlpm.total_count, TRUE, _xlpm.excluded_count = 0, FALSE, TRUE, "partial" ) )} -> FALSE | C22: Built Environment | D22: Urban morphology | E22: Street connectivity | G22: Quality | J22: BF-8 Community design: configuration of neighbourhood centre | K22: ['Design Analysis', 'Airflow simulations']
A23: 23 | B23: {=_xlfn.LET( _xlpm.ids, VALUE(_xlfn.TEXTSPLIT(SUBSTITUTE(A23,",",";"), ";", " ", TRUE)), _xlpm.status_list, _xlfn.MAP(_xlpm.ids, _xlfn.LAMBDA(_xlpm.id, _xlfn.LET( _xlpm.lookup_val, _xlfn.XLOOKUP(_xlpm.id, 'Article list'!$A$2:$A$995, 'Article list'!$H$2:$H$995, ""), AND(_xlpm.lookup_val <> "", _xlpm.lookup_val <> 0) ) )), _xlpm.total_count, COUNTA(_xlpm.ids), _xlpm.excluded_count, SUM(--_xlpm.status_list), _xlfn.IFS( _xlpm.excluded_count = _xlpm.total_count, TRUE, _xlpm.excluded_count = 0, FALSE, TRUE, "partial" ) )} -> FALSE | C23: Built Environment | D23: Urban morphology | E23: Land use | G23: Quantity | J23: BF-9 Houses plots arranged to face front sides and parklands | K23: ['Design Analysis', 'Field observation', 'Airflow simulations']
A24: 23 | B24: {=_xlfn.LET( _xlpm.ids, VALUE(_xlfn.TEXTSPLIT(SUBSTITUTE(A24,",",";"), ";", " ", TRUE)), _xlpm.status_list, _xlfn.MAP(_xlpm.ids, _xlfn.LAMBDA(_xlpm.id, _xlfn.LET( _xlpm.lookup_val, _xlfn.XLOOKUP(_xlpm.id, 'Article list'!$A$2:$A$995, 'Article list'!$H$2:$H$995, ""), AND(_xlpm.lookup_val <> "", _xlpm.lookup_val <> 0) ) )), _xlpm.total_count, COUNTA(_xlpm.ids), _xlpm.excluded_count, SUM(--_xlpm.status_list), _xlfn.IFS( _xlpm.excluded_count = _xlpm.total_count, TRUE, _xlpm.excluded_count = 0, FALSE, TRUE, "partial" ) )} -> FALSE | C24: Built Environment | D24: Urban morphology | E24: Land use | G24: Quantity | J24: BF10 Different residential plot sizes | K24: ['Design Analysis']
A25: 23 | B25: {=_xlfn.LET( _xlpm.ids, VALUE(_xlfn.TEXTSPLIT(SUBSTITUTE(A25,",",";"), ";", " ", TRUE)), _xlpm.status_list, _xlfn.MAP(_xlpm.ids, _xlfn.LAMBDA(_xlpm.id, _xlfn.LET( _xlpm.lookup_val, _xlfn.XLOOKUP(_xlpm.id, 'Article list'!$A$2:$A$995, 'Article list'!$H$2:$H$995, ""), AND(_xlpm.lookup_val <> "", _xlpm.lookup_val <> 0) ) )), _xlpm.total_count, COUNTA(_xlpm.ids), _xlpm.excluded_count, SUM(--_xlpm.status_list), _xlfn.IFS( _xlpm.excluded_count = _xlpm.total_count, TRUE, _xlpm.excluded_count = 0, FALSE, TRUE, "partial" ) )} -> FALSE | C25: Built Environment | D25: Urban morphology | G25: Quality | J25: BF11 Good views through the plot | K25: ['Field observation']
A26: 23 | B26: {=_xlfn.LET( _xlpm.ids, VALUE(_xlfn.TEXTSPLIT(SUBSTITUTE(A26,",",";"), ";", " ", TRUE)), _xlpm.status_list, _xlfn.MAP(_xlpm.ids, _xlfn.LAMBDA(_xlpm.id, _xlfn.LET( _xlpm.lookup_val, _xlfn.XLOOKUP(_xlpm.id, 'Article list'!$A$2:$A$995, 'Article list'!$H$2:$H$995, ""), AND(_xlpm.lookup_val <> "", _xlpm.lookup_val <> 0) ) )), _xlpm.total_count, COUNTA(_xlpm.ids), _xlpm.excluded_count, SUM(--_xlpm.status_list), _xlfn.IFS( _xlpm.excluded_count = _xlpm.total_count, TRUE, _xlpm.excluded_count = 0, FALSE, TRUE, "partial" ) )} -> FALSE | C26: Built Environment | D26: Urban morphology | E26: Land use | G26: Diversity | J26: BF12 Varying density near activity centre of a neighbourhood | K26: ['Design Analysis', 'Field observation']
A27: 23 | B27: {=_xlfn.LET( _xlpm.ids, VALUE(_xlfn.TEXTSPLIT(SUBSTITUTE(A27,",",";"), ";", " ", TRUE)), _xlpm.status_list, _xlfn.MAP(_xlpm.ids, _xlfn.LAMBDA(_xlpm.id, _xlfn.LET( _xlpm.lookup_val, _xlfn.XLOOKUP(_xlpm.id, 'Article list'!$A$2:$A$995, 'Article list'!$H$2:$H$995, ""), AND(_xlpm.lookup_val <> "", _xlpm.lookup_val <> 0) ) )), _xlpm.total_count, COUNTA(_xlpm.ids), _xlpm.excluded_count, SUM(--_xlpm.status_list), _xlfn.IFS( _xlpm.excluded_count = _xlpm.total_count, TRUE, _xlpm.excluded_count = 0, FALSE, TRUE, "partial" ) )} -> FALSE | C27: Built Environment | D27: Urban morphology | E27: Buildings | G27: Quantity | J27: BF13 Compactness ratio: ratio of area and perimeter of an urban form | K27: ['Design Analysis', 'Airflow simulations']
A28: 23 | B28: {=_xlfn.LET( _xlpm.ids, VALUE(_xlfn.TEXTSPLIT(SUBSTITUTE(A28,",",";"), ";", " ", TRUE)), _xlpm.status_list, _xlfn.MAP(_xlpm.ids, _xlfn.LAMBDA(_xlpm.id, _xlfn.LET( _xlpm.lookup_val, _xlfn.XLOOKUP(_xlpm.id, 'Article list'!$A$2:$A$995, 'Article list'!$H$2:$H$995, ""), AND(_xlpm.lookup_val <> "", _xlpm.lookup_val <> 0) ) )), _xlpm.total_count, COUNTA(_xlpm.ids), _xlpm.excluded_count, SUM(--_xlpm.status_list), _xlfn.IFS( _xlpm.excluded_count = _xlpm.total_count, TRUE, _xlpm.excluded_count = 0, FALSE, TRUE, "partial" ) )} -> FALSE | C28: Built Environment | D28: Urban morphology | E28: Buildings | G28: Quantity | J28: BF14 Shape index: ratio of perimeter to area | K28: ['Design Analysis', 'Airflow simulations']
A29: 23 | B29: {=_xlfn.LET( _xlpm.ids, VALUE(_xlfn.TEXTSPLIT(SUBSTITUTE(A29,",",";"), ";", " ", TRUE)), _xlpm.status_list, _xlfn.MAP(_xlpm.ids, _xlfn.LAMBDA(_xlpm.id, _xlfn.LET( _xlpm.lookup_val, _xlfn.XLOOKUP(_xlpm.id, 'Article list'!$A$2:$A$995, 'Article list'!$H$2:$H$995, ""), AND(_xlpm.lookup_val <> "", _xlpm.lookup_val <> 0) ) )), _xlpm.total_count, COUNTA(_xlpm.ids), _xlpm.excluded_count, SUM(--_xlpm.status_list), _xlfn.IFS( _xlpm.excluded_count = _xlpm.total_count, TRUE, _xlpm.excluded_count = 0, FALSE, TRUE, "partial" ) )} -> FALSE | C29: Built Environment | D29: Urban morphology | E29: Buildings | G29: Quantity | J29: BF15 Slenderness ratio: ratio of height and width of shape of an urban form | K29: ['Design Analysis', 'Airflow simulations']
A30: 23 | B30: {=_xlfn.LET( _xlpm.ids, VALUE(_xlfn.TEXTSPLIT(SUBSTITUTE(A30,",",";"), ";", " ", TRUE)), _xlpm.status_list, _xlfn.MAP(_xlpm.ids, _xlfn.LAMBDA(_xlpm.id, _xlfn.LET( _xlpm.lookup_val, _xlfn.XLOOKUP(_xlpm.id, 'Article list'!$A$2:$A$995, 'Article list'!$H$2:$H$995, ""), AND(_xlpm.lookup_val <> "", _xlpm.lookup_val <> 0) ) )), _xlpm.total_count, COUNTA(_xlpm.ids), _xlpm.excluded_count, SUM(--_xlpm.status_list), _xlfn.IFS( _xlpm.excluded_count = _xlpm.total_count, TRUE, _xlpm.excluded_count = 0, FALSE, TRUE, "partial" ) )} -> FALSE | C30: Built Environment | D30: Urban morphology | E30: Buildings | G30: Quantity | J30: BF16 Fractalness: measure of the degree of self-similar repetitiveness of an element in housing form layout or the complexity of a spatial structure | K30: ['Design Analysis', 'Airflow simulations']
A31: 23 | B31: {=_xlfn.LET( _xlpm.ids, VALUE(_xlfn.TEXTSPLIT(SUBSTITUTE(A31,",",";"), ";", " ", TRUE)), _xlpm.status_list, _xlfn.MAP(_xlpm.ids, _xlfn.LAMBDA(_xlpm.id, _xlfn.LET( _xlpm.lookup_val, _xlfn.XLOOKUP(_xlpm.id, 'Article list'!$A$2:$A$995, 'Article list'!$H$2:$H$995, ""), AND(_xlpm.lookup_val <> "", _xlpm.lookup_val <> 0) ) )), _xlpm.total_count, COUNTA(_xlpm.ids), _xlpm.excluded_count, SUM(--_xlpm.status_list), _xlfn.IFS( _xlpm.excluded_count = _xlpm.total_count, TRUE, _xlpm.excluded_count = 0, FALSE, TRUE, "partial" ) )} -> FALSE | C31: Built Environment | D31: Urban morphology | E31: Buildings | G31: Quantity | J31: BF17 Brokenness: measure of the degree to which an urban form can be fragmented. | K31: ['Design Analysis', 'Airflow simulations']
A32: 23 | B32: {=_xlfn.LET( _xlpm.ids, VALUE(_xlfn.TEXTSPLIT(SUBSTITUTE(A32,",",";"), ";", " ", TRUE)), _xlpm.status_list, _xlfn.MAP(_xlpm.ids, _xlfn.LAMBDA(_xlpm.id, _xlfn.LET( _xlpm.lookup_val, _xlfn.XLOOKUP(_xlpm.id, 'Article list'!$A$2:$A$995, 'Article list'!$H$2:$H$995, ""), AND(_xlpm.lookup_val <> "", _xlpm.lookup_val <> 0) ) )), _xlpm.total_count, COUNTA(_xlpm.ids), _xlpm.excluded_count, SUM(--_xlpm.status_list), _xlfn.IFS( _xlpm.excluded_count = _xlpm.total_count, TRUE, _xlpm.excluded_count = 0, FALSE, TRUE, "partial" ) )} -> FALSE | C32: Built Environment | D32: Urban morphology | E32: Buildings | G32: Quantity | J32: BF19 Form factor: ratio of surface area to the volume of urban form | K32: ['Design Analysis', 'Airflow simulations']
A33: 23 | B33: {=_xlfn.LET( _xlpm.ids, VALUE(_xlfn.TEXTSPLIT(SUBSTITUTE(A33,",",";"), ";", " ", TRUE)), _xlpm.status_list, _xlfn.MAP(_xlpm.ids, _xlfn.LAMBDA(_xlpm.id, _xlfn.LET( _xlpm.lookup_val, _xlfn.XLOOKUP(_xlpm.id, 'Article list'!$A$2:$A$995, 'Article list'!$H$2:$H$995, ""), AND(_xlpm.lookup_val <> "", _xlpm.lookup_val <> 0) ) )), _xlpm.total_count, COUNTA(_xlpm.ids), _xlpm.excluded_count, SUM(--_xlpm.status_list), _xlfn.IFS( _xlpm.excluded_count = _xlpm.total_count, TRUE, _xlpm.excluded_count = 0, FALSE, TRUE, "partial" ) )} -> FALSE | C33: Built Environment | D33: Green Infrastructure | E33: Public open spaces | G33: Quantity; Quality | J33: BF20 Courtyard design, size and type | K33: ['Design Analysis', 'Airflow simulations']
A34: 6 | B34: {=_xlfn.LET( _xlpm.ids, VALUE(_xlfn.TEXTSPLIT(SUBSTITUTE(A34,",",";"), ";", " ", TRUE)), _xlpm.status_list, _xlfn.MAP(_xlpm.ids, _xlfn.LAMBDA(_xlpm.id, _xlfn.LET( _xlpm.lookup_val, _xlfn.XLOOKUP(_xlpm.id, 'Article list'!$A$2:$A$995, 'Article list'!$H$2:$H$995, ""), AND(_xlpm.lookup_val <> "", _xlpm.lookup_val <> 0) ) )), _xlpm.total_count, COUNTA(_xlpm.ids), _xlpm.excluded_count, SUM(--_xlpm.status_list), _xlfn.IFS( _xlpm.excluded_count = _xlpm.total_count, TRUE, _xlpm.excluded_count = 0, FALSE, TRUE, "partial" ) )} -> TRUE | C34: Built Environment | D34: Urban Morphology | E34: Block size | G34: Quantity | J34: Block Size | K34: ['Delphi Process', 'Analytic Hierarchy Process']
A35: 2 | B35: {=_xlfn.LET( _xlpm.ids, VALUE(_xlfn.TEXTSPLIT(SUBSTITUTE(A35,",",";"), ";", " ", TRUE)), _xlpm.status_list, _xlfn.MAP(_xlpm.ids, _xlfn.LAMBDA(_xlpm.id, _xlfn.LET( _xlpm.lookup_val, _xlfn.XLOOKUP(_xlpm.id, 'Article list'!$A$2:$A$995, 'Article list'!$H$2:$H$995, ""), AND(_xlpm.lookup_val <> "", _xlpm.lookup_val <> 0) ) )), _xlpm.total_count, COUNTA(_xlpm.ids), _xlpm.excluded_count, SUM(--_xlpm.status_list), _xlfn.IFS( _xlpm.excluded_count = _xlpm.total_count, TRUE, _xlpm.excluded_count = 0, FALSE, TRUE, "partial" ) )} -> TRUE | C35: Built Environment | D35: Urban Morphology | J35: Building footprint | K35: ['Analytical hierarchy process']
A36: 6 | B36: {=_xlfn.LET( _xlpm.ids, VALUE(_xlfn.TEXTSPLIT(SUBSTITUTE(A36,",",";"), ";", " ", TRUE)), _xlpm.status_list, _xlfn.MAP(_xlpm.ids, _xlfn.LAMBDA(_xlpm.id, _xlfn.LET( _xlpm.lookup_val, _xlfn.XLOOKUP(_xlpm.id, 'Article list'!$A$2:$A$995, 'Article list'!$H$2:$H$995, ""), AND(_xlpm.lookup_val <> "", _xlpm.lookup_val <> 0) ) )), _xlpm.total_count, COUNTA(_xlpm.ids), _xlpm.excluded_count, SUM(--_xlpm.status_list), _xlfn.IFS( _xlpm.excluded_count = _xlpm.total_count, TRUE, _xlpm.excluded_count = 0, FALSE, TRUE, "partial" ) )} -> TRUE | C36: Built Environment | D36: Personal Safety | J36: building frontage/ Windows Facing street/ Façade | K36: ['Delphi Process', 'Analytic Hierarchy Process'] | L36: Eyes on the street
A37: 6 | B37: {=_xlfn.LET( _xlpm.ids, VALUE(_xlfn.TEXTSPLIT(SUBSTITUTE(A37,",",";"), ";", " ", TRUE)), _xlpm.status_list, _xlfn.MAP(_xlpm.ids, _xlfn.LAMBDA(_xlpm.id, _xlfn.LET( _xlpm.lookup_val, _xlfn.XLOOKUP(_xlpm.id, 'Article list'!$A$2:$A$995, 'Article list'!$H$2:$H$995, ""), AND(_xlpm.lookup_val <> "", _xlpm.lookup_val <> 0) ) )), _xlpm.total_count, COUNTA(_xlpm.ids), _xlpm.excluded_count, SUM(--_xlpm.status_list), _xlfn.IFS( _xlpm.excluded_count = _xlpm.total_count, TRUE, _xlpm.excluded_count = 0, FALSE, TRUE, "partial" ) )} -> TRUE | C37: Built Environment | D37: Urban Morphology | G37: Quantity | J37: Building Height | K37: ['Delphi Process', 'Analytic Hierarchy Process'] | M37: Indicator
A38: 1; 6 | B38: {=_xlfn.LET( _xlpm.ids, VALUE(_xlfn.TEXTSPLIT(SUBSTITUTE(A38,",",";"), ";", " ", TRUE)), _xlpm.status_list, _xlfn.MAP(_xlpm.ids, _xlfn.LAMBDA(_xlpm.id, _xlfn.LET( _xlpm.lookup_val, _xlfn.XLOOKUP(_xlpm.id, 'Article list'!$A$2:$A$995, 'Article list'!$H$2:$H$995, ""), AND(_xlpm.lookup_val <> "", _xlpm.lookup_val <> 0) ) )), _xlpm.total_count, COUNTA(_xlpm.ids), _xlpm.excluded_count, SUM(--_xlpm.status_list), _xlfn.IFS( _xlpm.excluded_count = _xlpm.total_count, TRUE, _xlpm.excluded_count = 0, FALSE, TRUE, "partial" ) )} -> TRUE | C38: Built Environment | D38: Urban Morphology | E38: Block size | G38: Density | J38: Built up Density | K38: 1: ['Delphi', "Kendall's coefficient", "Cronbach's alpha value"] 6: ['Delphi Process', 'Analytic Hierarchy Process'] | M38: Indicator
A39: 13 | B39: {=_xlfn.LET( _xlpm.ids, VALUE(_xlfn.TEXTSPLIT(SUBSTITUTE(A39,",",";"), ";", " ", TRUE)), _xlpm.status_list, _xlfn.MAP(_xlpm.ids, _xlfn.LAMBDA(_xlpm.id, _xlfn.LET( _xlpm.lookup_val, _xlfn.XLOOKUP(_xlpm.id, 'Article list'!$A$2:$A$995, 'Article list'!$H$2:$H$995, ""), AND(_xlpm.lookup_val <> "", _xlpm.lookup_val <> 0) ) )), _xlpm.total_count, COUNTA(_xlpm.ids), _xlpm.excluded_count, SUM(--_xlpm.status_list), _xlfn.IFS( _xlpm.excluded_count = _xlpm.total_count, TRUE, _xlpm.excluded_count = 0, FALSE, TRUE, "partial" ) )} -> FALSE | C39: Built Environment | D39: Blue infrastructure | E39: Blue infrastructure | G39: Presence; Proximity | J39: Canal water storage sample locations | K39: ['Identification of measurable spatial indicators, how they can me calculated and monitored']
